Workbook

Sheet README
A1: 4ORM FINANCE
A2: Institutional Settlement Layer | 5-Year Financial Escalation Model
A3: KCS Capital | July 2026 | All Figures in Canadian Dollars (CAD)
B5: ABOUT THIS MODEL
B6: This workbook models the 5-year financial trajectory for 4ORM Finance, Canada's institutional settlement layer for tokenized real-world assets.
B7: The platform is being built to serve targeted Alberta and BC financial institutions. Modeled counterparties include ATB Financial, Bow Valley Credit Union, Servus Credit Union, and Vancity Credit Union as illustrative examples of the institution profile 4orm is designed to serve. No partnerships are yet in place; two Memoranda of Understanding are targeted during the Phase 1 pre-seed period.
B8: Revenue model validated against ATB Financial FY2025 Annual Report ($43.3B deposits, $37.2B AUA, $29.1B lending).
B9: Six revenue streams + (Reserved 6th Stream). Modeled ATB revenue in 2028 (post-onboarding) approximately $5.2M (H1 at 50% ramp); approximately $7M at full modeled capacity.
B10: V10 DATA ROOM EDITION: Semi-annual periods (H1/H2). ALL calculations are Excel formulas. SPEER toggle wired at Control Panel B22.
B11: ATB + BVCU modeled to start 2028, Servus + Vancity modeled to start 2029. Change Control Panel inputs to stress test scenarios.
B13: V10 CHANGES FROM V9
B14: SPEER Engineering toggle added (Control Panel B22): when ON, SPEER contracted phases 1-3 are active ($317,304 CAD contract) and internal build lines suppressed to avoid double-counting
B15: SPEER payment schedule updated: deposit shifts to September 1, 2026 (aligning with pre-seed close)
B16: Team rates updated: Chad $8K/mo, Kevin $4K/mo (CMO), CTO $15K/mo (Phase 1 hire), Fractional CFO $6K/mo, Bruce $6K/mo, Dean $5K/mo
B17: Zed Head Architect, Smart Contract Dev, Backend Dev all full-time from H2 2026 (partial-period ramp)
... B93: Date: July 3, 2026

Sheet Control Panel
A1: 4ORM FINANCE - SCENARIO CONTROL PANEL
A2: Set toggles to 1 (ON) or 0 (OFF) - all sheets reference these cells | Yellow cells = editable inputs
A4: Scenario / Vertical | B4: Toggle (1=ON, 0=OFF) | C4: Status | D4: Description
A5: REVENUE STREAMS
A6: Settlement Fees (1.5 bps) | B6: 1 | C6: =IF(B6=1,"ON","OFF") | D6: Deposits x 5x turnover x 1% tokenized x 1.5 bps - 4ORM 30%
A7: Issuance Fees (0.5%) | B7: 1 | C7: =IF(B7=1,"ON","OFF") | D7: Lending x 1.5% tokenized x 0.5% - 4ORM 60%
A8: Trading Fees (5 bps) | B8: 1 | C8: =IF(B8=1,"ON","OFF") | D8: 40% of issuance volume x 5 bps - 4ORM 100%
A9: Custody Fees (30 bps) | B9: 1 | C9: =IF(B9=1,"ON","OFF") | D9: AUA x 1.5% tokenized x 30 bps - 4ORM 40%
A10: SaaS + APIs | B10: 1 | C10: =IF(B10=1,"ON","OFF") | D10: Enterprise clients x $25K/mo - 4ORM 80%
A11: (reserved slot - vertical removed) | B11: 0 | C11: =IF(B11=1,"ON","OFF") | D11: Removed from v10 scope
A13: PARTNER INSTITUTIONS
A14: ATB Financial (Anchor) | B14: 1 | C14: =IF(B14=1,"ON","OFF") | D14: $43.3B deposits - starts 2027 (anchor)
A15: Bow Valley Credit Union | B15: 1 | C15: =IF(B15=1,"ON","OFF") | D15: ~$2B est. - starts 2027
A16: Vancity Credit Union | B16: 1 | C16: =IF(B16=1,"ON","OFF") | D16: $35.5B AUA - starts 2028
A17: Servus Credit Union | B17: 1 | C17: =IF(B17=1,"ON","OFF") | D17: $29.3B assets - starts 2028
A19: BUILD SCENARIOS
A20: platform Build | B20: 1 | C20: =IF(B20=1,"ON","OFF") | D20: MASTER SWITCH: 1 = the platform Build flows to P&L; 0 = Traditional. ~35% headcount savings via developer tooling
A21: Traditional Build | B21: =1-B20 | C21: =IF(B21=1,"ON","OFF") | D21: Full team, no developer tooling - compare side-by-side
A22: SPEER Engineering (External) | B22: 1 | C22: =IF(B22=1,"ON","OFF") | D22: Gates SPEER phases 1-3 + HST on DevEx sheet. Total $317,304 CAD; deposit Sept 1 2026 + 12 monthly installments through Sept 2027
A23: SPEER Fractional CTO | B23: 0 | C23: =IF(B23=1,"ON","OFF") | D23: Gates SPEER Fractional CTO row on DevEx ($18K/half)
A24: SPEER Grants/SR&ED Support | B24: 1 | C24: =IF(B24=1,"ON","OFF") | D24: Gates SR&ED credit line in OpEx (negative expense)
A26: MACRO ASSUMPTIONS
A27: Deposit Tokenization Rate | B27: 0.01 | C27: 1.0% | D27: Percentage of FI deposits tokenized on platform
A28: Issuance/Custody Tokenization Rate | B28: 0.015 | C28: 1.5% | D28: Percentage of lending/AUA tokenized
A29: Deposit Turnover Multiplier | B29: 5 | C29: 5x | D29: Annual turnover on tokenized deposits (settlement volume)
A30: Annual Growth Rate | B30: 0.04 | C30: 4.0% | D30: Conservative YoY growth in volume + adoption
A31: ATB Deposit Base ($B) | B31: 43.3 | C31: $43.3B | D31: Source: ATB Annual Report FY2025
A32: ATB Lending Base ($B) | B32: 29.1 | C32: $29.1B | D32: Source: ATB Annual Report FY2025
A33: ATB AUA ($B) | B33: 37.2 | C33: $37.2B | D33: Source: ATB Annual Report FY2025
A34: Enterprise Clients (ATB) | B34: 20 | C34: 20 | D34: Enterprise SaaS clients at ATB
A35: SaaS Price per Client ($/mo) | B35: 25000 | C35: $25K/mo | D35: Monthly SaaS + API licensing fee
A36: Salary Escalation | B36: 0.03 | C36: 3.0% | D36: Standard Canadian CPI-linked
A37: Infrastructure Escalation | B37: 0.12 | C37: 12.0% | D37: Cloud/blockchain scales with usage
A39: FEE RATES & SPLITS
A40: Stream | B40: Fee Rate | C40: 4ORM Split | D40: Description
A41: Settlement | B41: 0.00015 | C41: 0.3 | D41: 1.5 bps of settlement volume
A42: Issuance | B42: 0.005 | C42: 0.6 | D42: 0.5% of issuance volume
A43: Trading | B43: 0.0005 | C43: 1 | D43: 5 bps of trading volume
A44: Custody | B44: 0.003 | C44: 0.4 | D44: 30 bps of custody AUA
A45: SaaS | B45: =B35*12 | C45: 0.8 | D45: Annual per enterprise client
A47: FI BASE DATA
A48: Institution | B48: Deposits $M | C48: Lending $M | D48: AUA $M | E48: Enterprise Clients | F48: Start Period
A49: ATB Financial | B49: 43332 | C49: 29100 | D49: 37166 | E49: 20 | F49: 1
A50: Bow Valley CU | B50: 2000 | C50: 1200 | D50: 1500 | E50: 3 | F50: 1
A51: Vancity CU | B51: 25000 | C51: 18000 | D51: 30000 | E51: 12 | F51: 3
A52: Servus CU | B52: 20000 | C52: 15000 | D52: 20000 | E52: 10 | F52: 3
A54: ONBOARDING RAMP SCHEDULE (Semi-Annual)
A55: FI | B55: H2 2026 | C55: H1 2027 | D55: H2 2027 | E55: H1 2028 | F55: H2 2028 | G55: H1 2029 | H55: H2 2029 | I55: H1 2030 | J55: H2 2030 | K55: H1 2031 | L55: H2 2031
A56: ATB Financial | B56: 0 | C56: 0 | D56: 0 | E56: 0.5 | F56: 1 | G56: 1 | H56: 1 | I56: 1 | J56: 1 | K56: 1 | L56: 1
A57: Bow Valley CU | B57: 0 | C57: 0 | D57: 0 | E57: 0.5 | F57: 1 | G57: 1 | H57: 1 | I57: 1 | J57: 1 | K57: 1 | L57: 1
A58: Vancity CU | B58: 0 | C58: 0 | D58: 0 | E58: 0 | F58: 0 | G58: 0.5 | H58: 1 | I58: 1 | J58: 1 | K58: 1 | L58: 1
A59: Servus CU | B59: 0 | C59: 0 | D59: 0 | E59: 0 | F59: 0 | G59: 0.5 | H59: 1 | I59: 1 | J59: 1 | K59: 1 | L59: 1
A61: ADDITIONAL PARAMETERS
A62: Trading Volume % of Issuance | B62: 0.4 | C62: Trading Vol %
A63: (reserved) | B63: 0
A65: (reserved - TAM vertical removed)
A79: M2 MONEY SUPPLY GROWTH SCENARIOS
A80: Canada M2 YoY growth (Jan 2026): 3.8%. ATB deposits grew 6.8% FY2025. Historical M2 correlation ~0.75 for ATB.
A81: Scenario | B81: Annual Growth % | C81: M2 Basis | D81: FI Correlation | E81: Effective Rate | F81: Description
A82: Bear Case (Low Inflation) | B82: 0.02 | C82: M2 < 2% | D82: 0.75 | E82: =B82*D82 | F82: Bullish for citizens - unlikely given current trend
A83: Base Case (Moderate) | B83: 0.057 | C83: M2 ~5.7% | D83: 0.75 | E83: =B83*D83 | F83: Historical average M2 expansion
A84: Bull Case (High Inflation) | B84: 0.0985 | C84: M2 ~9.85% | D84: 0.75 | E84: =B84*D84 | F84: Bear for citizens - assessed as most likely scenario
A85: Model Default (Conservative) | B85: 0.04 | C85: Below M2 | D85: 1.0 | E85: =B85*D85 | F85: Current model assumption - below all M2 scenarios
A87: PER-INSTITUTION M2-ADJUSTED GROWTH RATES
A88: Set each FI growth rate independently. Yellow cells override the global growth rate for that FI's revenue formulas.
A89: Institution | B89: M2 Correlation | C89: Custom Growth Rate | D89: Use Custom? (1=Yes) | E89: Notes
A90: ATB Financial | B90: 0.75 | C90: 0.068 | D90: 0 | E90: ATB FY2025 deposit growth was 6.8%. M2 corr ~0.75
A91: Bow Valley CU | B91: 0.7 | C91: 0.055 | D91: 0 | E91: Small Alberta CU, moderate M2 correlation
A92: Vancity CU | B92: 0.6 | C92: 0.045 | D92: 0 | E92: BC-based, different regional dynamics
A93: Servus CU | B93: 0.65 | C93: 0.05 | D93: 0 | E93: Smaller institution, slightly lower M2 correlation
A95: TOKENIZATION PENETRATION RAMP (% of FI Base Tokenized)
A96: Start conservative (1%), scale as platform matures. | JPM Kinexys: $1.5T+ processed, 10x YoY growth | BoC Project Samara: $100M tokenized bond pilot (Mar 2026) | McKinsey: 75% CAGR tokenized assets to $2-4T by 2030
A97: Rate | B97: H2 2026 | C97: H1 2027 | D97: H2 2027 | E97: H1 2028 | F97: H2 2028 | G97: H1 2029 | H97: H2 2029 | I97: H1 2030 | J97: H2 2030 | K97: H1 2031 | L97: H2 2031
A98: Deposit Tokenization % | B98: 0.01 | C98: 0.01 | D98: 0.01 | E98: 0.02 | F98: 0.02 | G98: 0.03 | H98: 0.03 | I98: 0.04 | J98: 0.04 | K98: 0.05 | L98: 0.05
A99: Issuance/Custody Tokenization % | B99: 0.015 | C99: 0.015 | D99: 0.015 | E99: 0.03 | F99: 0.03 | G99: 0.045 | H99: 0.045 | I99: 0.06 | J99: 0.06 | K99: 0.075 | L99: 0.075
A100: Use Ramp Schedule? (1=Ramp, 0=Flat) | B100: 1 | C100: If 0, uses flat rates from Macro Assumptions (B27=1%, B28=1.5%)
A102: INDUSTRY TOKENIZATION BENCHMARKS
A103: Institution / Source | B103: Metric | C103: Value | D103: Date | E103: Relevance | F103: Source
A104: JP Morgan Kinexys | B104: Total notional processed | C104: $1.5T+ | D104: 2025 | E104: Proves institutional-scale tokenized deposit demand | F104: JPM Kinexys docs
A105: JP Morgan Kinexys | B105: YoY payment growth | C105: 10x | D105: 2025 | E105: Exponential adoption curve once platform live | F105: CoinDesk Dec 2025
A106: Bank of Canada | B106: Project Samara pilot | C106: $100M bond | D106: Mar 2026 | E106: BoC validating tokenization for Canadian market | F106: BoC announcement
A107: McKinsey & Co. | B107: Tokenized RWA forecast (base) | C107: $2T by 2030 | D107: 2024 | E107: 75% CAGR across asset classes | F107: McKinsey report
A108: BCG + Ripple | B108: Tokenized RWA forecast | C108: $9.4T by 2030 | D108: 2025 | E108: Broader adoption curve for all RWAs | F108: BCG/Ripple report
A109: Jamie Dimon (JPM CEO) | B109: Strategic priority | C109: "Must move faster" | D109: Apr 2026 | E109: CEO-level urgency on tokenization | F109: CoinDesk Apr 2026
A111: NON-DILUTIVE CAPITAL / GRANTS
A112: Toggle each grant ON/OFF (1/0). Edit funding amounts per semi-annual period. | Amounts flow into Summary and P&L as non-dilutive income. | SR&ED also appears as negative OpEx - this section is ADDITIVE for scenario modeling.
A113: Grant Program | B113: Toggle (1=ON) | C113: Status | D113: Max Amount | E113: Notes
A114: Alberta Innovates FinTech Sandbox | B114: 1 | C114: =IF(B114=1,"ON","OFF") | D114: $250K | E114: Provincial - regulated pilot programs, sandbox deployment, compliance testing
A115: NRC IRAP (Industrial Research Assistance) | B115: 1 | C115: =IF(B115=1,"ON","OFF") | D115: $500K+ | E115: Federal - core R&D, security architecture, custody integration. 4 streams incl Innovation Assist
A116: SR&ED Tax Credits (35% of R&D) | B116: 1 | C116: =IF(B116=1,"ON","OFF") | D116: ~35% R&D | E116: Federal - smart contract dev, settlement systems, tokenization infra. $6M limit (2026 expansion)
A117: Digital Supercluster | B117: 1 | C117: =IF(B117=1,"ON","OFF") | D117: Multi-$M | E117: Federal/Private partnership - institutional fintech, large-scale infrastructure pilots
A118: Innovative Solutions Canada | B118: 1 | C118: =IF(B118=1,"ON","OFF") | D118: $150K-$1M | E118: Federal - settlement modernization challenges, public-sector infra pilots (challenge-based)
A119: PrairiesCan (Regional Development) | B119: 1 | C119: =IF(B119=1,"ON","OFF") | D119: $50K-$500K | E119: Federal - Prairies Economic Development Canada, innovation + growth funding for Alberta startups
A120: Mitacs Business Strategy Internship | B120: 1 | C120: =IF(B120=1,"ON","OFF") | D120: $15K-$60K | E120: Federal - subsidized R&D talent, 4-12 month terms, pairs with IRAP
A121: Alberta Enterprise Accelerate Fund IV | B121: 0 | C121: =IF(B121=1,"ON","OFF") | D121: Co-invest | E121: Provincial - $25M fund for pre-seed/seed Alberta tech. Co-invest model (equity component - toggle OFF by default)
A123: GRANT FUNDING SCHEDULE (Semi-Annual - Editable)
A124: Enter expected funding per semi-annual period. Total row auto-sums. | Only grants toggled ON flow into P&L. Yellow cells = editable.
A125: Grant Program | B125: Toggle Ref | C125: H2 2026 | D125: H1 2027 | E125: H2 2027 | F125: H1 2028 | G125: H2 2028 | H125: H1 2029 | I125: H2 2029 | J125: H1 2030 | K125: H2 2030 | L125: H1 2031 | M125: H2 2031 | N125: 5-Year Total
A126: Alberta Innovates FinTech Sandbox | B126: =IF(B114=1,"ON","OFF") | C126: 0 | D126: 50000 | E126: 50000 | F126: 50000 | G126: 50000 | H126: 25000 | I126: 25000 | J126: 0 | K126: 0 | L126: 0 | M126: 0 | N126: =SUM(C126:M126)
A127: NRC IRAP | B127: =IF(B115=1,"ON","OFF") | C127: 0 | D127: 75000 | E127: 75000 | F127: 100000 | G127: 100000 | H127: 75000 | I127: 75000 | J127: 0 | K127: 0 | L127: 0 | M127: 0 | N127: =SUM(C127:M127)
...

Sheet Summary
A1: 4ORM FINANCE - EXECUTIVE SUMMARY
A2: 5-Year Financial Snapshot | Semi-Annual Periods | the platform Build | 5 Revenue Streams + (reserved) | CAD
A4: KEY METRICS AT A GLANCE | LEAN BUILD vs TRADITIONAL | B4: platform Build | C4: Traditional Build | D4: Efficiency Savings
A5: ATB Year 1 Revenue (4ORM Share) | B5: ='Revenue Model'!D26+'Revenue Model'!E26 | C5: =B5 | D5: N/A - Revenue same | E5: 5 streams: Settlement + Issuance + Trading + Custody + SaaS
A6: 5-Year Total Revenue (4 FIs + (reserved)) | B6: ='5-Year P&L Summary'!M16 | C6: =B6 | D6: N/A - Revenue same | E6: ATB+BVCU (2027) + Servus+Vancity (2028) + (reserved)
A7: 5-Year Total Expenses (platform Build) | B7: ='5-Year P&L Summary'!M24 | C7: =SUM('DevEx - Build Costs'!C36:M37)+SUM('OpEx - Ongoing'!C39:M40) | D7: =C7-B7 | E7: Traditional = +35% DevEx + ~$890K/yr additional comp
A8: 5-Year Net Income | B8: ='5-Year P&L Summary'!M26 | C8: =B6-C7 | D8: =B8-C8 | E8: platform Build generates more profit by reducing expenses
A9: Year 5 Annual Revenue (H2 2031) | B9: ='Revenue Model'!M58 | C9: =B9 | D9: N/A - Revenue same | E9: H2 2031: 4 FIs at full capacity + (reserved)
A10: Blended Gross Margin | B10: =IF('5-Year P&L Summary'!M16=0,0,'5-Year P&L Summary'!M26/'5-Year P&L Summary'!M16) | C10: =IF(B6=0,0,(B6-C7)/B6) | D10: =B10-C10 | E10: platform Build achieves higher margins via lower headcount
A12: 5-YEAR P&L SNAPSHOT (platform BUILD)
B13: H2 2026 | C13: H1 2027 | D13: H2 2027 | E13: H1 2028 | F13: H2 2028 | G13: H1 2029 | H13: H2 2029 | I13: H1 2030 | J13: H2 2030 | K13: H1 2031 | L13: H2 2031 | M13: 5-Year Total
A14: Total Revenue | B14: ='5-Year P&L Summary'!B13 | C14: ='5-Year P&L Summary'!C13 | D14: ='5-Year P&L Summary'!D13 | E14: ='5-Year P&L Summary'!E13 | F14: ='5-Year P&L Summary'!F13 | G14: ='5-Year P&L Summary'!G13 | H14: ='5-Year P&L Summary'!H13 | I14: ='5-Year P&L Summary'!I13 | ... L14: ='5-Year P&L Summary'!L13 | M14: =SUM(B14:L14)
A15: Settlement Fees (1.5 bps) | B15: ='5-Year P&L Summary'!B6 | C15: ='5-Year P&L Summary'!C6 | D15: ='5-Year P&L Summary'!D6 | E15: ='5-Year P&L Summary'!E6 | F15: ='5-Year P&L Summary'!F6 | G15: ='5-Year P&L Summary'!G6 | H15: ='5-Year P&L Summary'!H6 | I15: ='5-Year P&L Summary'!I6 | ... L15: ='5-Year P&L Summary'!L6 | M15: =SUM(B15:L15)
A16: Issuance Fees (0.5%) | B16: ='5-Year P&L Summary'!B7 | C16: ='5-Year P&L Summary'!C7 | D16: ='5-Year P&L Summary'!D7 | E16: ='5-Year P&L Summary'!E7 | F16: ='5-Year P&L Summary'!F7 | G16: ='5-Year P&L Summary'!G7 | H16: ='5-Year P&L Summary'!H7 | I16: ='5-Year P&L Summary'!I7 | ... L16: ='5-Year P&L Summary'!L7 | M16: =SUM(B16:L16)
A17: Trading Fees (5 bps) | B17: ='5-Year P&L Summary'!B8 | C17: ='5-Year P&L Summary'!C8 | D17: ='5-Year P&L Summary'!D8 | E17: ='5-Year P&L Summary'!E8 | F17: ='5-Year P&L Summary'!F8 | G17: ='5-Year P&L Summary'!G8 | H17: ='5-Year P&L Summary'!H8 | I17: ='5-Year P&L Summary'!I8 | ... L17: ='5-Year P&L Summary'!L8 | M17: =SUM(B17:L17)
A18: Custody Fees (30 bps) | B18: ='5-Year P&L Summary'!B9 | C18: ='5-Year P&L Summary'!C9 | D18: ='5-Year P&L Summary'!D9 | E18: ='5-Year P&L Summary'!E9 | F18: ='5-Year P&L Summary'!F9 | G18: ='5-Year P&L Summary'!G9 | H18: ='5-Year P&L Summary'!H9 | I18: ='5-Year P&L Summary'!I9 | ... L18: ='5-Year P&L Summary'!L9 | M18: =SUM(B18:L18)
A19: SaaS + APIs ($25K/mo) | B19: ='5-Year P&L Summary'!B10 | C19: ='5-Year P&L Summary'!C10 | D19: ='5-Year P&L Summary'!D10 | E19: ='5-Year P&L Summary'!E10 | F19: ='5-Year P&L Summary'!F10 | G19: ='5-Year P&L Summary'!G10 | H19: ='5-Year P&L Summary'!H10 | I19: ='5-Year P&L Summary'!I10 | ... L19: ='5-Year P&L Summary'!L10 | M19: =SUM(B19:L19)
A20: (reserved) | B20: ='5-Year P&L Summary'!B11 | C20: ='5-Year P&L Summary'!C11 | D20: ='5-Year P&L Summary'!D11 | E20: ='5-Year P&L Summary'!E11 | F20: ='5-Year P&L Summary'!F11 | G20: ='5-Year P&L Summary'!G11 | H20: ='5-Year P&L Summary'!H11 | I20: ='5-Year P&L Summary'!I11 | ... L20: ='5-Year P&L Summary'!L11 | M20: =SUM(B20:L20)
A21: (Reserved 6th Stream) | B21: ='5-Year P&L Summary'!B12 | C21: ='5-Year P&L Summary'!C12 | D21: ='5-Year P&L Summary'!D12 | E21: ='5-Year P&L Summary'!E12 | F21: ='5-Year P&L Summary'!F12 | G21: ='5-Year P&L Summary'!G12 | H21: ='5-Year P&L Summary'!H12 | I21: ='5-Year P&L Summary'!I12 | ... L21: ='5-Year P&L Summary'!L12 | M21: =SUM(B21:L21)
A22: Total DevEx | B22: ='5-Year P&L Summary'!B19 | C22: ='5-Year P&L Summary'!C19 | D22: ='5-Year P&L Summary'!D19 | E22: ='5-Year P&L Summary'!E19 | F22: ='5-Year P&L Summary'!F19 | G22: ='5-Year P&L Summary'!G19 | H22: ='5-Year P&L Summary'!H19 | I22: ='5-Year P&L Summary'!I19 | ... L22: ='5-Year P&L Summary'!L19 | M22: =SUM(B22:L22)
A23: Total OpEx | B23: ='5-Year P&L Summary'!B22 | C23: ='5-Year P&L Summary'!C22 | D23: ='5-Year P&L Summary'!D22 | E23: ='5-Year P&L Summary'!E22 | F23: ='5-Year P&L Summary'!F22 | G23: ='5-Year P&L Summary'!G22 | H23: ='5-Year P&L Summary'!H22 | I23: ='5-Year P&L Summary'!I22 | ... L23: ='5-Year P&L Summary'!L22 | M23: =SUM(B23:L23)
A24: Total Expenses | B24: ='5-Year P&L Summary'!B24 | C24: ='5-Year P&L Summary'!C24 | D24: ='5-Year P&L Summary'!D24 | E24: ='5-Year P&L Summary'!E24 | F24: ='5-Year P&L Summary'!F24 | G24: ='5-Year P&L Summary'!G24 | H24: ='5-Year P&L Summary'!H24 | I24: ='5-Year P&L Summary'!I24 | ... L24: ='5-Year P&L Summary'!L24 | M24: =SUM(B24:L24)
A25: NET PROFIT (LOSS) | B25: ='5-Year P&L Summary'!B26 | C25: ='5-Year P&L Summary'!C26 | D25: ='5-Year P&L Summary'!D26 | E25: ='5-Year P&L Summary'!E26 | F25: ='5-Year P&L Summary'!F26 | G25: ='5-Year P&L Summary'!G26 | H25: ='5-Year P&L Summary'!H26 | I25: ='5-Year P&L Summary'!I26 | ... L25: ='5-Year P&L Summary'!L26 | M25: =SUM(B25:L25)
A26: Net Margin % | B26: ='5-Year P&L Summary'!B27 | C26: ='5-Year P&L Summary'!C27 | D26: ='5-Year P&L Summary'!D27 | E26: ='5-Year P&L Summary'!E27 | F26: ='5-Year P&L Summary'!F27 | G26: ='5-Year P&L Summary'!G27 | H26: ='5-Year P&L Summary'!H27 | I26: ='5-Year P&L Summary'!I27 | ... L26: ='5-Year P&L Summary'!L27 | M26: =IF(M14=0,0,M25/M14)
A28: LEAN BUILD vs TRADITIONAL BUILD COMPARISON
A29: Metric | B29: H2 2026 | C29: H1 2027 | D29: H2 2027 | E29: H1 2028 | F29: H2 2028 | G29: H1 2029 | H29: H2 2029 | I29: H1 2030 | J29: H2 2030 | K29: H1 2031 | L29: H2 2031 | M29: 5-Year Total
A30: platform Build - Total DevEx | B30: ='DevEx - Build Costs'!C35 | C30: ='DevEx - Build Costs'!D35 | D30: ='DevEx - Build Costs'!E35 | E30: ='DevEx - Build Costs'!F35 | F30: ='DevEx - Build Costs'!G35 | G30: ='DevEx - Build Costs'!H35 | H30: ='DevEx - Build Costs'!I35 | I30: ='DevEx - Build Costs'!J35 | ... L30: ='DevEx - Build Costs'!M35 | M30: =SUM(B30:L30)
A31: platform Build - Total OpEx | B31: ='OpEx - Ongoing'!C38 | C31: ='OpEx - Ongoing'!D38 | D31: ='OpEx - Ongoing'!E38 | E31: ='OpEx - Ongoing'!F38 | F31: ='OpEx - Ongoing'!G38 | G31: ='OpEx - Ongoing'!H38 | H31: ='OpEx - Ongoing'!I38 | I31: ='OpEx - Ongoing'!J38 | ... L31: ='OpEx - Ongoing'!M38 | M31: =SUM(B31:L31)
A32: platform Build - Total Expenses | B32: =B30+B31 | C32: =C30+C31 | D32: =D30+D31 | E32: =E30+E31 | F32: =F30+F31 | G32: =G30+G31 | H32: =H30+H31 | I32: =I30+I31 | ... L32: =L30+L31 | M32: =SUM(B32:L32)
A33: Traditional - Total DevEx (+35%) | B33: ='DevEx - Build Costs'!C36 | C33: ='DevEx - Build Costs'!D36 | D33: ='DevEx - Build Costs'!E36 | E33: ='DevEx - Build Costs'!F36 | F33: ='DevEx - Build Costs'!G36 | G33: ='DevEx - Build Costs'!H36 | H33: ='DevEx - Build Costs'!I36 | I33: ='DevEx - Build Costs'!J36 | ... L33: ='DevEx - Build Costs'!M36 | M33: =SUM(B33:L33)
A34: Traditional - Total OpEx (+~$890K comp) | B34: ='OpEx - Ongoing'!C39 | C34: ='OpEx - Ongoing'!D39 | D34: ='OpEx - Ongoing'!E39 | E34: ='OpEx - Ongoing'!F39 | F34: ='OpEx - Ongoing'!G39 | G34: ='OpEx - Ongoing'!H39 | H34: ='OpEx - Ongoing'!I39 | I34: ='OpEx - Ongoing'!J39 | ... L34: ='OpEx - Ongoing'!M39 | M34: =SUM(B34:L34)
A35: Traditional - Total Expenses | B35: =B33+B34 | C35: =C33+C34 | D35: =D33+D34 | E35: =E33+E34 | F35: =F33+F34 | G35: =G33+G34 | H35: =H33+H34 | I35: =I33+I34 | ... L35: =L33+L34 | M35: =SUM(B35:L35)
A36: EFFICIENCY BUILD SAVINGS | B36: =B35-B32 | C36: =C35-C32 | D36: =D35-D32 | E36: =E35-E32 | F36: =F35-F32 | G36: =G35-G32 | H36: =H35-H32 | I36: =I35-I32 | ... L36: =L35-L32 | M36: =SUM(B36:L36)
A38: REVENUE BY FINANCIAL INSTITUTION
A39: Institution | B39: H2 2026 | C39: H1 2027 | D39: H2 2027 | E39: H1 2028 | F39: H2 2028 | G39: H1 2029 | H39: H2 2029 | I39: H1 2030 | J39: H2 2030 | K39: H1 2031 | L39: H2 2031 | M39: 5-Year Total
A40: ATB Financial | B40: ='Revenue Model'!C26 | C40: ='Revenue Model'!D26 | D40: ='Revenue Model'!E26 | E40: ='Revenue Model'!F26 | F40: ='Revenue Model'!G26 | G40: ='Revenue Model'!H26 | H40: ='Revenue Model'!I26 | I40: ='Revenue Model'!J26 | ... L40: ='Revenue Model'!M26 | M40: =SUM(B40:L40)
A41: Bow Valley CU | B41: ='Revenue Model'!C33 | C41: ='Revenue Model'!D33 | D41: ='Revenue Model'!E33 | E41: ='Revenue Model'!F33 | F41: ='Revenue Model'!G33 | G41: ='Revenue Model'!H33 | H41: ='Revenue Model'!I33 | I41: ='Revenue Model'!J33 | ... L41: ='Revenue Model'!M33 | M41: =SUM(B41:L41)
A42: Vancity Credit Union | B42: ='Revenue Model'!C40 | C42: ='Revenue Model'!D40 | D42: ='Revenue Model'!E40 | E42: ='Revenue Model'!F40 | F42: ='Revenue Model'!G40 | G42: ='Revenue Model'!H40 | H42: ='Revenue Model'!I40 | I42: ='Revenue Model'!J40 | ... L42: ='Revenue Model'!M40 | M42: =SUM(B42:L42)
A43: Servus Credit Union | B43: ='Revenue Model'!C47 | C43: ='Revenue Model'!D47 | D43: ='Revenue Model'!E47 | E43: ='Revenue Model'!F47 | F43: ='Revenue Model'!G47 | G43: ='Revenue Model'!H47 | H43: ='Revenue Model'!I47 | I43: ='Revenue Model'!J47 | ... L43: ='Revenue Model'!M47 | M43: =SUM(B43:L43)
A44: (reserved slot) | B44: ='Revenue Model'!C49 | C44: ='Revenue Model'!D49 | D44: ='Revenue Model'!E49 | E44: ='Revenue Model'!F49 | F44: ='Revenue Model'!G49 | G44: ='Revenue Model'!H49 | H44: ='Revenue Model'!I49 | I44: ='Revenue Model'!J49 | ... L44: ='Revenue Model'!M49 | M44: =SUM(B44:L44)
A45: (Reserved 6th Stream) | B45: ='Revenue Model'!C68 | C45: ='Revenue Model'!D68 | D45: ='Revenue Model'!E68 | E45: ='Revenue Model'!F68 | F45: ='Revenue Model'!G68 | G45: ='Revenue Model'!H68 | H45: ='Revenue Model'!I68 | I45: ='Revenue Model'!J68 | ... L45: ='Revenue Model'!M68 | M45: =SUM(B45:L45)
A46: TOTAL ALL REVENUE | B46: =B40+B41+B42+B43+B44+B45 | C46: =C40+C41+C42+C43+C44+C45 | D46: =D40+D41+D42+D43+D44+D45 | E46: =E40+E41+E42+E43+E44+E45 | F46: =F40+F41+F42+F43+F44+F45 | G46: =G40+G41+G42+G43+G44+G45 | H46: =H40+H41+H42+H43+H44+H45 | I46: =I40+I41+I42+I43+I44+I45 | ... L46: =L40+L41+L42+L43+L44+L45 | M46: =SUM(B46:L46)
A48: REQUIRED CORPORATE STRUCTURE (Canadian Securities Regulation)
A49: CIRO (Feb 2026) mandates custody operations be legally and functionally separate from exchange operations. Minimum 3 corporate entities required.
A50: Entity | B50: Type | C50: Purpose | D50: Regulatory Basis | E50: Est. Annual Cost | F50: Notes
A51: 4ORM Holdings Inc. | B51: HoldCo | C51: Parent holding company - owns OpCo and CustodyCo. Holds intellectual property (patents, trade secrets, copyrights on code/APIs), brand, and licensing agreements. | D51: Standard corporate structure; IP protection via Copyright Act, Patent Act | E51: $45,000-$65,000 | F51: Legal + annual filings + IP maintenance + D&O insurance
A52: 4ORM Exchange Inc. | B52: OpCo | C52: Registered Investment Dealer with CIRO. Operates the institutional settlement layer / ATS (Alternative Trading System). All trading, settlement, and client-facing operations. | D52: CIRO dealer membership; CSA registration; NI 21-101 (ATS rules) | E52: $250,000-$350,000 | F52: CIRO fees + compliance staff + regulatory filings + capital requirements
A53: 4ORM Custody Inc. | B53: CustodyCo | C53: Separate legal entity for digital asset custody. Must be independent from exchange operations per CIRO framework. Holds client assets in qualified custody. | D53: CIRO Digital Asset Custody Framework (Feb 2026); must meet Tier requirements | E53: $150,000-$200,000 | F53: SOC 2 audit + insurance + security infrastructure + independent board
A54: TOTAL ANNUAL CORPORATE OVERHEAD | E54: $445,000-$615,000
A56: KEY REGULATORY REQUIREMENTS
A57: Requirement | B57: Detail | C57: Status
A58: CIRO Dealer Membership | B58: OpCo must register as investment dealer with CIRO. Required for any firm facilitating trades of securities/derivatives including tokenized assets. | C58: Mandatory
A59: Custody Separation | B59: Custodian must be legally and functionally independent from exchange/marketplace. Eliminates exposure to exchange losses and conflicts of interest. | C59: Mandatory
A60: Tiered Custody Compliance | B60: CIRO 4-tier system: Tier 1 ($100M+ capital), Tier 2 (full compliance), Tier 3 (75% limit), Tier 4 (self-custody up to 20%). CustodyCo targets Tier 2-3. | C60: Mandatory
A61: SOC 2 Type II | B61: Annual SOC 2 audit for custody operations. Required for all Acceptable Crypto Custodians under CIRO framework. | C61: Mandatory
A62: Weekly Custody Monitoring | B62: Dealer must monitor custody limit compliance weekly, report breaches promptly, maintain documented key management and authorization policies. | C62: Mandatory
A63: CSA Prospectus/Exemption | B63: Tokenized deposits may require prospectus exemption filing under CSA rules. OpCo handles all securities law compliance. | C63: Case-dependent
A64: IP Protection (HoldCo) | B64: Patents on exchange mechanics, copyright on all code/APIs, trade secrets. HoldCo licenses IP to OpCo. Protects IP in insolvency. | C64: Best practice
A65: Provincial Registration | B65: Registration in each province where clients are located (minimum AB + BC for initial FI partners). | C65: Mandatory
A67: NON-DILUTIVE CAPITAL / GRANTS OVERVIEW
A68: Grant Program | B68: H2 2026 | C68: H1 2027 | D68: H2 2027 | E68: H1 2028 | F68: H2 2028 | G68: H1 2029 | H68: H2 2029 | I68: H1 2030 | J68: H2 2030 | K68: H1 2031 | L68: H2 2031 | M68: 5-Year Total
A69: Alberta Innovates FinTech Sandbox | B69: ='Control Panel'!$B$114*'Control Panel'!C126 | C69: ='Control Panel'!$B$114*'Control Panel'!D126 | D69: ='Control Panel'!$B$114*'Control Panel'!E126 | E69: ='Control Panel'!$B$114*'Control Panel'!F126 | F69: ='Control Panel'!$B$114*'Control Panel'!G126 | G69: ='Control Panel'!$B$114*'Control Panel'!H126 | H69: ='Control Panel'!$B$114*'Control Panel'!I126 | I69: ='Control Panel'!$B$114*'Control Panel'!J126 | ... L69: ='Control Panel'!$B$114*'Control Panel'!M126 | M69: =SUM(B69:L69)
A70: NRC IRAP | B70: ='Control Panel'!$B$115*'Control Panel'!C127 | C70: ='Control Panel'!$B$115*'Control Panel'!D127 | D70: ='Control Panel'!$B$115*'Control Panel'!E127 | E70: ='Control Panel'!$B$115*'Control Panel'!F127 | F70: ='Control Panel'!$B$115*'Control Panel'!G127 | G70: ='Control Panel'!$B$115*'Control Panel'!H127 | H70: ='Control Panel'!$B$115*'Control Panel'!I127 | I70: ='Control Panel'!$B$115*'Control Panel'!J127 | ... L70: ='Control Panel'!$B$115*'Control Panel'!M127 | M70: =SUM(B70:L70)
A71: SR&ED Tax Credits | B71: ='Control Panel'!$B$116*'Control Panel'!C128 | C71: ='Control Panel'!$B$116*'Control Panel'!D128 | D71: ='Control Panel'!$B$116*'Control Panel'!E128 | E71: ='Control Panel'!$B$116*'Control Panel'!F128 | F71: ='Control Panel'!$B$116*'Control Panel'!G128 | G71: ='Control Panel'!$B$116*'Control Panel'!H128 | H71: ='Control Panel'!$B$116*'Control Panel'!I128 | I71: ='Control Panel'!$B$116*'Control Panel'!J128 | ... L71: ='Control Panel'!$B$116*'Control Panel'!M128 | M71: =SUM(B71:L71)
A72: Digital Supercluster | B72: ='Control Panel'!$B$117*'Control Panel'!C129 | C72: ='Control Panel'!$B$117*'Control Panel'!D129 | D72: ='Control Panel'!$B$117*'Control Panel'!E129 | E72: ='Control Panel'!$B$117*'Control Panel'!F129 | F72: ='Control Panel'!$B$117*'Control Panel'!G129 | G72: ='Control Panel'!$B$117*'Control Panel'!H129 | H72: ='Control Panel'!$B$117*'Control Panel'!I129 | I72: ='Control Panel'!$B$117*'Control Panel'!J129 | ... L72: ='Control Panel'!$B$117*'Control Panel'!M129 | M72: =SUM(B72:L72)
A73: Innovative Solutions Canada | B73: ='Control Panel'!$B$118*'Control Panel'!C130 | C73: ='Control Panel'!$B$118*'Control Panel'!D130 | D73: ='Control Panel'!$B$118*'Control Panel'!E130 | E73: ='Control Panel'!$B$118*'Control Panel'!F130 | F73: ='Control Panel'!$B$118*'Control Panel'!G130 | G73: ='Control Panel'!$B$118*'Control Panel'!H130 | H73: ='Control Panel'!$B$118*'Control Panel'!I130 | I73: ='Control Panel'!$B$118*'Control Panel'!J130 | ... L73: ='Control Panel'!$B$118*'Control Panel'!M130 | M73: =SUM(B73:L73)
A74: PrairiesCan | B74: ='Control Panel'!$B$119*'Control Panel'!C131 | C74: ='Control Panel'!$B$119*'Control Panel'!D131 | D74: ='Control Panel'!$B$119*'Control Panel'!E131 | E74: ='Control Panel'!$B$119*'Control Panel'!F131 | F74: ='Control Panel'!$B$119*'Control Panel'!G131 | G74: ='Control Panel'!$B$119*'Control Panel'!H131 | H74: ='Control Panel'!$B$119*'Control Panel'!I131 | I74: ='Control Panel'!$B$119*'Control Panel'!J131 | ... L74: ='Control Panel'!$B$119*'Control Panel'!M131 | M74: =SUM(B74:L74)
A75: Mitacs | B75: ='Control Panel'!$B$120*'Control Panel'!C132 | C75: ='Control Panel'!$B$120*'Control Panel'!D132 | D75: ='Control Panel'!$B$120*'Control Panel'!E132 | E75: ='Control Panel'!$B$120*'Control Panel'!F132 | F75: ='Control Panel'!$B$120*'Control Panel'!G132 | G75: ='Control Panel'!$B$120*'Control Panel'!H132 | H75: ='Control Panel'!$B$120*'Control Panel'!I132 | I75: ='Control Panel'!$B$120*'Control Panel'!J132 | ... L75: ='Control Panel'!$B$120*'Control Panel'!M132 | M75: =SUM(B75:L75)
A76: Alberta Enterprise Accelerate Fund IV | B76: ='Control Panel'!$B$121*'Control Panel'!C133 | C76: ='Control Panel'!$B$121*'Control Panel'!D133 | D76: ='Control Panel'!$B$121*'Control Panel'!E133 | E76: ='Control Panel'!$B$121*'Control Panel'!F133 | F76: ='Control Panel'!$B$121*'Control Panel'!G133 | G76: ='Control Panel'!$B$121*'Control Panel'!H133 | H76: ='Control Panel'!$B$121*'Control Panel'!I133 | I76: ='Control Panel'!$B$121*'Control Panel'!J133 | ... L76: ='Control Panel'!$B$121*'Control Panel'!M133 | M76: =SUM(B76:L76)
A77: TOTAL NON-DILUTIVE CAPITAL | B77: =B69+B70+B71+B72+B73+B74+B75+B76 | C77: =C69+C70+C71+C72+C73+C74+C75+C76 | D77: =D69+D70+D71+D72+D73+D74+D75+D76 | E77: =E69+E70+E71+E72+E73+E74+E75+E76 | F77: =F69+F70+F71+F72+F73+F74+F75+F76 | G77: =G69+G70+G71+G72+G73+G74+G75+G76 | H77: =H69+H70+H71+H72+H73+H74+H75+H76 | I77: =I69+I70+I71+I72+I73+I74+I75+I76 | ... L77: =L69+L70+L71+L72+L73+L74+L75+L76 | M77: =SUM(B77:L77)

Sheet Team Roadmap
A1: 4ORM FINANCE - 5-YEAR TEAM HIRING ROADMAP | the platform BUILD vs TRADITIONAL BUILD
A2: Phase 1 = Pre-Seed team (Chad, Zed, Kevin, Bruce, Dean, plus CTO + Smart Contract Dev + Backend Dev + DevOps + Exec Asst).
A4: Role | B4: Annual Salary | C4: platform H2 2026 | D4: platform H1 2027 | E4: platform H2 2027 | F4: platform H1 2028 | G4: platform H2 2028 | H4: platform H1 2029 | I4: platform H2 2029 | J4: platform H1 2030 | K4: platform H2 2030 | L4: platform H1 2031 | M4: platform H2 2031 | N4: Trad H2 2026 | O4: Trad H1 2027 | P4: Trad H2 2027 | Q4: Trad H1 2028 | R4: Trad H2 2028 | S4: Trad H1 2029 | T4: Trad H2 2029 | U4: Trad H1 2030 | V4: Trad H2 2030 | W4: Trad H1 2031 | X4: Trad H2 2031 | Y4: platform Build Savings %
A5: EXECUTIVE TEAM
A6: CEO (Chad) | B6: 96000 | C6: 0.5 | D6: 1 | E6: 1 | F6: 1 | G6: 1 | H6: 1 | I6: 1 | J6: 1 | K6: 1 | L6: 1 | M6: 1 | N6: 1 | O6: 1 | P6: 1 | Q6: 1 | R6: 1 | S6: 1 | T6: 1 | U6: 1 | V6: 1 | W6: 1 | X6: 1 | Y6: 0
A7: CTO (Phase 1 hire) | B7: 180000 | C7: 0.5 | D7: 1 | E7: 1 | F7: 1 | G7: 1 | H7: 1 | I7: 1 | J7: 1 | K7: 1 | L7: 1 | M7: 1 | N7: 0 | O7: 0 | P7: 0 | Q7: 1 | R7: 1 | S7: 1 | T7: 1 | U7: 1 | V7: 1 | W7: 1 | X7: 1 | Y7: 0
A8: CCO (Chief Compliance) (Phase 2) | B8: 180000 | C8: 0 | D8: 0 | E8: 0 | F8: 1 | G8: 1 | H8: 1 | I8: 1 | J8: 1 | K8: 1 | L8: 1 | M8: 1 | N8: 0 | O8: 0 | P8: 0 | Q8: 1 | R8: 1 | S8: 1 | T8: 1 | U8: 1 | V8: 1 | W8: 1 | X8: 1 | Y8: 0
A9: CFO (Fractional -> Full-time in Phase 2) | B9: 72000 | C9: 0.15 | D9: 0.3 | E9: 0.3 | F9: 1 | G9: 1 | H9: 1 | I9: 1 | J9: 1 | K9: 1 | L9: 1 | M9: 1 | N9: 1 | O9: 1 | P9: 1 | Q9: 1 | R9: 1 | S9: 1 | T9: 1 | U9: 1 | V9: 1 | W9: 1 | X9: 1 | Y9: 0
A10: General Counsel (Phase 2) | B10: 200000 | C10: 0 | D10: 0 | E10: 0 | F10: 1 | G10: 1 | H10: 1 | I10: 1 | J10: 1 | K10: 1 | L10: 1 | M10: 1 | N10: 0 | O10: 0 | P10: 0 | Q10: 1 | R10: 1 | S10: 1 | T10: 1 | U10: 1 | V10: 1 | W10: 1 | X10: 1 | Y10: 0
A11: ENGINEERING
A12: Head Architect (Zed) | B12: 170000 | C12: 0.5 | D12: 1 | E12: 1 | F12: 1 | G12: 1 | H12: 1 | I12: 1 | J12: 1 | K12: 1 | L12: 1 | M12: 1 | N12: 1 | O12: 1 | P12: 1 | Q12: 1 | R12: 1 | S12: 1 | T12: 1 | U12: 1 | V12: 1 | W12: 1 | X12: 1 | Y12: 0
A13: Backend Developer (starts H2 2026 at 0.5 FTE) | B13: 145000 | C13: 0.5 | D13: 1 | E13: 1 | F13: 1 | G13: 1 | H13: 1 | I13: 1 | J13: 1 | K13: 1 | L13: 1 | M13: 1 | N13: 0 | O13: 1 | P13: 1 | Q13: 2 | R13: 2 | S13: 2 | T13: 2 | U13: 2 | V13: 2 | W13: 2 | X13: 2 | Y13: 0
A14: Backend Developer #2 (Phase 2) | B14: 145000 | C14: 0 | D14: 0 | E14: 0 | F14: 1 | G14: 1 | H14: 1 | I14: 1 | J14: 1 | K14: 1 | L14: 1 | M14: 1 | N14: 1 | O14: 1 | P14: 1 | Q14: 1 | R14: 1 | S14: 1 | T14: 1 | U14: 1 | V14: 1 | W14: 1 | X14: 1 | Y14: 0.27272727
A15: Frontend Developer #1 (Phase 2) | B15: 130000 | C15: 0 | D15: 0 | E15: 0 | F15: 1 | G15: 1 | H15: 1 | I15: 1 | J15: 1 | K15: 1 | L15: 1 | M15: 1 | N15: 0 | O15: 0 | P15: 0 | Q15: 1 | R15: 1 | S15: 1 | T15: 1 | U15: 1 | V15: 1 | W15: 1 | X15: 1 | Y15: 0
A16: Frontend Developer #2 | B16: 130000 | C16: 0 | D16: 0 | E16: 0 | F16: 0 | G16: 0 | H16: 1 | I16: 1 | J16: 1 | K16: 1 | L16: 1 | M16: 1 | N16: 1 | O16: 1 | P16: 1 | Q16: 1 | R16: 1 | S16: 1 | T16: 1 | U16: 1 | V16: 1 | W16: 1 | X16: 1 | Y16: 0.45454545
A17: Smart Contract Developer (starts H2 2026 at 0.5 FTE) | B17: 145000 | C17: 0.5 | D17: 1 | E17: 1 | F17: 1 | G17: 1 | H17: 1 | I17: 1 | J17: 1 | K17: 1 | L17: 1 | M17: 1 | N17: 1 | O17: 1 | P17: 1 | Q17: 1 | R17: 1 | S17: 1 | T17: 1 | U17: 1 | V17: 1 | W17: 1 | X17: 1 | Y17: 0.045454545
A18: DevOps / Infrastructure (0.5 FTE from H1 2027) | B18: 140000 | C18: 0 | D18: 0.5 | E18: 0.5 | F18: 1 | G18: 1 | H18: 1 | I18: 1 | J18: 1 | K18: 1 | L18: 1 | M18: 1 | N18: 0 | O18: 1 | P18: 1 | Q18: 1 | R18: 1 | S18: 1 | T18: 1 | U18: 1 | V18: 1 | W18: 1 | X18: 1 | Y18: 0.13636364
A19: Security Engineer (Phase 2) | B19: 150000 | C19: 0 | D19: 0 | E19: 0 | F19: 1 | G19: 1 | H19: 1 | I19: 1 | J19: 1 | K19: 1 | L19: 1 | M19: 1 | N19: 0 | O19: 0 | P19: 0 | Q19: 1 | R19: 1 | S19: 1 | T19: 1 | U19: 1 | V19: 1 | W19: 1 | X19: 1 | Y19: 0.18181818
A20: QA / Test Engineer | B20: 105000 | C20: 0 | D20: 0 | E20: 0 | F20: 0 | G20: 0 | H20: 1 | I20: 1 | J20: 1 | K20: 1 | L20: 1 | M20: 1 | N20: 1 | O20: 1 | P20: 1 | Q20: 1 | R20: 1 | S20: 1 | T20: 1 | U20: 1 | V20: 1 | W20: 1 | X20: 1 | Y20: 0.45454545
A21: Data Engineer | B21: 130000 | C21: 0 | D21: 0 | E21: 0 | F21: 0 | G21: 0 | H21: 0 | I21: 0 | J21: 1 | K21: 1 | L21: 1 | M21: 1 | N21: 0 | O21: 1 | P21: 1 | Q21: 1 | R21: 1 | S21: 1 | T21: 1 | U21: 1 | V21: 1 | W21: 1 | X21: 1 | Y21: 0.6
A22: UX / UI Designer | B22: 120000 | C22: 0 | D22: 0 | E22: 0 | F22: 0 | G22: 0 | H22: 0 | I22: 0 | J22: 0 | K22: 0 | L22: 0 | M22: 0 | N22: 1 | O22: 1 | P22: 1 | Q22: 1 | R22: 1 | S22: 1 | T22: 1 | U22: 1 | V22: 1 | W22: 1 | X22: 1 | Y22: 1
A23: Data Analyst | B23: 110000 | C23: 0 | D23: 0 | E23: 0 | F23: 0 | G23: 0 | H23: 0 | I23: 0 | J23: 0 | K23: 0 | L23: 0 | M23: 0 | N23: 0 | O23: 0 | P23: 0 | Q23: 1 | R23: 1 | S23: 1 | T23: 1 | U23: 1 | V23: 1 | W23: 1 | X23: 1 | Y23: 1
A24: COMPLIANCE & LEGAL
A25: Compliance Analyst #1 (Phase 2) | B25: 85000 | C25: 0 | D25: 0 | E25: 0 | F25: 1 | G25: 1 | H25: 1 | I25: 1 | J25: 1 | K25: 1 | L25: 1 | M25: 1 | N25: 0 | O25: 0 | P25: 0 | Q25: 1 | R25: 1 | S25: 1 | T25: 1 | U25: 1 | V25: 1 | W25: 1 | X25: 1 | Y25: 0
A26: Compliance Analyst #2 | B26: 85000 | C26: 0 | D26: 0 | E26: 0 | F26: 1 | G26: 1 | H26: 1 | I26: 1 | J26: 1 | K26: 1 | L26: 1 | M26: 1 | N26: 0 | O26: 1 | P26: 1 | Q26: 1 | R26: 1 | S26: 1 | T26: 1 | U26: 1 | V26: 1 | W26: 1 | X26: 1 | Y26: 0.2
A27: AML/KYC Specialist | B27: 95000 | C27: 0 | D27: 0 | E27: 0 | F27: 0 | G27: 0 | H27: 1 | I27: 1 | J27: 1 | K27: 1 | L27: 1 | M27: 1 | N27: 0 | O27: 0 | P27: 0 | Q27: 1 | R27: 1 | S27: 1 | T27: 1 | U27: 1 | V27: 1 | W27: 1 | X27: 1 | Y27: 0.25
A28: Paralegal / Reg Filing | B28: 75000 | C28: 0 | D28: 0 | E28: 0 | F28: 0 | G28: 0 | H28: 1 | I28: 1 | J28: 1 | K28: 1 | L28: 1 | M28: 1 | N28: 0 | O28: 0 | P28: 0 | Q28: 0 | R28: 0 | S28: 1 | T28: 1 | U28: 1 | V28: 1 | W28: 1 | X28: 1 | Y28: 0
A29: OPERATIONS & BUSINESS
A30: Head of Business Dev (Phase 2) | B30: 140000 | C30: 0 | D30: 0 | E30: 0 | F30: 1 | G30: 1 | H30: 1 | I30: 1 | J30: 1 | K30: 1 | L30: 1 | M30: 1 | N30: 0 | O30: 0 | P30: 0 | Q30: 1 | R30: 1 | S30: 1 | T30: 1 | U30: 1 | V30: 1 | W30: 1 | X30: 1 | Y30: 0
A31: Marketing Manager | B31: 110000 | C31: 0 | D31: 0 | E31: 0 | F31: 1 | G31: 1 | H31: 1 | I31: 1 | J31: 1 | K31: 1 | L31: 1 | M31: 1 | N31: 0 | O31: 0 | P31: 0 | Q31: 1 | R31: 1 | S31: 1 | T31: 1 | U31: 1 | V31: 1 | W31: 1 | X31: 1 | Y31: 0
A32: Client Success Manager | B32: 95000 | C32: 0 | D32: 0 | E32: 0 | F32: 0 | G32: 0 | H32: 1 | I32: 1 | J32: 1 | K32: 1 | L32: 1 | M32: 1 | N32: 0 | O32: 0 | P32: 0 | Q32: 0 | R32: 0 | S32: 1 | T32: 1 | U32: 1 | V32: 1 | W32: 1 | X32: 1 | Y32: 0
A33: Operations Manager | B33: 100000 | C33: 0 | D33: 0 | E33: 0 | F33: 0 | G33: 0 | H33: 0 | I33: 0 | J33: 1 | K33: 1 | L33: 1 | M33: 1 | N33: 0 | O33: 0 | P33: 0 | Q33: 0 | R33: 0 | S33: 1 | T33: 1 | U33: 1 | V33: 1 | W33: 1 | X33: 1 | Y33: 0.33333333
A34: Executive Assistant / Ops (0.5 FTE from H1 2027) | B34: 55000 | C34: 0 | D34: 0.545 | E34: 0.545 | F34: 1 | G34: 1 | H34: 1 | I34: 1 | J34: 1 | K34: 1 | L34: 1 | M34: 1 | N34: 0 | O34: 1 | P34: 1 | Q34: 1 | R34: 1 | S34: 1 | T34: 1 | U34: 1 | V34: 1 | W34: 1 | X34: 1 | Y34: 0.27272727
A35: CMO (Kevin) Part-Time | B35: 48000 | C35: 0.5 | D35: 1 | E35: 1 | F35: 1 | G35: 1 | H35: 1 | I35: 1 | J35: 1 | K35: 1 | L35: 1 | M35: 1 | N35: 1 | O35: 1 | P35: 1 | Q35: 1 | R35: 1 | S35: 1 | T35: 1 | U35: 1 | V35: 1 | W35: 1 | X35: 1 | Y35: 0
A36: Founding Capital Markets Advisor (Bruce Fair, via Mench Capital) | B36: 72000 | C36: 0.5 | D36: 1 | E36: 1 | F36: 1 | G36: 1 | H36: 1 | I36: 1 | J36: 1 | K36: 1 | L36: 1 | M36: 1 | N36: 1 | O36: 1 | P36: 1 | Q36: 1 | R36: 1 | S36: 1 | T36: 1 | U36: 1 | V36: 1 | W36: 1 | X36: 1 | Y36: 0
A37: Advisory Council Retainer (Dean McCall) | B37: 60000 | C37: 0.5 | D37: 1 | E37: 1 | F37: 1 | G37: 1 | H37: 1 | I37: 1 | J37: 1 | K37: 1 | L37: 1 | M37: 1 | N37: 1 | O37: 1 | P37: 1 | Q37: 1 | R37: 1 | S37: 1 | T37: 1 | U37: 1 | V37: 1 | W37: 1 | X37: 1 | Y37: 0
A38: TOTAL HEADCOUNT (FTE) | C38: =C6+C7+C8+C9+C10+C12+C13+C14+C15+C16+C17+C18+C19+C20+C21+C22+C23+C25+C26+C27+C28+C30+C31+C32+C33+C34+C35+C36+C37 | D38: =D6+D7+D8+D9+D10+D12+D13+D14+D15+D16+D17+D18+D19+D20+D21+D22+D23+D25+D26+D27+D28+D30+D31+D32+D33+D34+D35+D36+D37 | E38: =E6+E7+E8+E9+E10+E12+E13+E14+E15+E16+E17+E18+E19+E20+E21+E22+E23+E25+E26+E27+E28+E30+E31+E32+E33+E34+E35+E36+E37 | F38: =F6+F7+F8+F9+F10+F12+F13+F14+F15+F16+F17+F18+F19+F20+F21+F22+F23+F25+F26+F27+F28+F30+F31+F32+F33+F34+F35+F36+F37 | G38: =G6+G7+G8+G9+G10+G12+G13+G14+G15+G16+G17+G18+G19+G20+G21+G22+G23+G25+G26+G27+G28+G30+G31+G32+G33+G34+G35+G36+G37 | H38: =H6+H7+H8+H9+H10+H12+H13+H14+H15+H16+H17+H18+H19+H20+H21+H22+H23+H25+H26+H27+H28+H30+H31+H32+H33+H34+H35+H36+H37 | I38: =I6+I7+I8+I9+I10+I12+I13+I14+I15+I16+I17+I18+I19+I20+I21+I22+I23+I25+I26+I27+I28+I30+I31+I32+I33+I34+I35+I36+I37 | J38: =J6+J7+J8+J9+J10+J12+J13+J14+J15+J16+J17+J18+J19+J20+J21+J22+J23+J25+J26+J27+J28+J30+J31+J32+J33+J34+J35+J36+J37 | ... X38: =X6+X7+X8+X9+X10+X12+X13+X14+X15+X16+X17+X18+X19+X20+X21+X22+X23+X25+X26+X27+X28+X30+X31+X32+X33+X34+X35+X36+X37
A39: TOTAL SEMI-ANNUAL COMPENSATION | C39: =($B6*C6/2+$B7*C7/2+$B8*C8/2+$B9*C9/2+$B10*C10/2+$B12*C12/2+$B13*C13/2+$B14*C14/2+$B15*C15/2+$B16*C16/2+$B17*C17/2+$B18*C18/2+$B19*C19/2+$B20*C20/2+$B21*C21/2+$B22*C22/2+$B23*C23/2+$B25*C25/2+$B26*C26/2+$B27*C27/2+$B28*C28/2+$B30*C30/2+$B31*C31/2+$B32*C32/2+$B33*C33/2+$B34*C34/2+$B35*C35/2+$B36*C36/2+$B37*C37/2) | D39: =($B6*D6/2+$B7*D7/2+$B8*D8/2+$B9*D9/2+$B10*D10/2+$B12*D12/2+$B13*D13/2+$B14*D14/2+$B15*D15/2+$B16*D16/2+$B17*D17/2+$B18*D18/2+$B19*D19/2+$B20*D20/2+$B21*D21/2+$B22*D22/2+$B23*D23/2+$B25*D25/2+$B26*D26/2+$B27*D27/2+$B28*D28/2+$B30*D30/2+$B31*D31/2+$B32*D32/2+$B33*D33/2+$B34*D34/2+$B35*D35/2+$B36*D36/2+$B37*D37/2) | E39: =($B6*E6/2+$B7*E7/2+$B8*E8/2+$B9*E9/2+$B10*E10/2+$B12*E12/2+$B13*E13/2+$B14*E14/2+$B15*E15/2+$B16*E16/2+$B17*E17/2+$B18*E18/2+$B19*E19/2+$B20*E20/2+$B21*E21/2+$B22*E22/2+$B23*E23/2+$B25*E25/2+$B26*E26/2+$B27*E27/2+$B28*E28/2+$B30*E30/2+$B31*E31/2+$B32*E32/2+$B33*E33/2+$B34*E34/2+$B35*E35/2+$B36*E36/2+$B37*E37/2) | F39: =($B6*F6/2+$B7*F7/2+$B8*F8/2+$B9*F9/2+$B10*F10/2+$B12*F12/2+$B13*F13/2+$B14*F14/2+$B15*F15/2+$B16*F16/2+$B17*F17/2+$B18*F18/2+$B19*F19/2+$B20*F20/2+$B21*F21/2+$B22*F22/2+$B23*F23/2+$B25*F25/2+$B26*F26/2+$B27*F27/2+$B28*F28/2+$B30*F30/2+$B31*F31/2+$B32*F32/2+$B33*F33/2+$B34*F34/2+$B35*F35/2+$B36*F36/2+$B37*F37/2) | G39: =($B6*G6/2+$B7*G7/2+$B8*G8/2+$B9*G9/2+$B10*G10/2+$B12*G12/2+$B13*G13/2+$B14*G14/2+$B15*G15/2+$B16*G16/2+$B17*G17/2+$B18*G18/2+$B19*G19/2+$B20*G20/2+$B21*G21/2+$B22*G22/2+$B23*G23/2+$B25*G25/2+$B26*G26/2+$B27*G27/2+$B28*G28/2+$B30*G30/2+$B31*G31/2+$B32*G32/2+$B33*G33/2+$B34*G34/2+$B35*G35/2+$B36*G36/2+$B37*G37/2) | H39: =($B6*H6/2+$B7*H7/2+$B8*H8/2+$B9*H9/2+$B10*H10/2+$B12*H12/2+$B13*H13/2+$B14*H14/2+$B15*H15/2+$B16*H16/2+$B17*H17/2+$B18*H18/2+$B19*H19/2+$B20*H20/2+$B21*H21/2+$B22*H22/2+$B23*H23/2+$B25*H25/2+$B26*H26/2+$B27*H27/2+$B28*H28/2+$B30*H30/2+$B31*H31/2+$B32*H32/2+$B33*H33/2+$B34*H34/2+$B35*H35/2+$B36*H36/2+$B37*H37/2) | I39: =($B6*I6/2+$B7*I7/2+$B8*I8/2+$B9*I9/2+$B10*I10/2+$B12*I12/2+$B13*I13/2+$B14*I14/2+$B15*I15/2+$B16*I16/2+$B17*I17/2+$B18*I18/2+$B19*I19/2+$B20*I20/2+$B21*I21/2+$B22*I22/2+$B23*I23/2+$B25*I25/2+$B26*I26/2+$B27*I27/2+$B28*I28/2+$B30*I30/2+$B31*I31/2+$B32*I32/2+$B33*I33/2+$B34*I34/2+$B35*I35/2+$B36*I36/2+$B37*I37/2) | J39: =($B6*J6/2+$B7*J7/2+$B8*J8/2+$B9*J9/2+$B10*J10/2+$B12*J12/2+$B13*J13/2+$B14*J14/2+$B15*J15/2+$B16*J16/2+$B17*J17/2+$B18*J18/2+$B19*J19/2+$B20*J20/2+$B21*J21/2+$B22*J22/2+$B23*J23/2+$B25*J25/2+$B26*J26/2+$B27*J27/2+$B28*J28/2+$B30*J30/2+$B31*J31/2+$B32*J32/2+$B33*J33/2+$B34*J34/2+$B35*J35/2+$B36*J36/2+$B37*J37/2) | ... X39: =($B6*X6/2+$B7*X7/2+$B8*X8/2+$B9*X9/2+$B10*X10/2+$B12*X12/2+$B13*X13/2+$B14*X14/2+$B15*X15/2+$B16*X16/2+$B17*X17/2+$B18*X18/2+$B19*X19/2+$B20*X20/2+$B21*X21/2+$B22*X22/2+$B23*X23/2+$B25*X25/2+$B26*X26/2+$B27*X27/2+$B28*X28/2+$B30*X30/2+$B31*X31/2+$B32*X32/2+$B33*X33/2+$B34*X34/2+$B35*X35/2+$B36*X36/2+$B37*X37/2)
A40: platform SAVINGS (Traditional - the platform Build) | C40: =N39-C39 | D40: =O39-D39 | E40: =P39-E39 | F40: =Q39-F39 | G40: =R39-G39 | H40: =S39-H39 | I40: =T39-I39 | J40: =U39-J39 | ... M40: =X39-M39

Sheet DevEx - Build Costs
A1: 4ORM FINANCE - DEVELOPMENT EXPENSES | SPEER + INTERNAL | EFFICIENT BUILD vs TRADITIONAL
A2: SPEER contracted at $317,304 (3 phases, 13 months). Deposit Sept 1 2026 + 12 monthly installments through Sept 2027. the platform Build reduces internal DevEx via toolchain.
A4: Category / Item | B4: Build Option | C4: H2 2026 | D4: H1 2027 | E4: H2 2027 | F4: H1 2028 | G4: H2 2028 | H4: H1 2029 | I4: H2 2029 | J4: H1 2030 | K4: H2 2030 | L4: H1 2031 | M4: H2 2031 | N4: Total
A5: SPEER ENGINEERING - CONTRACTED BUILD
A6: Phase 1: Discovery & Architecture (1-2 mo) | B6: SPEER | C6: =IF('Control Panel'!$B$22=1,31200,0) | D6: 0 | E6: 0 | F6: 0 | G6: 0 | H6: 0 | I6: 0 | J6: 0 | K6: 0 | L6: 0 | M6: 0 | N6: =SUM(C6:M6)
A7: Phase 2: MVP Design & Dev (3-5 mo) | B7: SPEER | C7: =IF('Control Panel'!$B$22=1,91650,0) | D7: =IF('Control Panel'!$B$22=1,1950,0) | E7: 0 | F7: 0 | G7: 0 | H7: 0 | I7: 0 | J7: 0 | K7: 0 | L7: 0 | M7: 0 | N7: =SUM(C7:M7)
A8: Phase 3: Continued Dev & Integration (3-6 mo) | B8: SPEER | C8: 0 | D8: =IF('Control Panel'!$B$22=1,103350,0) | E8: =IF('Control Panel'!$B$22=1,52650,0) | F8: 0 | G8: 0 | H8: 0 | I8: 0 | J8: 0 | K8: 0 | L8: 0 | M8: 0 | N8: =SUM(C8:M8)
A9: HST 13% on SPEER (auto-calculated) | B9: Tax | C9: =IF('Control Panel'!$B$22=1,(C6+C7+C8)*0.13,0) | D9: =IF('Control Panel'!$B$22=1,(D6+D7+D8)*0.13,0) | E9: =IF('Control Panel'!$B$22=1,(E6+E7+E8)*0.13,0) | F9: =IF('Control Panel'!$B$22=1,(F6+F7+F8)*0.13,0) | G9: =IF('Control Panel'!$B$22=1,(G6+G7+G8)*0.13,0) | H9: =IF('Control Panel'!$B$22=1,(H6+H7+H8)*0.13,0) | I9: =IF('Control Panel'!$B$22=1,(I6+I7+I8)*0.13,0) | J9: =IF('Control Panel'!$B$22=1,(J6+J7+J8)*0.13,0) | ... M9: =IF('Control Panel'!$B$22=1,(M6+M7+M8)*0.13,0) | N9: =SUM(C9:M9)
A10: SPEER Fractional CTO (Option A) | B10: SPEER | C10: 0 | D10: =18000*'Control Panel'!$B$23 | E10: =18000*'Control Panel'!$B$23 | F10: =18000*'Control Panel'!$B$23 | G10: =18000*'Control Panel'!$B$23 | H10: =18000*'Control Panel'!$B$23 | I10: =18000*'Control Panel'!$B$23 | J10: 0 | K10: 0 | L10: 0 | M10: 0 | N10: =SUM(C10:M10)
A11: Chain abstraction layer (internal) | B11: Internal | C11: 40000 | D11: 0 | E11: 0 | F11: 0 | G11: 0 | H11: 0 | I11: 0 | J11: 0 | K11: 0 | L11: 0 | M11: 0 | N11: =SUM(C11:M11)
A12: INTERNAL PLATFORM BUILD (platform Build)
A13: Core exchange engine (matching, order book) | B13: Internal | C13: =IF('Control Panel'!$B$22=1,0,80000) | D13: =IF('Control Panel'!$B$22=1,0,50000) | E13: 0 | F13: 0 | G13: 0 | H13: 0 | I13: 0 | J13: 0 | K13: 0 | L13: 0 | M13: 0 | N13: =SUM(C13:M13)
A14: Smart contract development (patent-differentiated) | B14: Internal | C14: =IF('Control Panel'!$B$22=1,30000,60000) | D14: =IF('Control Panel'!$B$22=1,0,40000) | E14: 0 | F14: 0 | G14: 0 | H14: 0 | I14: 0 | J14: 0 | K14: 0 | L14: 0 | M14: 0 | N14: =SUM(C14:M14)
A15: KYC/AML integration (Deferred - iComply partnership Phase 2) | B15: Vendor+Internal | C15: 0 | D15: 0 | E15: 0 | F15: 30000 | G15: 30000 | H15: 0 | I15: 0 | J15: 0 | K15: 0 | L15: 0 | M15: 0 | N15: =SUM(C15:M15)
A16: Custody integration (Deferred - Phase 2) | B16: Vendor+Internal | C16: 0 | D16: 0 | E16: 0 | F16: 50000 | G16: 30000 | H16: 0 | I16: 0 | J16: 0 | K16: 0 | L16: 0 | M16: 0 | N16: =SUM(C16:M16)
A17: (reserved slot) | C17: 0 | D17: 0 | E17: 0 | F17: 0 | G17: 0 | H17: 0 | I17: 0 | J17: 0 | K17: 0 | L17: 0 | M17: 0 | N17: =SUM(C17:M17)
A18: Secondary market / trading engine | B18: Internal | C18: 0 | D18: =IF('Control Panel'!$B$22=1,0,25000) | E18: =IF('Control Panel'!$B$22=1,0,25000) | F18: =IF('Control Panel'!$B$22=1,0,35000) | G18: =IF('Control Panel'!$B$22=1,0,35000) | H18: 0 | I18: 0 | J18: 0 | K18: 0 | L18: 0 | M18: 0 | N18: =SUM(C18:M18)
A19: Mobile app development | B19: Internal | C19: 0 | D19: 0 | E19: 0 | F19: 37500 | G19: 37500 | H19: 20000 | I19: 20000 | J19: 0 | K19: 0 | L19: 0 | M19: 0 | N19: =SUM(C19:M19)
A20: Multi-chain expansion | B20: Internal | C20: 0 | D20: 0 | E20: 0 | F20: 0 | G20: 0 | H20: 25000 | I20: 25000 | J20: 17500 | K20: 17500 | L20: 0 | M20: 0 | N20: =SUM(C20:M20)
A21: API marketplace for FI integrations | B21: Internal | C21: 0 | D21: 0 | E21: 0 | F21: 0 | G21: 0 | H21: =IF('Control Panel'!$B$22=1,0,20000) | I21: =IF('Control Panel'!$B$22=1,0,20000) | J21: =IF('Control Panel'!$B$22=1,0,12500) | K21: =IF('Control Panel'!$B$22=1,0,12500) | L21: 0 | M21: 0 | N21: =SUM(C21:M21)
A22: Alberta Sandbox admission prep | B22: Internal | C22: 30000 | D22: 20000 | E22: 0 | F22: 0 | G22: 0 | H22: 0 | I22: 0 | J22: 0 | K22: 0 | L22: 0 | M22: 0 | N22: =SUM(C22:M22)
A23: SECURITY & AUDIT
A24: Smart contract audit (initial - Trail of Bits) | B24: External | C24: 0 | D24: 0 | E24: 0 | F24: 80000 | G24: 0 | H24: 0 | I24: 0 | J24: 0 | K24: 0 | L24: 0 | M24: 0 | N24: =SUM(C24:M24)
A25: Smart contract audit (annual re-audit) | B25: External | C25: 0 | D25: 25000 | E25: 25000 | F25: 25000 | G25: 25000 | H25: 25000 | I25: 25000 | J25: 25000 | K25: 25000 | L25: 25000 | M25: 25000 | N25: =SUM(C25:M25)
A26: Penetration testing (initial) | B26: External | C26: 0 | D26: 0 | E26: 0 | F26: 40000 | G26: 0 | H26: 0 | I26: 0 | J26: 0 | K26: 0 | L26: 0 | M26: 0 | N26: =SUM(C26:M26)
A27: Penetration testing (annual) | B27: External | C27: 0 | D27: 12500 | E27: 12500 | F27: 12500 | G27: 12500 | H27: 12500 | I27: 12500 | J27: 12500 | K27: 12500 | L27: 12500 | M27: 12500 | N27: =SUM(C27:M27)
A28: SOC 2 Type II certification | B28: External | C28: 0 | D28: 0 | E28: 0 | F28: 0 | G28: 30000 | H28: 30000 | I28: 0 | J28: 0 | K28: 0 | L28: 0 | M28: 0 | N28: =SUM(C28:M28)
A29: Patent provisional filings | B29: Legal+Filing | C29: 15000 | D29: 0 | E29: 0 | F29: 0 | G29: 0 | H29: 0 | I29: 0 | J29: 0 | K29: 0 | L29: 0 | M29: 0 | N29: =SUM(C29:M29)
A30: REGULATORY & LICENSING (ONE-TIME)
A31: CIRO dealer registration (application) | B31: Legal+Filing | C31: 0 | D31: 0 | E31: 0 | F31: 150000 | G31: 50000 | H31: 50000 | I31: 0 | J31: 0 | K31: 0 | L31: 0 | M31: 0 | N31: =SUM(C31:M31)
A32: CSA prospectus / exemption filing | B32: Legal | C32: 0 | D32: 0 | E32: 0 | F32: 80000 | G32: 20000 | H32: 20000 | I32: 0 | J32: 0 | K32: 0 | L32: 0 | M32: 0 | N32: =SUM(C32:M32)
A33: Legal structuring (token legal opinion) | B33: External | C33: 30000 | D33: 0 | E33: 0 | F33: 30000 | G33: 15000 | H33: 15000 | I33: 0 | J33: 0 | K33: 0 | L33: 0 | M33: 0 | N33: =SUM(C33:M33)
A34: Provincial registrations (AB, BC) | B34: Filing | C34: 10000 | D34: 0 | E34: 0 | F34: 15000 | G34: 0 | H34: 0 | I34: 0 | J34: 0 | K34: 0 | L34: 0 | M34: 0 | N34: =SUM(C34:M34)
A35: TOTAL DevEx (platform Build) | C35: =C6+C7+C8+C9+C10+C11+C13+C14+C15+C16+C17+C18+C19+C20+C21+C22+C24+C25+C26+C27+C28+C29+C31+C32+C33+C34 | D35: =D6+D7+D8+D9+D10+D11+D13+D14+D15+D16+D17+D18+D19+D20+D21+D22+D24+D25+D26+D27+D28+D29+D31+D32+D33+D34 | E35: =E6+E7+E8+E9+E10+E11+E13+E14+E15+E16+E17+E18+E19+E20+E21+E22+E24+E25+E26+E27+E28+E29+E31+E32+E33+E34 | F35: =F6+F7+F8+F9+F10+F11+F13+F14+F15+F16+F17+F18+F19+F20+F21+F22+F24+F25+F26+F27+F28+F29+F31+F32+F33+F34 | G35: =G6+G7+G8+G9+G10+G11+G13+G14+G15+G16+G17+G18+G19+G20+G21+G22+G24+G25+G26+G27+G28+G29+G31+G32+G33+G34 | H35: =H6+H7+H8+H9+H10+H11+H13+H14+H15+H16+H17+H18+H19+H20+H21+H22+H24+H25+H26+H27+H28+H29+H31+H32+H33+H34 | I35: =I6+I7+I8+I9+I10+I11+I13+I14+I15+I16+I17+I18+I19+I20+I21+I22+I24+I25+I26+I27+I28+I29+I31+I32+I33+I34 | J35: =J6+J7+J8+J9+J10+J11+J13+J14+J15+J16+J17+J18+J19+J20+J21+J22+J24+J25+J26+J27+J28+J29+J31+J32+J33+J34 | ... M35: =M6+M7+M8+M9+M10+M11+M13+M14+M15+M16+M17+M18+M19+M20+M21+M22+M24+M25+M26+M27+M28+M29+M31+M32+M33+M34 | N35: =SUM(C35:M35)
A36: TOTAL DevEx (Traditional Build - +35% internal) | C36: =C35*1.35 | D36: =D35*1.35 | E36: =E35*1.35 | F36: =F35*1.35 | G36: =G35*1.35 | H36: =H35*1.35 | I36: =I35*1.35 | J36: =J35*1.35 | ... M36: =M35*1.35 | N36: =SUM(C36:M36)
A37: EFFICIENT BUILD SAVINGS | C37: =C36-C35 | D37: =D36-D35 | E37: =E36-E35 | F37: =F36-F35 | G37: =G36-G35 | H37: =H36-H35 | I37: =I36-I35 | J37: =J36-J35 | ... M37: =M36-M35

Sheet OpEx - Ongoing
A1: 4ORM FINANCE - OPERATING EXPENSES | the platform BUILD vs TRADITIONAL COMPARE
A2: platform Build = lower team cost, higher tooling | Traditional = full team, no tooling
A4: Category / Item | B4: Escalation | C4: platform H2 2026 | D4: platform H1 2027 | E4: platform H2 2027 | F4: platform H1 2028 | G4: platform H2 2028 | H4: platform H1 2029 | I4: platform H2 2029 | J4: platform H1 2030 | K4: platform H2 2030 | L4: platform H1 2031 | M4: platform H2 2031 | N4: Trad Delta | O4: Notes
A5: TEAM COMPENSATION (platform Build)
A6: Team Comp (linked to Team Roadmap row 39 - the platform Build) | B6: 3% raises/yr | C6: ='Team Roadmap'!C39 | D6: ='Team Roadmap'!D39 | E6: ='Team Roadmap'!E39 | F6: ='Team Roadmap'!F39 | G6: ='Team Roadmap'!G39 | H6: ='Team Roadmap'!H39 | I6: ='Team Roadmap'!I39 | J6: ='Team Roadmap'!J39 | ... M6: ='Team Roadmap'!M39 | O6: efficiency-augmented team
A7: Benefits & Payroll Tax (rate in B7) | B7: 0.18 | C7: =C6*$B$7 | D7: =D6*$B$7 | E7: =E6*$B$7 | F7: =F6*$B$7 | G7: =G6*$B$7 | H7: =H6*$B$7 | I7: =I6*$B$7 | J7: =J6*$B$7 | ... M7: =M6*$B$7 | O7: CPP, EI, health, RRSP
A8: Advisor cash retainers (memo - included in Team Comp above) | B8: 3% raises/yr | C8: 0 | D8: 0 | E8: 0 | F8: 0 | G8: 0 | H8: 0 | I8: 0 | J8: 0 | K8: 0 | L8: 0 | M8: 0 | O8: Bruce+Dean+CFO+Kevin PT (already in Team Roadmap)
A9: DEVELOPER TOOLING & PLATFORMS
A10: GitHub Copilot Business (5-8 seats) | B10: 5%/yr | C10: 2850 | D10: 2850 | E10: 2850 | F10: 2992 | G10: 2992 | H10: 3142 | I10: 3142 | J10: 3300 | K10: 3300 | L10: 3464 | M10: 3464 | N10: -$6.9K
A11: Cursor Pro (5-8 seats) | B11: 5%/yr | C11: 600 | D11: 600 | E11: 600 | F11: 630 | G11: 630 | H11: 662 | I11: 662 | J11: 694 | K11: 694 | L11: 730 | M11: 730 | N11: -$1.5K
A12: Snyk (Team) | B12: 5%/yr | C12: 3000 | D12: 3000 | E12: 3000 | F12: 3150 | G12: 3150 | H12: 3308 | I12: 3308 | J12: 3473 | K12: 3473 | L12: 3646 | M12: 3646 | N12: -$7.3K
A13: Codiumplatform + CodeRabbit | B13: 5%/yr | C13: 2100 | D13: 2100 | E13: 2100 | F13: 2205 | G13: 2205 | H13: 2316 | I13: 2316 | J13: 2431 | K13: 2431 | L13: 2552 | M13: 2552 | N13: -$5.1K
A14: Datadog (Pro) | B14: 10%/yr | C14: 9000 | D14: 9000 | E14: 9000 | F14: 9900 | G14: 9900 | H14: 10890 | I14: 10890 | J14: 11979 | K14: 11979 | L14: 13177 | M14: 13177 | N14: $0 | O14: Needed either way
A15: Claude API + Openplatform API | B15: 12%/yr | C15: 4800 | D15: 4800 | E15: 4800 | F15: 5376 | G15: 5376 | H15: 6021 | I15: 6021 | J15: 6744 | K15: 6744 | L15: 7553 | M15: 7553 | N15: -$15.1K
A16: Mintlify + v0 Vercel | B16: 5%/yr | C16: 1020 | D16: 1020 | E16: 1020 | F16: 1071 | G16: 1071 | H16: 1124 | I16: 1124 | J16: 1181 | K16: 1181 | L16: 1240 | M16: 1240 | N16: -$2.5K
A17: REGULATORY & COMPLIANCE
A18: CIRO/CSA annual fees | B18: 3%/yr | C18: 0 | D18: 0 | E18: 0 | F18: 0 | G18: 30900 | H18: 31827 | I18: 31827 | J18: 32782 | K18: 32782 | L18: 33766 | M18: 33766 | N18: $0
A19: External legal counsel | B19: 5%/yr | C19: 50000 | D19: 50000 | E19: 50000 | F19: 52500 | G19: 52500 | H19: 55125 | I19: 55125 | J19: 57882 | K19: 57882 | L19: 60776 | M19: 60776 | N19: $0
A20: Audit & accounting | B20: 5%/yr | C20: 30000 | D20: 30000 | E20: 37500 | F20: 39375 | G20: 39375 | H20: 41344 | I20: 41344 | J20: 43411 | K20: 43411 | L20: 45582 | M20: 45582 | N20: $0
A21: Compliance software (Chainalysis) | B21: 8%/yr | C21: 0 | D21: 0 | E21: 0 | F21: 0 | G21: 27000 | H21: 29160 | I21: 29160 | J21: 31493 | K21: 31493 | L21: 34012 | M21: 34012 | N21: $0
A22: Insurance (D&O, E&O, Cyber) | B22: 10%/yr | C22: 30000 | D22: 30000 | E22: 50000 | F22: 55000 | G22: 55000 | H22: 60500 | I22: 60500 | J22: 66550 | K22: 66550 | L22: 73205 | M22: 73205 | N22: $0
A23: Licensing & reg filings | B23: 3%/yr | C23: 5000 | D23: 5000 | E23: 7500 | F23: 7725 | G23: 7725 | H23: 7957 | I23: 7957 | J23: 8196 | K23: 8196 | L23: 8441 | M23: 8441 | N23: $0
A24: TECHNOLOGY & INFRASTRUCTURE
A25: Cloud hosting (AWS/Azure) | B25: 15%/yr | C25: 18000 | D25: 18000 | E25: 18000 | F25: 20700 | G25: 20700 | H25: 23805 | I25: 23805 | J25: 27376 | K25: 27376 | L25: 31482 | M25: 31482 | N25: $0
A26: Blockchain infra (nodes/RPC) | B26: 10%/yr | C26: 12000 | D26: 12000 | E26: 12000 | F26: 13200 | G26: 13200 | H26: 14520 | I26: 14520 | J26: 15972 | K26: 15972 | L26: 17569 | M26: 17569 | N26: $0
A27: API & data services | B27: 5%/yr | C27: 6000 | D27: 6000 | E27: 6000 | F27: 6300 | G27: 6300 | H27: 6615 | I27: 6615 | J27: 6946 | K27: 6946 | L27: 7293 | M27: 7293 | N27: $0
A28: Cybersecurity & monitoring | B28: 8%/yr | C28: 9000 | D28: 9000 | E28: 9000 | F28: 9720 | G28: 9720 | H28: 10498 | I28: 10498 | J28: 11338 | K28: 11338 | L28: 12244 | M28: 12244 | N28: $0
A29: DR, backups, CDN, SSL | B29: 4%/yr | C29: 6000 | D29: 6000 | E29: 6000 | F29: 6240 | G29: 6240 | H29: 6490 | I29: 6490 | J29: 6749 | K29: 6749 | L29: 7019 | M29: 7019 | N29: $0
A30: OPERATIONS & OVERHEAD
A31: Office rent & utilities | B31: 5%/yr | C31: 12000 | D31: 12000 | E31: 18000 | F31: 24000 | G31: 24000 | H31: 30000 | I31: 30000 | J31: 36000 | K31: 36000 | L31: 42000 | M31: 42000 | N31: +$12K/yr
A32: Travel & conferences | B32: 10%/yr | C32: 10000 | D32: 10000 | E32: 7500 | F32: 10000 | G32: 10000 | H32: 12500 | I32: 12500 | J32: 15000 | K32: 15000 | L32: 17500 | M32: 17500 | N32: $0
A33: Marketing & BD | B33: 25%/yr | C33: 10000 | D33: 10000 | E33: 7500 | F33: 12500 | G33: 12500 | H33: 20000 | I33: 20000 | J33: 30000 | K33: 30000 | L33: 40000 | M33: 40000 | N33: $0
A34: HR & recruitment | B34: 20%/yr | C34: 2000 | D34: 2000 | E34: 5000 | F34: 7500 | G34: 7500 | H34: 10000 | I34: 10000 | J34: 15000 | K34: 15000 | L34: 20000 | M34: 20000 | N34: +$15K/yr
A35: Office supplies & misc. | B35: 5%/yr | C35: 2000 | D35: 2000 | E35: 2500 | F35: 3000 | G35: 3000 | H35: 3750 | I35: 3750 | J35: 4500 | K35: 4500 | L35: 5000 | M35: 5000 | N35: $0
A36: Software subs (general) | B36: 5%/yr | C36: 5000 | D36: 5000 | E36: 7760 | F36: 8148 | G36: 8148 | H36: 8556 | I36: 8556 | J36: 8983 | K36: 8983 | L36: 9432 | M36: 9432 | N36: $0
A37: SR&ED Tax Credit (gated by CP toggle B24) | B37: - | C37: =-10000*'Control Panel'!$B$24 | D37: =-10000*'Control Panel'!$B$24 | E37: =-15000*'Control Panel'!$B$24 | F37: =-15000*'Control Panel'!$B$24 | G37: =-15000*'Control Panel'!$B$24 | H37: =-12500*'Control Panel'!$B$24 | I37: =-12500*'Control Panel'!$B$24 | J37: =-10000*'Control Panel'!$B$24 | K37: =-10000*'Control Panel'!$B$24 | L37: =-7500*'Control Panel'!$B$24 | M37: =-7500*'Control Panel'!$B$24 | N37: $0 | O37: Est. 15-20% of eligible R&D
A38: TOTAL OpEx (platform Build) | C38: =C6+C7+C8+C10+C11+C12+C13+C14+C15+C16+C18+C19+C20+C21+C22+C23+C25+C26+C27+C28+C29+C31+C32+C33+C34+C35+C36+C37 | D38: =D6+D7+D8+D10+D11+D12+D13+D14+D15+D16+D18+D19+D20+D21+D22+D23+D25+D26+D27+D28+D29+D31+D32+D33+D34+D35+D36+D37 | E38: =E6+E7+E8+E10+E11+E12+E13+E14+E15+E16+E18+E19+E20+E21+E22+E23+E25+E26+E27+E28+E29+E31+E32+E33+E34+E35+E36+E37 | F38: =F6+F7+F8+F10+F11+F12+F13+F14+F15+F16+F18+F19+F20+F21+F22+F23+F25+F26+F27+F28+F29+F31+F32+F33+F34+F35+F36+F37 | G38: =G6+G7+G8+G10+G11+G12+G13+G14+G15+G16+G18+G19+G20+G21+G22+G23+G25+G26+G27+G28+G29+G31+G32+G33+G34+G35+G36+G37 | H38: =H6+H7+H8+H10+H11+H12+H13+H14+H15+H16+H18+H19+H20+H21+H22+H23+H25+H26+H27+H28+H29+H31+H32+H33+H34+H35+H36+H37 | I38: =I6+I7+I8+I10+I11+I12+I13+I14+I15+I16+I18+I19+I20+I21+I22+I23+I25+I26+I27+I28+I29+I31+I32+I33+I34+I35+I36+I37 | J38: =J6+J7+J8+J10+J11+J12+J13+J14+J15+J16+J18+J19+J20+J21+J22+J23+J25+J26+J27+J28+J29+J31+J32+J33+J34+J35+J36+J37 | ... M38: =M6+M7+M8+M10+M11+M12+M13+M14+M15+M16+M18+M19+M20+M21+M22+M23+M25+M26+M27+M28+M29+M31+M32+M33+M34+M35+M36+M37
A39: TOTAL OpEx (Traditional - Trad comp from Roadmap, developer tooling zero) | C39: =C38-('Team Roadmap'!C39*(1+$B$7))+('Team Roadmap'!N39*(1+$B$7))-(C10+C11+C12+C13+C15+C16) | D39: =D38-('Team Roadmap'!D39*(1+$B$7))+('Team Roadmap'!O39*(1+$B$7))-(D10+D11+D12+D13+D15+D16) | E39: =E38-('Team Roadmap'!E39*(1+$B$7))+('Team Roadmap'!P39*(1+$B$7))-(E10+E11+E12+E13+E15+E16) | F39: =F38-('Team Roadmap'!F39*(1+$B$7))+('Team Roadmap'!Q39*(1+$B$7))-(F10+F11+F12+F13+F15+F16) | G39: =G38-('Team Roadmap'!G39*(1+$B$7))+('Team Roadmap'!R39*(1+$B$7))-(G10+G11+G12+G13+G15+G16) | H39: =H38-('Team Roadmap'!H39*(1+$B$7))+('Team Roadmap'!S39*(1+$B$7))-(H10+H11+H12+H13+H15+H16) | I39: =I38-('Team Roadmap'!I39*(1+$B$7))+('Team Roadmap'!T39*(1+$B$7))-(I10+I11+I12+I13+I15+I16) | J39: =J38-('Team Roadmap'!J39*(1+$B$7))+('Team Roadmap'!U39*(1+$B$7))-(J10+J11+J12+J13+J15+J16) | ... M39: =M38-('Team Roadmap'!M39*(1+$B$7))+('Team Roadmap'!X39*(1+$B$7))-(M10+M11+M12+M13+M15+M16)
A40: platform BUILD SEMI-ANNUAL SAVINGS | C40: =C39-C38 | D40: =D39-D38 | E40: =E39-E38 | F40: =F39-F38 | G40: =G39-G38 | H40: =H39-H38 | I40: =I39-I38 | J40: =J39-J38 | ... M40: =M39-M38
A42: CORPORATE STRUCTURE NOTE
A43: The above OpEx includes costs for operating 3 required corporate entities:
A44: • 4ORM Holdings Inc. (HoldCo) - IP ownership, parent company overhead
A45: • 4ORM Exchange Inc. (OpCo) - CIRO dealer, exchange operations, all regulatory costs
A46: • 4ORM Custody Inc. (CustodyCo) - Digital asset custody, SOC 2, security infrastructure
A47: • Regulatory/compliance, legal, audit, and insurance line items above cover all 3 entities.
A48: • CIRO custody framework (Feb 2026) requires custody to be legally separate from exchange.

Sheet Revenue Model
A1: 4ORM FINANCE - 5-YEAR REVENUE MODEL | 5 STREAMS + RESERVED 6TH STREAM (placeholder)
A2: Fee pool split model per Master Pro Forma | ALL CALCULATIONS DRIVEN BY CONTROL PANEL
A4: CONTROL PANEL REFERENCES (for transparency)
A5: ATB Financial - Base Data | B5: ='Control Panel'!B49 | C5: ='Control Panel'!C49 | D5: ='Control Panel'!D49 | E5: ='Control Panel'!E49
A6: Tokenization Rates | B6: ='Control Panel'!B27 | C6: ='Control Panel'!B28
A7: Deposit Turnover | B7: ='Control Panel'!B29
A8: Annual Growth | B8: ='Control Panel'!B30
A10: TOKENIZATION PARAMETERS & FEE STRUCTURE
A11: Stream | B11: Fee Rate (CP) | C11: 4ORM Split (CP) | D11: Description
A12: Settlement | B12: ='Control Panel'!B41 | C12: ='Control Panel'!C41 | D12: 1.5 bps of settlement volume
A13: Issuance | B13: ='Control Panel'!B42 | C13: ='Control Panel'!C42 | D13: 0.5% of issuance volume
A14: Trading | B14: ='Control Panel'!B43 | C14: ='Control Panel'!C43 | D14: 5 bps of trading volume
A15: Custody | B15: ='Control Panel'!B44 | C15: ='Control Panel'!C44 | D15: 30 bps of custody AUA
A16: SaaS + APIs | B16: ='Control Panel'!B45 | C16: ='Control Panel'!C45 | D16: Annual per enterprise client
A18: 5-YEAR REVENUE BY FINANCIAL INSTITUTION (SEMI-ANNUAL)
A19: Revenue Source | B19: Onboard | C19: H2 2026 | D19: H1 2027 | E19: H2 2027 | F19: H1 2028 | G19: H2 2028 | H19: H1 2029 | I19: H2 2029 | J19: H1 2030 | K19: H2 2030 | L19: H1 2031 | M19: H2 2031 | N19: 5-Year Total
A20: ATB FINANCIAL ($43.3B deposits)
A21: Settlement (1.5 bps, 30%) | B21: H1 2028 | C21: ='Control Panel'!$B$14*'Control Panel'!$B$6*'Control Panel'!B49*1000000*'Control Panel'!$B$29*IF('Control Panel'!$B$100=1,'Control Panel'!B$98,'Control Panel'!$B$27)*'Control Panel'!$B$41*'Control Panel'!$C$41*'Control Panel'!B$56*(1+IF('Control Panel'!$D$90=1,'Control Panel'!$C$90,'Control Panel'!$B$30))^MAX(0,(0-'Control Panel'!$F$49)/2)*0.5 | D21: ='Control Panel'!$B$14*'Control Panel'!$B$6*'Control Panel'!B49*1000000*'Control Panel'!$B$29*IF('Control Panel'!$B$100=1,'Control Panel'!C$98,'Control Panel'!$B$27)*'Control Panel'!$B$41*'Control Panel'!$C$41*'Control Panel'!C$56*(1+IF('Control Panel'!$D$90=1,'Control Panel'!$C$90,'Control Panel'!$B$30))^MAX(0,(1-'Control Panel'!$F$49)/2)*0.5 | E21: ='Control Panel'!$B$14*'Control Panel'!$B$6*'Control Panel'!B49*1000000*'Control Panel'!$B$29*IF('Control Panel'!$B$100=1,'Control Panel'!D$98,'Control Panel'!$B$27)*'Control Panel'!$B$41*'Control Panel'!$C$41*'Control Panel'!D$56*(1+IF('Control Panel'!$D$90=1,'Control Panel'!$C$90,'Control Panel'!$B$30))^MAX(0,(2-'Control Panel'!$F$49)/2)*0.5 | F21: ='Control Panel'!$B$14*'Control Panel'!$B$6*'Control Panel'!B49*1000000*'Control Panel'!$B$29*IF('Control Panel'!$B$100=1,'Control Panel'!E$98,'Control Panel'!$B$27)*'Control Panel'!$B$41*'Control Panel'!$C$41*'Control Panel'!E$56*(1+IF('Control Panel'!$D$90=1,'Control Panel'!$C$90,'Control Panel'!$B$30))^MAX(0,(3-'Control Panel'!$F$49)/2)*0.5 | G21: ='Control Panel'!$B$14*'Control Panel'!$B$6*'Control Panel'!B49*1000000*'Control Panel'!$B$29*IF('Control Panel'!$B$100=1,'Control Panel'!F$98,'Control Panel'!$B$27)*'Control Panel'!$B$41*'Control Panel'!$C$41*'Control Panel'!F$56*(1+IF('Control Panel'!$D$90=1,'Control Panel'!$C$90,'Control Panel'!$B$30))^MAX(0,(4-'Control Panel'!$F$49)/2)*0.5 | H21: ='Control Panel'!$B$14*'Control Panel'!$B$6*'Control Panel'!B49*1000000*'Control Panel'!$B$29*IF('Control Panel'!$B$100=1,'Control Panel'!G$98,'Control Panel'!$B$27)*'Control Panel'!$B$41*'Control Panel'!$C$41*'Control Panel'!G$56*(1+IF('Control Panel'!$D$90=1,'Control Panel'!$C$90,'Control Panel'!$B$30))^MAX(0,(5-'Control Panel'!$F$49)/2)*0.5 | I21: ='Control Panel'!$B$14*'Control Panel'!$B$6*'Control Panel'!B49*1000000*'Control Panel'!$B$29*IF('Control Panel'!$B$100=1,'Control Panel'!H$98,'Control Panel'!$B$27)*'Control Panel'!$B$41*'Control Panel'!$C$41*'Control Panel'!H$56*(1+IF('Control Panel'!$D$90=1,'Control Panel'!$C$90,'Control Panel'!$B$30))^MAX(0,(6-'Control Panel'!$F$49)/2)*0.5 | J21: ='Control Panel'!$B$14*'Control Panel'!$B$6*'Control Panel'!B49*1000000*'Control Panel'!$B$29*IF('Control Panel'!$B$100=1,'Control Panel'!I$98,'Control Panel'!$B$27)*'Control Panel'!$B$41*'Control Panel'!$C$41*'Control Panel'!I$56*(1+IF('Control Panel'!$D$90=1,'Control Panel'!$C$90,'Control Panel'!$B$30))^MAX(0,(7-'Control Panel'!$F$49)/2)*0.5 | K21: ='Control Panel'!$B$14*'Control Panel'!$B$6*'Control Panel'!B49*1000000*'Control Panel'!$B$29*IF('Control Panel'!$B$100=1,'Control Panel'!J$98,'Control Panel'!$B$27)*'Control Panel'!$B$41*'Control Panel'!$C$41*'Control Panel'!J$56*(1+IF('Control Panel'!$D$90=1,'Control Panel'!$C$90,'Control Panel'!$B$30))^MAX(0,(8-'Control Panel'!$F$49)/2)*0.5 | L21: ='Control Panel'!$B$14*'Control Panel'!$B$6*'Control Panel'!B49*1000000*'Control Panel'!$B$29*IF('Control Panel'!$B$100=1,'Control Panel'!K$98,'Control Panel'!$B$27)*'Control Panel'!$B$41*'Control Panel'!$C$41*'Control Panel'!K$56*(1+IF('Control Panel'!$D$90=1,'Control Panel'!$C$90,'Control Panel'!$B$30))^MAX(0,(9-'Control Panel'!$F$49)/2)*0.5 | M21: ='Control Panel'!$B$14*'Control Panel'!$B$6*'Control Panel'!B49*1000000*'Control Panel'!$B$29*IF('Control Panel'!$B$100=1,'Control Panel'!L$98,'Control Panel'!$B$27)*'Control Panel'!$B$41*'Control Panel'!$C$41*'Control Panel'!L$56*(1+IF('Control Panel'!$D$90=1,'Control Panel'!$C$90,'Control Panel'!$B$30))^MAX(0,(10-'Control Panel'!$F$49)/2)*0.5 | N21: =SUM(C21:M21)
A22: Issuance (0.5%, 60%) | B22: H1 2028 | C22: ='Control Panel'!$B$14*'Control Panel'!$B$7*'Control Panel'!C49*1000000*IF('Control Panel'!$B$100=1,'Control Panel'!B$99,'Control Panel'!$B$28)*'Control Panel'!$B$42*'Control Panel'!$C$42*'Control Panel'!B$56*(1+IF('Control Panel'!$D$90=1,'Control Panel'!$C$90,'Control Panel'!$B$30))^MAX(0,(0-'Control Panel'!$F$49)/2)*0.5 | D22: ='Control Panel'!$B$14*'Control Panel'!$B$7*'Control Panel'!C49*1000000*IF('Control Panel'!$B$100=1,'Control Panel'!C$99,'Control Panel'!$B$28)*'Control Panel'!$B$42*'Control Panel'!$C$42*'Control Panel'!C$56*(1+IF('Control Panel'!$D$90=1,'Control Panel'!$C$90,'Control Panel'!$B$30))^MAX(0,(1-'Control Panel'!$F$49)/2)*0.5 | E22: ='Control Panel'!$B$14*'Control Panel'!$B$7*'Control Panel'!C49*1000000*IF('Control Panel'!$B$100=1,'Control Panel'!D$99,'Control Panel'!$B$28)*'Control Panel'!$B$42*'Control Panel'!$C$42*'Control Panel'!D$56*(1+IF('Control Panel'!$D$90=1,'Control Panel'!$C$90,'Control Panel'!$B$30))^MAX(0,(2-'Control Panel'!$F$49)/2)*0.5 | F22: ='Control Panel'!$B$14*'Control Panel'!$B$7*'Control Panel'!C49*1000000*IF('Control Panel'!$B$100=1,'Control Panel'!E$99,'Control Panel'!$B$28)*'Control Panel'!$B$42*'Control Panel'!$C$42*'Control Panel'!E$56*(1+IF('Control Panel'!$D$90=1,'Control Panel'!$C$90,'Control Panel'!$B$30))^MAX(0,(3-'Control Panel'!$F$49)/2)*0.5 | G22: ='Control Panel'!$B$14*'Control Panel'!$B$7*'Control Panel'!C49*1000000*IF('Control Panel'!$B$100=1,'Control Panel'!F$99,'Control Panel'!$B$28)*'Control Panel'!$B$42*'Control Panel'!$C$42*'Control Panel'!F$56*(1+IF('Control Panel'!$D$90=1,'Control Panel'!$C$90,'Control Panel'!$B$30))^MAX(0,(4-'Control Panel'!$F$49)/2)*0.5 | H22: ='Control Panel'!$B$14*'Control Panel'!$B$7*'Control Panel'!C49*1000000*IF('Control Panel'!$B$100=1,'Control Panel'!G$99,'Control Panel'!$B$28)*'Control Panel'!$B$42*'Control Panel'!$C$42*'Control Panel'!G$56*(1+IF('Control Panel'!$D$90=1,'Control Panel'!$C$90,'Control Panel'!$B$30))^MAX(0,(5-'Control Panel'!$F$49)/2)*0.5 | I22: ='Control Panel'!$B$14*'Control Panel'!$B$7*'Control Panel'!C49*1000000*IF('Control Panel'!$B$100=1,'Control Panel'!H$99,'Control Panel'!$B$28)*'Control Panel'!$B$42*'Control Panel'!$C$42*'Control Panel'!H$56*(1+IF('Control Panel'!$D$90=1,'Control Panel'!$C$90,'Control Panel'!$B$30))^MAX(0,(6-'Control Panel'!$F$49)/2)*0.5 | J22: ='Control Panel'!$B$14*'Control Panel'!$B$7*'Control Panel'!C49*1000000*IF('Control Panel'!$B$100=1,'Control Panel'!I$99,'Control Panel'!$B$28)*'Control Panel'!$B$42*'Control Panel'!$C$42*'Control Panel'!I$56*(1+IF('Control Panel'!$D$90=1,'Control Panel'!$C$90,'Control Panel'!$B$30))^MAX(0,(7-'Control Panel'!$F$49)/2)*0.5 | K22: ='Control Panel'!$B$14*'Control Panel'!$B$7*'Control Panel'!C49*1000000*IF('Control Panel'!$B$100=1,'Control Panel'!J$99,'Control Panel'!$B$28)*'Control Panel'!$B$42*'Control Panel'!$C$42*'Control Panel'!J$56*(1+IF('Control Panel'!$D$90=1,'Control Panel'!$C$90,'Control Panel'!$B$30))^MAX(0,(8-'Control Panel'!$F$49)/2)*0.5 | L22: ='Control Panel'!$B$14*'Control Panel'!$B$7*'Control Panel'!C49*1000000*IF('Control Panel'!$B$100=1,'Control Panel'!K$99,'Control Panel'!$B$28)*'Control Panel'!$B$42*'Control Panel'!$C$42*'Control Panel'!K$56*(1+IF('Control Panel'!$D$90=1,'Control Panel'!$C$90,'Control Panel'!$B$30))^MAX(0,(9-'Control Panel'!$F$49)/2)*0.5 | M22: ='Control Panel'!$B$14*'Control Panel'!$B$7*'Control Panel'!C49*1000000*IF('Control Panel'!$B$100=1,'Control Panel'!L$99,'Control Panel'!$B$28)*'Control Panel'!$B$42*'Control Panel'!$C$42*'Control Panel'!L$56*(1+IF('Control Panel'!$D$90=1,'Control Panel'!$C$90,'Control Panel'!$B$30))^MAX(0,(10-'Control Panel'!$F$49)/2)*0.5 | N22: =SUM(C22:M22)
A23: Trading (5 bps, 100%) | B23: H1 2028 | C23: ='Control Panel'!$B$14*'Control Panel'!$B$8*'Control Panel'!C49*1000000*IF('Control Panel'!$B$100=1,'Control Panel'!B$99,'Control Panel'!$B$28)*'Control Panel'!$B$62*'Control Panel'!$B$43*'Control Panel'!$C$43*'Control Panel'!B$56*(1+IF('Control Panel'!$D$90=1,'Control Panel'!$C$90,'Control Panel'!$B$30))^MAX(0,(0-'Control Panel'!$F$49)/2)*0.5 | D23: ='Control Panel'!$B$14*'Control Panel'!$B$8*'Control Panel'!C49*1000000*IF('Control Panel'!$B$100=1,'Control Panel'!C$99,'Control Panel'!$B$28)*'Control Panel'!$B$62*'Control Panel'!$B$43*'Control Panel'!$C$43*'Control Panel'!C$56*(1+IF('Control Panel'!$D$90=1,'Control Panel'!$C$90,'Control Panel'!$B$30))^MAX(0,(1-'Control Panel'!$F$49)/2)*0.5 | E23: ='Control Panel'!$B$14*'Control Panel'!$B$8*'Control Panel'!C49*1000000*IF('Control Panel'!$B$100=1,'Control Panel'!D$99,'Control Panel'!$B$28)*'Control Panel'!$B$62*'Control Panel'!$B$43*'Control Panel'!$C$43*'Control Panel'!D$56*(1+IF('Control Panel'!$D$90=1,'Control Panel'!$C$90,'Control Panel'!$B$30))^MAX(0,(2-'Control Panel'!$F$49)/2)*0.5 | F23: ='Control Panel'!$B$14*'Control Panel'!$B$8*'Control Panel'!C49*1000000*IF('Control Panel'!$B$100=1,'Control Panel'!E$99,'Control Panel'!$B$28)*'Control Panel'!$B$62*'Control Panel'!$B$43*'Control Panel'!$C$43*'Control Panel'!E$56*(1+IF('Control Panel'!$D$90=1,'Control Panel'!$C$90,'Control Panel'!$B$30))^MAX(0,(3-'Control Panel'!$F$49)/2)*0.5 | G23: ='Control Panel'!$B$14*'Control Panel'!$B$8*'Control Panel'!C49*1000000*IF('Control Panel'!$B$100=1,'Control Panel'!F$99,'Control Panel'!$B$28)*'Control Panel'!$B$62*'Control Panel'!$B$43*'Control Panel'!$C$43*'Control Panel'!F$56*(1+IF('Control Panel'!$D$90=1,'Control Panel'!$C$90,'Control Panel'!$B$30))^MAX(0,(4-'Control Panel'!$F$49)/2)*0.5 | H23: ='Control Panel'!$B$14*'Control Panel'!$B$8*'Control Panel'!C49*1000000*IF('Control Panel'!$B$100=1,'Control Panel'!G$99,'Control Panel'!$B$28)*'Control Panel'!$B$62*'Control Panel'!$B$43*'Control Panel'!$C$43*'Control Panel'!G$56*(1+IF('Control Panel'!$D$90=1,'Control Panel'!$C$90,'Control Panel'!$B$30))^MAX(0,(5-'Control Panel'!$F$49)/2)*0.5 | I23: ='Control Panel'!$B$14*'Control Panel'!$B$8*'Control Panel'!C49*1000000*IF('Control Panel'!$B$100=1,'Control Panel'!H$99,'Control Panel'!$B$28)*'Control Panel'!$B$62*'Control Panel'!$B$43*'Control Panel'!$C$43*'Control Panel'!H$56*(1+IF('Control Panel'!$D$90=1,'Control Panel'!$C$90,'Control Panel'!$B$30))^MAX(0,(6-'Control Panel'!$F$49)/2)*0.5 | J23: ='Control Panel'!$B$14*'Control Panel'!$B$8*'Control Panel'!C49*1000000*IF('Control Panel'!$B$100=1,'Control Panel'!I$99,'Control Panel'!$B$28)*'Control Panel'!$B$62*'Control Panel'!$B$43*'Control Panel'!$C$43*'Control Panel'!I$56*(1+IF('Control Panel'!$D$90=1,'Control Panel'!$C$90,'Control Panel'!$B$30))^MAX(0,(7-'Control Panel'!$F$49)/2)*0.5 | K23: ='Control Panel'!$B$14*'Control Panel'!$B$8*'Control Panel'!C49*1000000*IF('Control Panel'!$B$100=1,'Control Panel'!J$99,'Control Panel'!$B$28)*'Control Panel'!$B$62*'Control Panel'!$B$43*'Control Panel'!$C$43*'Control Panel'!J$56*(1+IF('Control Panel'!$D$90=1,'Control Panel'!$C$90,'Control Panel'!$B$30))^MAX(0,(8-'Control Panel'!$F$49)/2)*0.5 | L23: ='Control Panel'!$B$14*'Control Panel'!$B$8*'Control Panel'!C49*1000000*IF('Control Panel'!$B$100=1,'Control Panel'!K$99,'Control Panel'!$B$28)*'Control Panel'!$B$62*'Control Panel'!$B$43*'Control Panel'!$C$43*'Control Panel'!K$56*(1+IF('Control Panel'!$D$90=1,'Control Panel'!$C$90,'Control Panel'!$B$30))^MAX(0,(9-'Control Panel'!$F$49)/2)*0.5 | M23: ='Control Panel'!$B$14*'Control Panel'!$B$8*'Control Panel'!C49*1000000*IF('Control Panel'!$B$100=1,'Control Panel'!L$99,'Control Panel'!$B$28)*'Control Panel'!$B$62*'Control Panel'!$B$43*'Control Panel'!$C$43*'Control Panel'!L$56*(1+IF('Control Panel'!$D$90=1,'Control Panel'!$C$90,'Control Panel'!$B$30))^MAX(0,(10-'Control Panel'!$F$49)/2)*0.5 | N23: =SUM(C23:M23)
A24: Custody (30 bps, 40%) | B24: H1 2028 | C24: ='Control Panel'!$B$14*'Control Panel'!$B$9*'Control Panel'!D49*1000000*IF('Control Panel'!$B$100=1,'Control Panel'!B$99,'Control Panel'!$B$28)*'Control Panel'!$B$44*'Control Panel'!$C$44*'Control Panel'!B$56*(1+IF('Control Panel'!$D$90=1,'Control Panel'!$C$90,'Control Panel'!$B$30))^MAX(0,(0-'Control Panel'!$F$49)/2)*0.5 | D24: ='Control Panel'!$B$14*'Control Panel'!$B$9*'Control Panel'!D49*1000000*IF('Control Panel'!$B$100=1,'Control Panel'!C$99,'Control Panel'!$B$28)*'Control Panel'!$B$44*'Control Panel'!$C$44*'Control Panel'!C$56*(1+IF('Control Panel'!$D$90=1,'Control Panel'!$C$90,'Control Panel'!$B$30))^MAX(0,(1-'Control Panel'!$F$49)/2)*0.5 | E24: ='Control Panel'!$B$14*'Control Panel'!$B$9*'Control Panel'!D49*1000000*IF('Control Panel'!$B$100=1,'Control Panel'!D$99,'Control Panel'!$B$28)*'Control Panel'!$B$44*'Control Panel'!$C$44*'Control Panel'!D$56*(1+IF('Control Panel'!$D$90=1,'Control Panel'!$C$90,'Control Panel'!$B$30))^MAX(0,(2-'Control Panel'!$F$49)/2)*0.5 | F24: ='Control Panel'!$B$14*'Control Panel'!$B$9*'Control Panel'!D49*1000000*IF('Control Panel'!$B$100=1,'Control Panel'!E$99,'Control Panel'!$B$28)*'Control Panel'!$B$44*'Control Panel'!$C$44*'Control Panel'!E$56*(1+IF('Control Panel'!$D$90=1,'Control Panel'!$C$90,'Control Panel'!$B$30))^MAX(0,(3-'Control Panel'!$F$49)/2)*0.5 | G24: ='Control Panel'!$B$14*'Control Panel'!$B$9*'Control Panel'!D49*1000000*IF('Control Panel'!$B$100=1,'Control Panel'!F$99,'Control Panel'!$B$28)*'Control Panel'!$B$44*'Control Panel'!$C$44*'Control Panel'!F$56*(1+IF('Control Panel'!$D$90=1,'Control Panel'!$C$90,'Control Panel'!$B$30))^MAX(0,(4-'Control Panel'!$F$49)/2)*0.5 | H24: ='Control Panel'!$B$14*'Control Panel'!$B$9*'Control Panel'!D49*1000000*IF('Control Panel'!$B$100=1,'Control Panel'!G$99,'Control Panel'!$B$28)*'Control Panel'!$B$44*'Control Panel'!$C$44*'Control Panel'!G$56*(1+IF('Control Panel'!$D$90=1,'Control Panel'!$C$90,'Control Panel'!$B$30))^MAX(0,(5-'Control Panel'!$F$49)/2)*0.5 | I24: ='Control Panel'!$B$14*'Control Panel'!$B$9*'Control Panel'!D49*1000000*IF('Control Panel'!$B$100=1,'Control Panel'!H$99,'Control Panel'!$B$28)*'Control Panel'!$B$44*'Control Panel'!$C$44*'Control Panel'!H$56*(1+IF('Control Panel'!$D$90=1,'Control Panel'!$C$90,'Control Panel'!$B$30))^MAX(0,(6-'Control Panel'!$F$49)/2)*0.5 | J24: ='Control Panel'!$B$14*'Control Panel'!$B$9*'Control Panel'!D49*1000000*IF('Control Panel'!$B$100=1,'Control Panel'!I$99,'Control Panel'!$B$28)*'Control Panel'!$B$44*'Control Panel'!$C$44*'Control Panel'!I$56*(1+IF('Control Panel'!$D$90=1,'Control Panel'!$C$90,'Control Panel'!$B$30))^MAX(0,(7-'Control Panel'!$F$49)/2)*0.5 | K24: ='Control Panel'!$B$14*'Control Panel'!$B$9*'Control Panel'!D49*1000000*IF('Control Panel'!$B$100=1,'Control Panel'!J$99,'Control Panel'!$B$28)*'Control Panel'!$B$44*'Control Panel'!$C$44*'Control Panel'!J$56*(1+IF('Control Panel'!$D$90=1,'Control Panel'!$C$90,'Control Panel'!$B$30))^MAX(0,(8-'Control Panel'!$F$49)/2)*0.5 | L24: ='Control Panel'!$B$14*'Control Panel'!$B$9*'Control Panel'!D49*1000000*IF('Control Panel'!$B$100=1,'Control Panel'!K$99,'Control Panel'!$B$28)*'Control Panel'!$B$44*'Control Panel'!$C$44*'Control Panel'!K$56*(1+IF('Control Panel'!$D$90=1,'Control Panel'!$C$90,'Control Panel'!$B$30))^MAX(0,(9-'Control Panel'!$F$49)/2)*0.5 | M24: ='Control Panel'!$B$14*'Control Panel'!$B$9*'Control Panel'!D49*1000000*IF('Control Panel'!$B$100=1,'Control Panel'!L$99,'Control Panel'!$B$28)*'Control Panel'!$B$44*'Control Panel'!$C$44*'Control Panel'!L$56*(1+IF('Control Panel'!$D$90=1,'Control Panel'!$C$90,'Control Panel'!$B$30))^MAX(0,(10-'Control Panel'!$F$49)/2)*0.5 | N24: =SUM(C24:M24)
A25: SaaS + APIs (80%) | B25: H1 2028 | C25: ='Control Panel'!$B$14*'Control Panel'!$B$10*'Control Panel'!E49*'Control Panel'!$B$45*'Control Panel'!$C$45*'Control Panel'!B$56*0.5 | D25: ='Control Panel'!$B$14*'Control Panel'!$B$10*'Control Panel'!E49*'Control Panel'!$B$45*'Control Panel'!$C$45*'Control Panel'!C$56*0.5 | E25: ='Control Panel'!$B$14*'Control Panel'!$B$10*'Control Panel'!E49*'Control Panel'!$B$45*'Control Panel'!$C$45*'Control Panel'!D$56*0.5 | F25: ='Control Panel'!$B$14*'Control Panel'!$B$10*'Control Panel'!E49*'Control Panel'!$B$45*'Control Panel'!$C$45*'Control Panel'!E$56*0.5 | G25: ='Control Panel'!$B$14*'Control Panel'!$B$10*'Control Panel'!E49*'Control Panel'!$B$45*'Control Panel'!$C$45*'Control Panel'!F$56*0.5 | H25: ='Control Panel'!$B$14*'Control Panel'!$B$10*'Control Panel'!E49*'Control Panel'!$B$45*'Control Panel'!$C$45*'Control Panel'!G$56*0.5 | I25: ='Control Panel'!$B$14*'Control Panel'!$B$10*'Control Panel'!E49*'Control Panel'!$B$45*'Control Panel'!$C$45*'Control Panel'!H$56*0.5 | J25: ='Control Panel'!$B$14*'Control Panel'!$B$10*'Control Panel'!E49*'Control Panel'!$B$45*'Control Panel'!$C$45*'Control Panel'!I$56*0.5 | K25: ='Control Panel'!$B$14*'Control Panel'!$B$10*'Control Panel'!E49*'Control Panel'!$B$45*'Control Panel'!$C$45*'Control Panel'!J$56*0.5 | L25: ='Control Panel'!$B$14*'Control Panel'!$B$10*'Control Panel'!E49*'Control Panel'!$B$45*'Control Panel'!$C$45*'Control Panel'!K$56*0.5 | M25: ='Control Panel'!$B$14*'Control Panel'!$B$10*'Control Panel'!E49*'Control Panel'!$B$45*'Control Panel'!$C$45*'Control Panel'!L$56*0.5 | N25: =SUM(C25:M25)
A26: ATB FINANCIAL SUBTOTAL | B26: H1 2028 | C26: =C21+C22+C23+C24+C25 | D26: =D21+D22+D23+D24+D25 | E26: =E21+E22+E23+E24+E25 | F26: =F21+F22+F23+F24+F25 | G26: =G21+G22+G23+G24+G25 | H26: =H21+H22+H23+H24+H25 | I26: =I21+I22+I23+I24+I25 | J26: =J21+J22+J23+J24+J25 | ... M26: =M21+M22+M23+M24+M25 | N26: =SUM(C26:M26)
A27: BOW VALLEY CREDIT UNION (~$2B)
A28: Settlement (1.5 bps, 30%) | B28: H1 2028 | C28: ='Control Panel'!$B$15*'Control Panel'!$B$6*'Control Panel'!B50*1000000*'Control Panel'!$B$29*IF('Control Panel'!$B$100=1,'Control Panel'!B$98,'Control Panel'!$B$27)*'Control Panel'!$B$41*'Control Panel'!$C$41*'Control Panel'!B$57*(1+IF('Control Panel'!$D$91=1,'Control Panel'!$C$91,'Control Panel'!$B$30))^MAX(0,(0-'Control Panel'!$F$50)/2)*0.5 | D28: ='Control Panel'!$B$15*'Control Panel'!$B$6*'Control Panel'!B50*1000000*'Control Panel'!$B$29*IF('Control Panel'!$B$100=1,'Control Panel'!C$98,'Control Panel'!$B$27)*'Control Panel'!$B$41*'Control Panel'!$C$41*'Control Panel'!C$57*(1+IF('Control Panel'!$D$91=1,'Control Panel'!$C$91,'Control Panel'!$B$30))^MAX(0,(1-'Control Panel'!$F$50)/2)*0.5 | E28: ='Control Panel'!$B$15*'Control Panel'!$B$6*'Control Panel'!B50*1000000*'Control Panel'!$B$29*IF('Control Panel'!$B$100=1,'Control Panel'!D$98,'Control Panel'!$B$27)*'Control Panel'!$B$41*'Control Panel'!$C$41*'Control Panel'!D$57*(1+IF('Control Panel'!$D$91=1,'Control Panel'!$C$91,'Control Panel'!$B$30))^MAX(0,(2-'Control Panel'!$F$50)/2)*0.5 | F28: ='Control Panel'!$B$15*'Control Panel'!$B$6*'Control Panel'!B50*1000000*'Control Panel'!$B$29*IF('Control Panel'!$B$100=1,'Control Panel'!E$98,'Control Panel'!$B$27)*'Control Panel'!$B$41*'Control Panel'!$C$41*'Control Panel'!E$57*(1+IF('Control Panel'!$D$91=1,'Control Panel'!$C$91,'Control Panel'!$B$30))^MAX(0,(3-'Control Panel'!$F$50)/2)*0.5 | G28: ='Control Panel'!$B$15*'Control Panel'!$B$6*'Control Panel'!B50*1000000*'Control Panel'!$B$29*IF('Control Panel'!$B$100=1,'Control Panel'!F$98,'Control Panel'!$B$27)*'Control Panel'!$B$41*'Control Panel'!$C$41*'Control Panel'!F$57*(1+IF('Control Panel'!$D$91=1,'Control Panel'!$C$91,'Control Panel'!$B$30))^MAX(0,(4-'Control Panel'!$F$50)/2)*0.5 | H28: ='Control Panel'!$B$15*'Control Panel'!$B$6*'Control Panel'!B50*1000000*'Control Panel'!$B$29*IF('Control Panel'!$B$100=1,'Control Panel'!G$98,'Control Panel'!$B$27)*'Control Panel'!$B$41*'Control Panel'!$C$41*'Control Panel'!G$57*(1+IF('Control Panel'!$D$91=1,'Control Panel'!$C$91,'Control Panel'!$B$30))^MAX(0,(5-'Control Panel'!$F$50)/2)*0.5 | I28: ='Control Panel'!$B$15*'Control Panel'!$B$6*'Control Panel'!B50*1000000*'Control Panel'!$B$29*IF('Control Panel'!$B$100=1,'Control Panel'!H$98,'Control Panel'!$B$27)*'Control Panel'!$B$41*'Control Panel'!$C$41*'Control Panel'!H$57*(1+IF('Control Panel'!$D$91=1,'Control Panel'!$C$91,'Control Panel'!$B$30))^MAX(0,(6-'Control Panel'!$F$50)/2)*0.5 | J28: ='Control Panel'!$B$15*'Control Panel'!$B$6*'Control Panel'!B50*1000000*'Control Panel'!$B$29*IF('Control Panel'!$B$100=1,'Control Panel'!I$98,'Control Panel'!$B$27)*'Control Panel'!$B$41*'Control Panel'!$C$41*'Control Panel'!I$57*(1+IF('Control Panel'!$D$91=1,'Control Panel'!$C$91,'Control Panel'!$B$30))^MAX(0,(7-'Control Panel'!$F$50)/2)*0.5 | K28: ='Control Panel'!$B$15*'Control Panel'!$B$6*'Control Panel'!B50*1000000*'Control Panel'!$B$29*IF('Control Panel'!$B$100=1,'Control Panel'!J$98,'Control Panel'!$B$27)*'Control Panel'!$B$41*'Control Panel'!$C$41*'Control Panel'!J$57*(1+IF('Control Panel'!$D$91=1,'Control Panel'!$C$91,'Control Panel'!$B$30))^MAX(0,(8-'Control Panel'!$F$50)/2)*0.5 | L28: ='Control Panel'!$B$15*'Control Panel'!$B$6*'Control Panel'!B50*1000000*'Control Panel'!$B$29*IF('Control Panel'!$B$100=1,'Control Panel'!K$98,'Control Panel'!$B$27)*'Control Panel'!$B$41*'Control Panel'!$C$41*'Control Panel'!K$57*(1+IF('Control Panel'!$D$91=1,'Control Panel'!$C$91,'Control Panel'!$B$30))^MAX(0,(9-'Control Panel'!$F$50)/2)*0.5 | M28: ='Control Panel'!$B$15*'Control Panel'!$B$6*'Control Panel'!B50*1000000*'Control Panel'!$B$29*IF('Control Panel'!$B$100=1,'Control Panel'!L$98,'Control Panel'!$B$27)*'Control Panel'!$B$41*'Control Panel'!$C$41*'Control Panel'!L$57*(1+IF('Control Panel'!$D$91=1,'Control Panel'!$C$91,'Control Panel'!$B$30))^MAX(0,(10-'Control Panel'!$F$50)/2)*0.5 | N28: =SUM(C28:M28)
A29: Issuance (0.5%, 60%) | B29: H1 2028 | C29: ='Control Panel'!$B$15*'Control Panel'!$B$7*'Control Panel'!C50*1000000*IF('Control Panel'!$B$100=1,'Control Panel'!B$99,'Control Panel'!$B$28)*'Control Panel'!$B$42*'Control Panel'!$C$42*'Control Panel'!B$57*(1+IF('Control Panel'!$D$91=1,'Control Panel'!$C$91,'Control Panel'!$B$30))^MAX(0,(0-'Control Panel'!$F$50)/2)*0.5 | D29: ='Control Panel'!$B$15*'Control Panel'!$B$7*'Control Panel'!C50*1000000*IF('Control Panel'!$B$100=1,'Control Panel'!C$99,'Control Panel'!$B$28)*'Control Panel'!$B$42*'Control Panel'!$C$42*'Control Panel'!C$57*(1+IF('Control Panel'!$D$91=1,'Control Panel'!$C$91,'Control Panel'!$B$30))^MAX(0,(1-'Control Panel'!$F$50)/2)*0.5 | E29: ='Control Panel'!$B$15*'Control Panel'!$B$7*'Control Panel'!C50*1000000*IF('Control Panel'!$B$100=1,'Control Panel'!D$99,'Control Panel'!$B$28)*'Control Panel'!$B$42*'Control Panel'!$C$42*'Control Panel'!D$57*(1+IF('Control Panel'!$D$91=1,'Control Panel'!$C$91,'Control Panel'!$B$30))^MAX(0,(2-'Control Panel'!$F$50)/2)*0.5 | F29: ='Control Panel'!$B$15*'Control Panel'!$B$7*'Control Panel'!C50*1000000*IF('Control Panel'!$B$100=1,'Control Panel'!E$99,'Control Panel'!$B$28)*'Control Panel'!$B$42*'Control Panel'!$C$42*'Control Panel'!E$57*(1+IF('Control Panel'!$D$91=1,'Control Panel'!$C$91,'Control Panel'!$B$30))^MAX(0,(3-'Control Panel'!$F$50)/2)*0.5 | G29: ='Control Panel'!$B$15*'Control Panel'!$B$7*'Control Panel'!C50*1000000*IF('Control Panel'!$B$100=1,'Control Panel'!F$99,'Control Panel'!$B$28)*'Control Panel'!$B$42*'Control Panel'!$C$42*'Control Panel'!F$57*(1+IF('Control Panel'!$D$91=1,'Control Panel'!$C$91,'Control Panel'!$B$30))^MAX(0,(4-'Control Panel'!$F$50)/2)*0.5 | H29: ='Control Panel'!$B$15*'Control Panel'!$B$7*'Control Panel'!C50*1000000*IF('Control Panel'!$B$100=1,'Control Panel'!G$99,'Control Panel'!$B$28)*'Control Panel'!$B$42*'Control Panel'!$C$42*'Control Panel'!G$57*(1+IF('Control Panel'!$D$91=1,'Control Panel'!$C$91,'Control Panel'!$B$30))^MAX(0,(5-'Control Panel'!$F$50)/2)*0.5 | I29: ='Control Panel'!$B$15*'Control Panel'!$B$7*'Control Panel'!C50*1000000*IF('Control Panel'!$B$100=1,'Control Panel'!H$99,'Control Panel'!$B$28)*'Control Panel'!$B$42*'Control Panel'!$C$42*'Control Panel'!H$57*(1+IF('Control Panel'!$D$91=1,'Control Panel'!$C$91,'Control Panel'!$B$30))^MAX(0,(6-'Control Panel'!$F$50)/2)*0.5 | J29: ='Control Panel'!$B$15*'Control Panel'!$B$7*'Control Panel'!C50*1000000*IF('Control Panel'!$B$100=1,'Control Panel'!I$99,'Control Panel'!$B$28)*'Control Panel'!$B$42*'Control Panel'!$C$42*'Control Panel'!I$57*(1+IF('Control Panel'!$D$91=1,'Control Panel'!$C$91,'Control Panel'!$B$30))^MAX(0,(7-'Control Panel'!$F$50)/2)*0.5 | K29: ='Control Panel'!$B$15*'Control Panel'!$B$7*'Control Panel'!C50*1000000*IF('Control Panel'!$B$100=1,'Control Panel'!J$99,'Control Panel'!$B$28)*'Control Panel'!$B$42*'Control Panel'!$C$42*'Control Panel'!J$57*(1+IF('Control Panel'!$D$91=1,'Control Panel'!$C$91,'Control Panel'!$B$30))^MAX(0,(8-'Control Panel'!$F$50)/2)*0.5 | L29: ='Control Panel'!$B$15*'Control Panel'!$B$7*'Control Panel'!C50*1000000*IF('Control Panel'!$B$100=1,'Control Panel'!K$99,'Control Panel'!$B$28)*'Control Panel'!$B$42*'Control Panel'!$C$42*'Control Panel'!K$57*(1+IF('Control Panel'!$D$91=1,'Control Panel'!$C$91,'Control Panel'!$B$30))^MAX(0,(9-'Control Panel'!$F$50)/2)*0.5 | M29: ='Control Panel'!$B$15*'Control Panel'!$B$7*'Control Panel'!C50*1000000*IF('Control Panel'!$B$100=1,'Control Panel'!L$99,'Control Panel'!$B$28)*'Control Panel'!$B$42*'Control Panel'!$C$42*'Control Panel'!L$57*(1+IF('Control Panel'!$D$91=1,'Control Panel'!$C$91,'Control Panel'!$B$30))^MAX(0,(10-'Control Panel'!$F$50)/2)*0.5 | N29: =SUM(C29:M29)
A30: Trading (5 bps, 100%) | B30: H1 2028 | C30: ='Control Panel'!$B$15*'Control Panel'!$B$8*'Control Panel'!C50*1000000*IF('Control Panel'!$B$100=1,'Control Panel'!B$99,'Control Panel'!$B$28)*'Control Panel'!$B$62*'Control Panel'!$B$43*'Control Panel'!$C$43*'Control Panel'!B$57*(1+IF('Control Panel'!$D$91=1,'Control Panel'!$C$91,'Control Panel'!$B$30))^MAX(0,(0-'Control Panel'!$F$50)/2)*0.5 | D30: ='Control Panel'!$B$15*'Control Panel'!$B$8*'Control Panel'!C50*1000000*IF('Control Panel'!$B$100=1,'Control Panel'!C$99,'Control Panel'!$B$28)*'Control Panel'!$B$62*'Control Panel'!$B$43*'Control Panel'!$C$43*'Control Panel'!C$57*(1+IF('Control Panel'!$D$91=1,'Control Panel'!$C$91,'Control Panel'!$B$30))^MAX(0,(1-'Control Panel'!$F$50)/2)*0.5 | E30: ='Control Panel'!$B$15*'Control Panel'!$B$8*'Control Panel'!C50*1000000*IF('Control Panel'!$B$100=1,'Control Panel'!D$99,'Control Panel'!$B$28)*'Control Panel'!$B$62*'Control Panel'!$B$43*'Control Panel'!$C$43*'Control Panel'!D$57*(1+IF('Control Panel'!$D$91=1,'Control Panel'!$C$91,'Control Panel'!$B$30))^MAX(0,(2-'Control Panel'!$F$50)/2)*0.5 | F30: ='Control Panel'!$B$15*'Control Panel'!$B$8*'Control Panel'!C50*1000000*IF('Control Panel'!$B$100=1,'Control Panel'!E$99,'Control Panel'!$B$28)*'Control Panel'!$B$62*'Control Panel'!$B$43*'Control Panel'!$C$43*'Control Panel'!E$57*(1+IF('Control Panel'!$D$91=1,'Control Panel'!$C$91,'Control Panel'!$B$30))^MAX(0,(3-'Control Panel'!$F$50)/2)*0.5 | G30: ='Control Panel'!$B$15*'Control Panel'!$B$8*'Control Panel'!C50*1000000*IF('Control Panel'!$B$100=1,'Control Panel'!F$99,'Control Panel'!$B$28)*'Control Panel'!$B$62*'Control Panel'!$B$43*'Control Panel'!$C$43*'Control Panel'!F$57*(1+IF('Control Panel'!$D$91=1,'Control Panel'!$C$91,'Control Panel'!$B$30))^MAX(0,(4-'Control Panel'!$F$50)/2)*0.5 | H30: ='Control Panel'!$B$15*'Control Panel'!$B$8*'Control Panel'!C50*1000000*IF('Control Panel'!$B$100=1,'Control Panel'!G$99,'Control Panel'!$B$28)*'Control Panel'!$B$62*'Control Panel'!$B$43*'Control Panel'!$C$43*'Control Panel'!G$57*(1+IF('Control Panel'!$D$91=1,'Control Panel'!$C$91,'Control Panel'!$B$30))^MAX(0,(5-'Control Panel'!$F$50)/2)*0.5 | I30: ='Control Panel'!$B$15*'Control Panel'!$B$8*'Control Panel'!C50*1000000*IF('Control Panel'!$B$100=1,'Control Panel'!H$99,'Control Panel'!$B$28)*'Control Panel'!$B$62*'Control Panel'!$B$43*'Control Panel'!$C$43*'Control Panel'!H$57*(1+IF('Control Panel'!$D$91=1,'Control Panel'!$C$91,'Control Panel'!$B$30))^MAX(0,(6-'Control Panel'!$F$50)/2)*0.5 | J30: ='Control Panel'!$B$15*'Control Panel'!$B$8*'Control Panel'!C50*1000000*IF('Control Panel'!$B$100=1,'Control Panel'!I$99,'Control Panel'!$B$28)*'Control Panel'!$B$62*'Control Panel'!$B$43*'Control Panel'!$C$43*'Control Panel'!I$57*(1+IF('Control Panel'!$D$91=1,'Control Panel'!$C$91,'Control Panel'!$B$30))^MAX(0,(7-'Control Panel'!$F$50)/2)*0.5 | K30: ='Control Panel'!$B$15*'Control Panel'!$B$8*'Control Panel'!C50*1000000*IF('Control Panel'!$B$100=1,'Control Panel'!J$99,'Control Panel'!$B$28)*'Control Panel'!$B$62*'Control Panel'!$B$43*'Control Panel'!$C$43*'Control Panel'!J$57*(1+IF('Control Panel'!$D$91=1,'Control Panel'!$C$91,'Control Panel'!$B$30))^MAX(0,(8-'Control Panel'!$F$50)/2)*0.5 | L30: ='Control Panel'!$B$15*'Control Panel'!$B$8*'Control Panel'!C50*1000000*IF('Control Panel'!$B$100=1,'Control Panel'!K$99,'Control Panel'!$B$28)*'Control Panel'!$B$62*'Control Panel'!$B$43*'Control Panel'!$C$43*'Control Panel'!K$57*(1+IF('Control Panel'!$D$91=1,'Control Panel'!$C$91,'Control Panel'!$B$30))^MAX(0,(9-'Control Panel'!$F$50)/2)*0.5 | M30: ='Control Panel'!$B$15*'Control Panel'!$B$8*'Control Panel'!C50*1000000*IF('Control Panel'!$B$100=1,'Control Panel'!L$99,'Control Panel'!$B$28)*'Control Panel'!$B$62*'Control Panel'!$B$43*'Control Panel'!$C$43*'Control Panel'!L$57*(1+IF('Control Panel'!$D$91=1,'Control Panel'!$C$91,'Control Panel'!$B$30))^MAX(0,(10-'Control Panel'!$F$50)/2)*0.5 | N30: =SUM(C30:M30)
A31: Custody (30 bps, 40%) | B31: H1 2028 | C31: ='Control Panel'!$B$15*'Control Panel'!$B$9*'Control Panel'!D50*1000000*IF('Control Panel'!$B$100=1,'Control Panel'!B$99,'Control Panel'!$B$28)*'Control Panel'!$B$44*'Control Panel'!$C$44*'Control Panel'!B$57*(1+IF('Control Panel'!$D$91=1,'Control Panel'!$C$91,'Control Panel'!$B$30))^MAX(0,(0-'Control Panel'!$F$50)/2)*0.5 | D31: ='Control Panel'!$B$15*'Control Panel'!$B$9*'Control Panel'!D50*1000000*IF('Control Panel'!$B$100=1,'Control Panel'!C$99,'Control Panel'!$B$28)*'Control Panel'!$B$44*'Control Panel'!$C$44*'Control Panel'!C$57*(1+IF('Control Panel'!$D$91=1,'Control Panel'!$C$91,'Control Panel'!$B$30))^MAX(0,(1-'Control Panel'!$F$50)/2)*0.5 | E31: ='Control Panel'!$B$15*'Control Panel'!$B$9*'Control Panel'!D50*1000000*IF('Control Panel'!$B$100=1,'Control Panel'!D$99,'Control Panel'!$B$28)*'Control Panel'!$B$44*'Control Panel'!$C$44*'Control Panel'!D$57*(1+IF('Control Panel'!$D$91=1,'Control Panel'!$C$91,'Control Panel'!$B$30))^MAX(0,(2-'Control Panel'!$F$50)/2)*0.5 | F31: ='Control Panel'!$B$15*'Control Panel'!$B$9*'Control Panel'!D50*1000000*IF('Control Panel'!$B$100=1,'Control Panel'!E$99,'Control Panel'!$B$28)*'Control Panel'!$B$44*'Control Panel'!$C$44*'Control Panel'!E$57*(1+IF('Control Panel'!$D$91=1,'Control Panel'!$C$91,'Control Panel'!$B$30))^MAX(0,(3-'Control Panel'!$F$50)/2)*0.5 | G31: ='Control Panel'!$B$15*'Control Panel'!$B$9*'Control Panel'!D50*1000000*IF('Control Panel'!$B$100=1,'Control Panel'!F$99,'Control Panel'!$B$28)*'Control Panel'!$B$44*'Control Panel'!$C$44*'Control Panel'!F$57*(1+IF('Control Panel'!$D$91=1,'Control Panel'!$C$91,'Control Panel'!$B$30))^MAX(0,(4-'Control Panel'!$F$50)/2)*0.5 | H31: ='Control Panel'!$B$15*'Control Panel'!$B$9*'Control Panel'!D50*1000000*IF('Control Panel'!$B$100=1,'Control Panel'!G$99,'Control Panel'!$B$28)*'Control Panel'!$B$44*'Control Panel'!$C$44*'Control Panel'!G$57*(1+IF('Control Panel'!$D$91=1,'Control Panel'!$C$91,'Control Panel'!$B$30))^MAX(0,(5-'Control Panel'!$F$50)/2)*0.5 | I31: ='Control Panel'!$B$15*'Control Panel'!$B$9*'Control Panel'!D50*1000000*IF('Control Panel'!$B$100=1,'Control Panel'!H$99,'Control Panel'!$B$28)*'Control Panel'!$B$44*'Control Panel'!$C$44*'Control Panel'!H$57*(1+IF('Control Panel'!$D$91=1,'Control Panel'!$C$91,'Control Panel'!$B$30))^MAX(0,(6-'Control Panel'!$F$50)/2)*0.5 | J31: ='Control Panel'!$B$15*'Control Panel'!$B$9*'Control Panel'!D50*1000000*IF('Control Panel'!$B$100=1,'Control Panel'!I$99,'Control Panel'!$B$28)*'Control Panel'!$B$44*'Control Panel'!$C$44*'Control Panel'!I$57*(1+IF('Control Panel'!$D$91=1,'Control Panel'!$C$91,'Control Panel'!$B$30))^MAX(0,(7-'Control Panel'!$F$50)/2)*0.5 | K31: ='Control Panel'!$B$15*'Control Panel'!$B$9*'Control Panel'!D50*1000000*IF('Control Panel'!$B$100=1,'Control Panel'!J$99,'Control Panel'!$B$28)*'Control Panel'!$B$44*'Control Panel'!$C$44*'Control Panel'!J$57*(1+IF('Control Panel'!$D$91=1,'Control Panel'!$C$91,'Control Panel'!$B$30))^MAX(0,(8-'Control Panel'!$F$50)/2)*0.5 | L31: ='Control Panel'!$B$15*'Control Panel'!$B$9*'Control Panel'!D50*1000000*IF('Control Panel'!$B$100=1,'Control Panel'!K$99,'Control Panel'!$B$28)*'Control Panel'!$B$44*'Control Panel'!$C$44*'Control Panel'!K$57*(1+IF('Control Panel'!$D$91=1,'Control Panel'!$C$91,'Control Panel'!$B$30))^MAX(0,(9-'Control Panel'!$F$50)/2)*0.5 | M31: ='Control Panel'!$B$15*'Control Panel'!$B$9*'Control Panel'!D50*1000000*IF('Control Panel'!$B$100=1,'Control Panel'!L$99,'Control Panel'!$B$28)*'Control Panel'!$B$44*'Control Panel'!$C$44*'Control Panel'!L$57*(1+IF('Control Panel'!$D$91=1,'Control Panel'!$C$91,'Control Panel'!$B$30))^MAX(0,(10-'Control Panel'!$F$50)/2)*0.5 | N31: =SUM(C31:M31)
A32: SaaS + APIs (80%) | B32: H1 2028 | C32: ='Control Panel'!$B$15*'Control Panel'!$B$10*'Control Panel'!E50*'Control Panel'!$B$45*'Control Panel'!$C$45*'Control Panel'!B$57*0.5 | D32: ='Control Panel'!$B$15*'Control Panel'!$B$10*'Control Panel'!E50*'Control Panel'!$B$45*'Control Panel'!$C$45*'Control Panel'!C$57*0.5 | E32: ='Control Panel'!$B$15*'Control Panel'!$B$10*'Control Panel'!E50*'Control Panel'!$B$45*'Control Panel'!$C$45*'Control Panel'!D$57*0.5 | F32: ='Control Panel'!$B$15*'Control Panel'!$B$10*'Control Panel'!E50*'Control Panel'!$B$45*'Control Panel'!$C$45*'Control Panel'!E$57*0.5 | G32: ='Control Panel'!$B$15*'Control Panel'!$B$10*'Control Panel'!E50*'Control Panel'!$B$45*'Control Panel'!$C$45*'Control Panel'!F$57*0.5 | H32: ='Control Panel'!$B$15*'Control Panel'!$B$10*'Control Panel'!E50*'Control Panel'!$B$45*'Control Panel'!$C$45*'Control Panel'!G$57*0.5 | I32: ='Control Panel'!$B$15*'Control Panel'!$B$10*'Control Panel'!E50*'Control Panel'!$B$45*'Control Panel'!$C$45*'Control Panel'!H$57*0.5 | J32: ='Control Panel'!$B$15*'Control Panel'!$B$10*'Control Panel'!E50*'Control Panel'!$B$45*'Control Panel'!$C$45*'Control Panel'!I$57*0.5 | K32: ='Control Panel'!$B$15*'Control Panel'!$B$10*'Control Panel'!E50*'Control Panel'!$B$45*'Control Panel'!$C$45*'Control Panel'!J$57*0.5 | L32: ='Control Panel'!$B$15*'Control Panel'!$B$10*'Control Panel'!E50*'Control Panel'!$B$45*'Control Panel'!$C$45*'Control Panel'!K$57*0.5 | M32: ='Control Panel'!$B$15*'Control Panel'!$B$10*'Control Panel'!E50*'Control Panel'!$B$45*'Control Panel'!$C$45*'Control Panel'!L$57*0.5 | N32: =SUM(C32:M32)
A33: BVCU SUBTOTAL | B33: H1 2028 | C33: =C28+C29+C30+C31+C32 | D33: =D28+D29+D30+D31+D32 | E33: =E28+E29+E30+E31+E32 | F33: =F28+F29+F30+F31+F32 | G33: =G28+G29+G30+G31+G32 | H33: =H28+H29+H30+H31+H32 | I33: =I28+I29+I30+I31+I32 | J33: =J28+J29+J30+J31+J32 | ... M33: =M28+M29+M30+M31+M32 | N33: =SUM(C33:M33)
A34: VANCITY CU ($35.5B AUA)
A35: Settlement (1.5 bps, 30%) | B35: H1 2029 | C35: ='Control Panel'!$B$16*'Control Panel'!$B$6*'Control Panel'!B51*1000000*'Control Panel'!$B$29*IF('Control Panel'!$B$100=1,'Control Panel'!B$98,'Control Panel'!$B$27)*'Control Panel'!$B$41*'Control Panel'!$C$41*'Control Panel'!B$58*(1+IF('Control Panel'!$D$92=1,'Control Panel'!$C$92,'Control Panel'!$B$30))^MAX(0,(0-'Control Panel'!$F$51)/2)*0.5 | D35: ='Control Panel'!$B$16*'Control Panel'!$B$6*'Control Panel'!B51*1000000*'Control Panel'!$B$29*IF('Control Panel'!$B$100=1,'Control Panel'!C$98,'Control Panel'!$B$27)*'Control Panel'!$B$41*'Control Panel'!$C$41*'Control Panel'!C$58*(1+IF('Control Panel'!$D$92=1,'Control Panel'!$C$92,'Control Panel'!$B$30))^MAX(0,(1-'Control Panel'!$F$51)/2)*0.5 | E35: ='Control Panel'!$B$16*'Control Panel'!$B$6*'Control Panel'!B51*1000000*'Control Panel'!$B$29*IF('Control Panel'!$B$100=1,'Control Panel'!D$98,'Control Panel'!$B$27)*'Control Panel'!$B$41*'Control Panel'!$C$41*'Control Panel'!D$58*(1+IF('Control Panel'!$D$92=1,'Control Panel'!$C$92,'Control Panel'!$B$30))^MAX(0,(2-'Control Panel'!$F$51)/2)*0.5 | F35: ='Control Panel'!$B$16*'Control Panel'!$B$6*'Control Panel'!B51*1000000*'Control Panel'!$B$29*IF('Control Panel'!$B$100=1,'Control Panel'!E$98,'Control Panel'!$B$27)*'Control Panel'!$B$41*'Control Panel'!$C$41*'Control Panel'!E$58*(1+IF('Control Panel'!$D$92=1,'Control Panel'!$C$92,'Control Panel'!$B$30))^MAX(0,(3-'Control Panel'!$F$51)/2)*0.5 | G35: ='Control Panel'!$B$16*'Control Panel'!$B$6*'Control Panel'!B51*1000000*'Control Panel'!$B$29*IF('Control Panel'!$B$100=1,'Control Panel'!F$98,'Control Panel'!$B$27)*'Control Panel'!$B$41*'Control Panel'!$C$41*'Control Panel'!F$58*(1+IF('Control Panel'!$D$92=1,'Control Panel'!$C$92,'Control Panel'!$B$30))^MAX(0,(4-'Control Panel'!$F$51)/2)*0.5 | H35: ='Control Panel'!$B$16*'Control Panel'!$B$6*'Control Panel'!B51*1000000*'Control Panel'!$B$29*IF('Control Panel'!$B$100=1,'Control Panel'!G$98,'Control Panel'!$B$27)*'Control Panel'!$B$41*'Control Panel'!$C$41*'Control Panel'!G$58*(1+IF('Control Panel'!$D$92=1,'Control Panel'!$C$92,'Control Panel'!$B$30))^MAX(0,(5-'Control Panel'!$F$51)/2)*0.5 | I35: ='Control Panel'!$B$16*'Control Panel'!$B$6*'Control Panel'!B51*1000000*'Control Panel'!$B$29*IF('Control Panel'!$B$100=1,'Control Panel'!H$98,'Control Panel'!$B$27)*'Control Panel'!$B$41*'Control Panel'!$C$41*'Control Panel'!H$58*(1+IF('Control Panel'!$D$92=1,'Control Panel'!$C$92,'Control Panel'!$B$30))^MAX(0,(6-'Control Panel'!$F$51)/2)*0.5 | J35: ='Control Panel'!$B$16*'Control Panel'!$B$6*'Control Panel'!B51*1000000*'Control Panel'!$B$29*IF('Control Panel'!$B$100=1,'Control Panel'!I$98,'Control Panel'!$B$27)*'Control Panel'!$B$41*'Control Panel'!$C$41*'Control Panel'!I$58*(1+IF('Control Panel'!$D$92=1,'Control Panel'!$C$92,'Control Panel'!$B$30))^MAX(0,(7-'Control Panel'!$F$51)/2)*0.5 | K35: ='Control Panel'!$B$16*'Control Panel'!$B$6*'Control Panel'!B51*1000000*'Control Panel'!$B$29*IF('Control Panel'!$B$100=1,'Control Panel'!J$98,'Control Panel'!$B$27)*'Control Panel'!$B$41*'Control Panel'!$C$41*'Control Panel'!J$58*(1+IF('Control Panel'!$D$92=1,'Control Panel'!$C$92,'Control Panel'!$B$30))^MAX(0,(8-'Control Panel'!$F$51)/2)*0.5 | L35: ='Control Panel'!$B$16*'Control Panel'!$B$6*'Control Panel'!B51*1000000*'Control Panel'!$B$29*IF('Control Panel'!$B$100=1,'Control Panel'!K$98,'Control Panel'!$B$27)*'Control Panel'!$B$41*'Control Panel'!$C$41*'Control Panel'!K$58*(1+IF('Control Panel'!$D$92=1,'Control Panel'!$C$92,'Control Panel'!$B$30))^MAX(0,(9-'Control Panel'!$F$51)/2)*0.5 | M35: ='Control Panel'!$B$16*'Control Panel'!$B$6*'Control Panel'!B51*1000000*'Control Panel'!$B$29*IF('Control Panel'!$B$100=1,'Control Panel'!L$98,'Control Panel'!$B$27)*'Control Panel'!$B$41*'Control Panel'!$C$41*'Control Panel'!L$58*(1+IF('Control Panel'!$D$92=1,'Control Panel'!$C$92,'Control Panel'!$B$30))^MAX(0,(10-'Control Panel'!$F$51)/2)*0.5 | N35: =SUM(C35:M35)
A36: Issuance (0.5%, 60%) | B36: H1 2029 | C36: ='Control Panel'!$B$16*'Control Panel'!$B$7*'Control Panel'!C51*1000000*IF('Control Panel'!$B$100=1,'Control Panel'!B$99,'Control Panel'!$B$28)*'Control Panel'!$B$42*'Control Panel'!$C$42*'Control Panel'!B$58*(1+IF('Control Panel'!$D$92=1,'Control Panel'!$C$92,'Control Panel'!$B$30))^MAX(0,(0-'Control Panel'!$F$51)/2)*0.5 | D36: ='Control Panel'!$B$16*'Control Panel'!$B$7*'Control Panel'!C51*1000000*IF('Control Panel'!$B$100=1,'Control Panel'!C$99,'Control Panel'!$B$28)*'Control Panel'!$B$42*'Control Panel'!$C$42*'Control Panel'!C$58*(1+IF('Control Panel'!$D$92=1,'Control Panel'!$C$92,'Control Panel'!$B$30))^MAX(0,(1-'Control Panel'!$F$51)/2)*0.5 | E36: ='Control Panel'!$B$16*'Control Panel'!$B$7*'Control Panel'!C51*1000000*IF('Control Panel'!$B$100=1,'Control Panel'!D$99,'Control Panel'!$B$28)*'Control Panel'!$B$42*'Control Panel'!$C$42*'Control Panel'!D$58*(1+IF('Control Panel'!$D$92=1,'Control Panel'!$C$92,'Control Panel'!$B$30))^MAX(0,(2-'Control Panel'!$F$51)/2)*0.5 | F36: ='Control Panel'!$B$16*'Control Panel'!$B$7*'Control Panel'!C51*1000000*IF('Control Panel'!$B$100=1,'Control Panel'!E$99,'Control Panel'!$B$28)*'Control Panel'!$B$42*'Control Panel'!$C$42*'Control Panel'!E$58*(1+IF('Control Panel'!$D$92=1,'Control Panel'!$C$92,'Control Panel'!$B$30))^MAX(0,(3-'Control Panel'!$F$51)/2)*0.5 | G36: ='Control Panel'!$B$16*'Control Panel'!$B$7*'Control Panel'!C51*1000000*IF('Control Panel'!$B$100=1,'Control Panel'!F$99,'Control Panel'!$B$28)*'Control Panel'!$B$42*'Control Panel'!$C$42*'Control Panel'!F$58*(1+IF('Control Panel'!$D$92=1,'Control Panel'!$C$92,'Control Panel'!$B$30))^MAX(0,(4-'Control Panel'!$F$51)/2)*0.5 | H36: ='Control Panel'!$B$16*'Control Panel'!$B$7*'Control Panel'!C51*1000000*IF('Control Panel'!$B$100=1,'Control Panel'!G$99,'Control Panel'!$B$28)*'Control Panel'!$B$42*'Control Panel'!$C$42*'Control Panel'!G$58*(1+IF('Control Panel'!$D$92=1,'Control Panel'!$C$92,'Control Panel'!$B$30))^MAX(0,(5-'Control Panel'!$F$51)/2)*0.5 | I36: ='Control Panel'!$B$16*'Control Panel'!$B$7*'Control Panel'!C51*1000000*IF('Control Panel'!$B$100=1,'Control Panel'!H$99,'Control Panel'!$B$28)*'Control Panel'!$B$42*'Control Panel'!$C$42*'Control Panel'!H$58*(1+IF('Control Panel'!$D$92=1,'Control Panel'!$C$92,'Control Panel'!$B$30))^MAX(0,(6-'Control Panel'!$F$51)/2)*0.5 | J36: ='Control Panel'!$B$16*'Control Panel'!$B$7*'Control Panel'!C51*1000000*IF('Control Panel'!$B$100=1,'Control Panel'!I$99,'Control Panel'!$B$28)*'Control Panel'!$B$42*'Control Panel'!$C$42*'Control Panel'!I$58*(1+IF('Control Panel'!$D$92=1,'Control Panel'!$C$92,'Control Panel'!$B$30))^MAX(0,(7-'Control Panel'!$F$51)/2)*0.5 | K36: ='Control Panel'!$B$16*'Control Panel'!$B$7*'Control Panel'!C51*1000000*IF('Control Panel'!$B$100=1,'Control Panel'!J$99,'Control Panel'!$B$28)*'Control Panel'!$B$42*'Control Panel'!$C$42*'Control Panel'!J$58*(1+IF('Control Panel'!$D$92=1,'Control Panel'!$C$92,'Control Panel'!$B$30))^MAX(0,(8-'Control Panel'!$F$51)/2)*0.5 | L36: ='Control Panel'!$B$16*'Control Panel'!$B$7*'Control Panel'!C51*1000000*IF('Control Panel'!$B$100=1,'Control Panel'!K$99,'Control Panel'!$B$28)*'Control Panel'!$B$42*'Control Panel'!$C$42*'Control Panel'!K$58*(1+IF('Control Panel'!$D$92=1,'Control Panel'!$C$92,'Control Panel'!$B$30))^MAX(0,(9-'Control Panel'!$F$51)/2)*0.5 | M36: ='Control Panel'!$B$16*'Control Panel'!$B$7*'Control Panel'!C51*1000000*IF('Control Panel'!$B$100=1,'Control Panel'!L$99,'Control Panel'!$B$28)*'Control Panel'!$B$42*'Control Panel'!$C$42*'Control Panel'!L$58*(1+IF('Control Panel'!$D$92=1,'Control Panel'!$C$92,'Control Panel'!$B$30))^MAX(0,(10-'Control Panel'!$F$51)/2)*0.5 | N36: =SUM(C36:M36)
A37: Trading (5 bps, 100%) | B37: H1 2029 | C37: ='Control Panel'!$B$16*'Control Panel'!$B$8*'Control Panel'!C51*1000000*IF('Control Panel'!$B$100=1,'Control Panel'!B$99,'Control Panel'!$B$28)*'Control Panel'!$B$62*'Control Panel'!$B$43*'Control Panel'!$C$43*'Control Panel'!B$58*(1+IF('Control Panel'!$D$92=1,'Control Panel'!$C$92,'Control Panel'!$B$30))^MAX(0,(0-'Control Panel'!$F$51)/2)*0.5 | D37: ='Control Panel'!$B$16*'Control Panel'!$B$8*'Control Panel'!C51*1000000*IF('Control Panel'!$B$100=1,'Control Panel'!C$99,'Control Panel'!$B$28)*'Control Panel'!$B$62*'Control Panel'!$B$43*'Control Panel'!$C$43*'Control Panel'!C$58*(1+IF('Control Panel'!$D$92=1,'Control Panel'!$C$92,'Control Panel'!$B$30))^MAX(0,(1-'Control Panel'!$F$51)/2)*0.5 | E37: ='Control Panel'!$B$16*'Control Panel'!$B$8*'Control Panel'!C51*1000000*IF('Control Panel'!$B$100=1,'Control Panel'!D$99,'Control Panel'!$B$28)*'Control Panel'!$B$62*'Control Panel'!$B$43*'Control Panel'!$C$43*'Control Panel'!D$58*(1+IF('Control Panel'!$D$92=1,'Control Panel'!$C$92,'Control Panel'!$B$30))^MAX(0,(2-'Control Panel'!$F$51)/2)*0.5 | F37: ='Control Panel'!$B$16*'Control Panel'!$B$8*'Control Panel'!C51*1000000*IF('Control Panel'!$B$100=1,'Control Panel'!E$99,'Control Panel'!$B$28)*'Control Panel'!$B$62*'Control Panel'!$B$43*'Control Panel'!$C$43*'Control Panel'!E$58*(1+IF('Control Panel'!$D$92=1,'Control Panel'!$C$92,'Control Panel'!$B$30))^MAX(0,(3-'Control Panel'!$F$51)/2)*0.5 | G37: ='Control Panel'!$B$16*'Control Panel'!$B$8*'Control Panel'!C51*1000000*IF('Control Panel'!$B$100=1,'Control Panel'!F$99,'Control Panel'!$B$28)*'Control Panel'!$B$62*'Control Panel'!$B$43*'Control Panel'!$C$43*'Control Panel'!F$58*(1+IF('Control Panel'!$D$92=1,'Control Panel'!$C$92,'Control Panel'!$B$30))^MAX(0,(4-'Control Panel'!$F$51)/2)*0.5 | H37: ='Control Panel'!$B$16*'Control Panel'!$B$8*'Control Panel'!C51*1000000*IF('Control Panel'!$B$100=1,'Control Panel'!G$99,'Control Panel'!$B$28)*'Control Panel'!$B$62*'Control Panel'!$B$43*'Control Panel'!$C$43*'Control Panel'!G$58*(1+IF('Control Panel'!$D$92=1,'Control Panel'!$C$92,'Control Panel'!$B$30))^MAX(0,(5-'Control Panel'!$F$51)/2)*0.5 | I37: ='Control Panel'!$B$16*'Control Panel'!$B$8*'Control Panel'!C51*1000000*IF('Control Panel'!$B$100=1,'Control Panel'!H$99,'Control Panel'!$B$28)*'Control Panel'!$B$62*'Control Panel'!$B$43*'Control Panel'!$C$43*'Control Panel'!H$58*(1+IF('Control Panel'!$D$92=1,'Control Panel'!$C$92,'Control Panel'!$B$30))^MAX(0,(6-'Control Panel'!$F$51)/2)*0.5 | J37: ='Control Panel'!$B$16*'Control Panel'!$B$8*'Control Panel'!C51*1000000*IF('Control Panel'!$B$100=1,'Control Panel'!I$99,'Control Panel'!$B$28)*'Control Panel'!$B$62*'Control Panel'!$B$43*'Control Panel'!$C$43*'Control Panel'!I$58*(1+IF('Control Panel'!$D$92=1,'Control Panel'!$C$92,'Control Panel'!$B$30))^MAX(0,(7-'Control Panel'!$F$51)/2)*0.5 | K37: ='Control Panel'!$B$16*'Control Panel'!$B$8*'Control Panel'!C51*1000000*IF('Control Panel'!$B$100=1,'Control Panel'!J$99,'Control Panel'!$B$28)*'Control Panel'!$B$62*'Control Panel'!$B$43*'Control Panel'!$C$43*'Control Panel'!J$58*(1+IF('Control Panel'!$D$92=1,'Control Panel'!$C$92,'Control Panel'!$B$30))^MAX(0,(8-'Control Panel'!$F$51)/2)*0.5 | L37: ='Control Panel'!$B$16*'Control Panel'!$B$8*'Control Panel'!C51*1000000*IF('Control Panel'!$B$100=1,'Control Panel'!K$99,'Control Panel'!$B$28)*'Control Panel'!$B$62*'Control Panel'!$B$43*'Control Panel'!$C$43*'Control Panel'!K$58*(1+IF('Control Panel'!$D$92=1,'Control Panel'!$C$92,'Control Panel'!$B$30))^MAX(0,(9-'Control Panel'!$F$51)/2)*0.5 | M37: ='Control Panel'!$B$16*'Control Panel'!$B$8*'Control Panel'!C51*1000000*IF('Control Panel'!$B$100=1,'Control Panel'!L$99,'Control Panel'!$B$28)*'Control Panel'!$B$62*'Control Panel'!$B$43*'Control Panel'!$C$43*'Control Panel'!L$58*(1+IF('Control Panel'!$D$92=1,'Control Panel'!$C$92,'Control Panel'!$B$30))^MAX(0,(10-'Control Panel'!$F$51)/2)*0.5 | N37: =SUM(C37:M37)
A38: Custody (30 bps, 40%) | B38: H1 2029 | C38: ='Control Panel'!$B$16*'Control Panel'!$B$9*'Control Panel'!D51*1000000*IF('Control Panel'!$B$100=1,'Control Panel'!B$99,'Control Panel'!$B$28)*'Control Panel'!$B$44*'Control Panel'!$C$44*'Control Panel'!B$58*(1+IF('Control Panel'!$D$92=1,'Control Panel'!$C$92,'Control Panel'!$B$30))^MAX(0,(0-'Control Panel'!$F$51)/2)*0.5 | D38: ='Control Panel'!$B$16*'Control Panel'!$B$9*'Control Panel'!D51*1000000*IF('Control Panel'!$B$100=1,'Control Panel'!C$99,'Control Panel'!$B$28)*'Control Panel'!$B$44*'Control Panel'!$C$44*'Control Panel'!C$58*(1+IF('Control Panel'!$D$92=1,'Control Panel'!$C$92,'Control Panel'!$B$30))^MAX(0,(1-'Control Panel'!$F$51)/2)*0.5 | E38: ='Control Panel'!$B$16*'Control Panel'!$B$9*'Control Panel'!D51*1000000*IF('Control Panel'!$B$100=1,'Control Panel'!D$99,'Control Panel'!$B$28)*'Control Panel'!$B$44*'Control Panel'!$C$44*'Control Panel'!D$58*(1+IF('Control Panel'!$D$92=1,'Control Panel'!$C$92,'Control Panel'!$B$30))^MAX(0,(2-'Control Panel'!$F$51)/2)*0.5 | F38: ='Control Panel'!$B$16*'Control Panel'!$B$9*'Control Panel'!D51*1000000*IF('Control Panel'!$B$100=1,'Control Panel'!E$99,'Control Panel'!$B$28)*'Control Panel'!$B$44*'Control Panel'!$C$44*'Control Panel'!E$58*(1+IF('Control Panel'!$D$92=1,'Control Panel'!$C$92,'Control Panel'!$B$30))^MAX(0,(3-'Control Panel'!$F$51)/2)*0.5 | G38: ='Control Panel'!$B$16*'Control Panel'!$B$9*'Control Panel'!D51*1000000*IF('Control Panel'!$B$100=1,'Control Panel'!F$99,'Control Panel'!$B$28)*'Control Panel'!$B$44*'Control Panel'!$C$44*'Control Panel'!F$58*(1+IF('Control Panel'!$D$92=1,'Control Panel'!$C$92,'Control Panel'!$B$30))^MAX(0,(4-'Control Panel'!$F$51)/2)*0.5 | H38: ='Control Panel'!$B$16*'Control Panel'!$B$9*'Control Panel'!D51*1000000*IF('Control Panel'!$B$100=1,'Control Panel'!G$99,'Control Panel'!$B$28)*'Control Panel'!$B$44*'Control Panel'!$C$44*'Control Panel'!G$58*(1+IF('Control Panel'!$D$92=1,'Control Panel'!$C$92,'Control Panel'!$B$30))^MAX(0,(5-'Control Panel'!$F$51)/2)*0.5 | I38: ='Control Panel'!$B$16*'Control Panel'!$B$9*'Control Panel'!D51*1000000*IF('Control Panel'!$B$100=1,'Control Panel'!H$99,'Control Panel'!$B$28)*'Control Panel'!$B$44*'Control Panel'!$C$44*'Control Panel'!H$58*(1+IF('Control Panel'!$D$92=1,'Control Panel'!$C$92,'Control Panel'!$B$30))^MAX(0,(6-'Control Panel'!$F$51)/2)*0.5 | J38: ='Control Panel'!$B$16*'Control Panel'!$B$9*'Control Panel'!D51*1000000*IF('Control Panel'!$B$100=1,'Control Panel'!I$99,'Control Panel'!$B$28)*'Control Panel'!$B$44*'Control Panel'!$C$44*'Control Panel'!I$58*(1+IF('Control Panel'!$D$92=1,'Control Panel'!$C$92,'Control Panel'!$B$30))^MAX(0,(7-'Control Panel'!$F$51)/2)*0.5 | K38: ='Control Panel'!$B$16*'Control Panel'!$B$9*'Control Panel'!D51*1000000*IF('Control Panel'!$B$100=1,'Control Panel'!J$99,'Control Panel'!$B$28)*'Control Panel'!$B$44*'Control Panel'!$C$44*'Control Panel'!J$58*(1+IF('Control Panel'!$D$92=1,'Control Panel'!$C$92,'Control Panel'!$B$30))^MAX(0,(8-'Control Panel'!$F$51)/2)*0.5 | L38: ='Control Panel'!$B$16*'Control Panel'!$B$9*'Control Panel'!D51*1000000*IF('Control Panel'!$B$100=1,'Control Panel'!K$99,'Control Panel'!$B$28)*'Control Panel'!$B$44*'Control Panel'!$C$44*'Control Panel'!K$58*(1+IF('Control Panel'!$D$92=1,'Control Panel'!$C$92,'Control Panel'!$B$30))^MAX(0,(9-'Control Panel'!$F$51)/2)*0.5 | M38: ='Control Panel'!$B$16*'Control Panel'!$B$9*'Control Panel'!D51*1000000*IF('Control Panel'!$B$100=1,'Control Panel'!L$99,'Control Panel'!$B$28)*'Control Panel'!$B$44*'Control Panel'!$C$44*'Control Panel'!L$58*(1+IF('Control Panel'!$D$92=1,'Control Panel'!$C$92,'Control Panel'!$B$30))^MAX(0,(10-'Control Panel'!$F$51)/2)*0.5 | N38: =SUM(C38:M38)
A39: SaaS + APIs (80%) | B39: H1 2029 | C39: ='Control Panel'!$B$16*'Control Panel'!$B$10*'Control Panel'!E51*'Control Panel'!$B$45*'Control Panel'!$C$45*'Control Panel'!B$58*0.5 | D39: ='Control Panel'!$B$16*'Control Panel'!$B$10*'Control Panel'!E51*'Control Panel'!$B$45*'Control Panel'!$C$45*'Control Panel'!C$58*0.5 | E39: ='Control Panel'!$B$16*'Control Panel'!$B$10*'Control Panel'!E51*'Control Panel'!$B$45*'Control Panel'!$C$45*'Control Panel'!D$58*0.5 | F39: ='Control Panel'!$B$16*'Control Panel'!$B$10*'Control Panel'!E51*'Control Panel'!$B$45*'Control Panel'!$C$45*'Control Panel'!E$58*0.5 | G39: ='Control Panel'!$B$16*'Control Panel'!$B$10*'Control Panel'!E51*'Control Panel'!$B$45*'Control Panel'!$C$45*'Control Panel'!F$58*0.5 | H39: ='Control Panel'!$B$16*'Control Panel'!$B$10*'Control Panel'!E51*'Control Panel'!$B$45*'Control Panel'!$C$45*'Control Panel'!G$58*0.5 | I39: ='Control Panel'!$B$16*'Control Panel'!$B$10*'Control Panel'!E51*'Control Panel'!$B$45*'Control Panel'!$C$45*'Control Panel'!H$58*0.5 | J39: ='Control Panel'!$B$16*'Control Panel'!$B$10*'Control Panel'!E51*'Control Panel'!$B$45*'Control Panel'!$C$45*'Control Panel'!I$58*0.5 | K39: ='Control Panel'!$B$16*'Control Panel'!$B$10*'Control Panel'!E51*'Control Panel'!$B$45*'Control Panel'!$C$45*'Control Panel'!J$58*0.5 | L39: ='Control Panel'!$B$16*'Control Panel'!$B$10*'Control Panel'!E51*'Control Panel'!$B$45*'Control Panel'!$C$45*'Control Panel'!K$58*0.5 | M39: ='Control Panel'!$B$16*'Control Panel'!$B$10*'Control Panel'!E51*'Control Panel'!$B$45*'Control Panel'!$C$45*'Control Panel'!L$58*0.5 | N39: =SUM(C39:M39)
A40: VANCITY CU SUBTOTAL | B40: H1 2029 | C40: =C35+C36+C37+C38+C39 | D40: =D35+D36+D37+D38+D39 | E40: =E35+E36+E37+E38+E39 | F40: =F35+F36+F37+F38+F39 | G40: =G35+G36+G37+G38+G39 | H40: =H35+H36+H37+H38+H39 | I40: =I35+I36+I37+I38+I39 | J40: =J35+J36+J37+J38+J39 | ... M40: =M35+M36+M37+M38+M39 | N40: =SUM(C40:M40)
A41: SERVUS CREDIT UNION ($29.3B assets)
A42: Settlement (1.5 bps, 30%) | B42: H1 2029 | C42: ='Control Panel'!$B$17*'Control Panel'!$B$6*'Control Panel'!B52*1000000*'Control Panel'!$B$29*IF('Control Panel'!$B$100=1,'Control Panel'!B$98,'Control Panel'!$B$27)*'Control Panel'!$B$41*'Control Panel'!$C$41*'Control Panel'!B$59*(1+IF('Control Panel'!$D$93=1,'Control Panel'!$C$93,'Control Panel'!$B$30))^MAX(0,(0-'Control Panel'!$F$52)/2)*0.5 | D42: ='Control Panel'!$B$17*'Control Panel'!$B$6*'Control Panel'!B52*1000000*'Control Panel'!$B$29*IF('Control Panel'!$B$100=1,'Control Panel'!C$98,'Control Panel'!$B$27)*'Control Panel'!$B$41*'Control Panel'!$C$41*'Control Panel'!C$59*(1+IF('Control Panel'!$D$93=1,'Control Panel'!$C$93,'Control Panel'!$B$30))^MAX(0,(1-'Control Panel'!$F$52)/2)*0.5 | E42: ='Control Panel'!$B$17*'Control Panel'!$B$6*'Control Panel'!B52*1000000*'Control Panel'!$B$29*IF('Control Panel'!$B$100=1,'Control Panel'!D$98,'Control Panel'!$B$27)*'Control Panel'!$B$41*'Control Panel'!$C$41*'Control Panel'!D$59*(1+IF('Control Panel'!$D$93=1,'Control Panel'!$C$93,'Control Panel'!$B$30))^MAX(0,(2-'Control Panel'!$F$52)/2)*0.5 | F42: ='Control Panel'!$B$17*'Control Panel'!$B$6*'Control Panel'!B52*1000000*'Control Panel'!$B$29*IF('Control Panel'!$B$100=1,'Control Panel'!E$98,'Control Panel'!$B$27)*'Control Panel'!$B$41*'Control Panel'!$C$41*'Control Panel'!E$59*(1+IF('Control Panel'!$D$93=1,'Control Panel'!$C$93,'Control Panel'!$B$30))^MAX(0,(3-'Control Panel'!$F$52)/2)*0.5 | G42: ='Control Panel'!$B$17*'Control Panel'!$B$6*'Control Panel'!B52*1000000*'Control Panel'!$B$29*IF('Control Panel'!$B$100=1,'Control Panel'!F$98,'Control Panel'!$B$27)*'Control Panel'!$B$41*'Control Panel'!$C$41*'Control Panel'!F$59*(1+IF('Control Panel'!$D$93=1,'Control Panel'!$C$93,'Control Panel'!$B$30))^MAX(0,(4-'Control Panel'!$F$52)/2)*0.5 | H42: ='Control Panel'!$B$17*'Control Panel'!$B$6*'Control Panel'!B52*1000000*'Control Panel'!$B$29*IF('Control Panel'!$B$100=1,'Control Panel'!G$98,'Control Panel'!$B$27)*'Control Panel'!$B$41*'Control Panel'!$C$41*'Control Panel'!G$59*(1+IF('Control Panel'!$D$93=1,'Control Panel'!$C$93,'Control Panel'!$B$30))^MAX(0,(5-'Control Panel'!$F$52)/2)*0.5 | I42: ='Control Panel'!$B$17*'Control Panel'!$B$6*'Control Panel'!B52*1000000*'Control Panel'!$B$29*IF('Control Panel'!$B$100=1,'Control Panel'!H$98,'Control Panel'!$B$27)*'Control Panel'!$B$41*'Control Panel'!$C$41*'Control Panel'!H$59*(1+IF('Control Panel'!$D$93=1,'Control Panel'!$C$93,'Control Panel'!$B$30))^MAX(0,(6-'Control Panel'!$F$52)/2)*0.5 | J42: ='Control Panel'!$B$17*'Control Panel'!$B$6*'Control Panel'!B52*1000000*'Control Panel'!$B$29*IF('Control Panel'!$B$100=1,'Control Panel'!I$98,'Control Panel'!$B$27)*'Control Panel'!$B$41*'Control Panel'!$C$41*'Control Panel'!I$59*(1+IF('Control Panel'!$D$93=1,'Control Panel'!$C$93,'Control Panel'!$B$30))^MAX(0,(7-'Control Panel'!$F$52)/2)*0.5 | K42: ='Control Panel'!$B$17*'Control Panel'!$B$6*'Control Panel'!B52*1000000*'Control Panel'!$B$29*IF('Control Panel'!$B$100=1,'Control Panel'!J$98,'Control Panel'!$B$27)*'Control Panel'!$B$41*'Control Panel'!$C$41*'Control Panel'!J$59*(1+IF('Control Panel'!$D$93=1,'Control Panel'!$C$93,'Control Panel'!$B$30))^MAX(0,(8-'Control Panel'!$F$52)/2)*0.5 | L42: ='Control Panel'!$B$17*'Control Panel'!$B$6*'Control Panel'!B52*1000000*'Control Panel'!$B$29*IF('Control Panel'!$B$100=1,'Control Panel'!K$98,'Control Panel'!$B$27)*'Control Panel'!$B$41*'Control Panel'!$C$41*'Control Panel'!K$59*(1+IF('Control Panel'!$D$93=1,'Control Panel'!$C$93,'Control Panel'!$B$30))^MAX(0,(9-'Control Panel'!$F$52)/2)*0.5 | M42: ='Control Panel'!$B$17*'Control Panel'!$B$6*'Control Panel'!B52*1000000*'Control Panel'!$B$29*IF('Control Panel'!$B$100=1,'Control Panel'!L$98,'Control Panel'!$B$27)*'Control Panel'!$B$41*'Control Panel'!$C$41*'Control Panel'!L$59*(1+IF('Control Panel'!$D$93=1,'Control Panel'!$C$93,'Control Panel'!$B$30))^MAX(0,(10-'Control Panel'!$F$52)/2)*0.5 | N42: =SUM(C42:M42)
A43: Issuance (0.5%, 60%) | B43: H1 2029 | C43: ='Control Panel'!$B$17*'Control Panel'!$B$7*'Control Panel'!C52*1000000*IF('Control Panel'!$B$100=1,'Control Panel'!B$99,'Control Panel'!$B$28)*'Control Panel'!$B$42*'Control Panel'!$C$42*'Control Panel'!B$59*(1+IF('Control Panel'!$D$93=1,'Control Panel'!$C$93,'Control Panel'!$B$30))^MAX(0,(0-'Control Panel'!$F$52)/2)*0.5 | D43: ='Control Panel'!$B$17*'Control Panel'!$B$7*'Control Panel'!C52*1000000*IF('Control Panel'!$B$100=1,'Control Panel'!C$99,'Control Panel'!$B$28)*'Control Panel'!$B$42*'Control Panel'!$C$42*'Control Panel'!C$59*(1+IF('Control Panel'!$D$93=1,'Control Panel'!$C$93,'Control Panel'!$B$30))^MAX(0,(1-'Control Panel'!$F$52)/2)*0.5 | E43: ='Control Panel'!$B$17*'Control Panel'!$B$7*'Control Panel'!C52*1000000*IF('Control Panel'!$B$100=1,'Control Panel'!D$99,'Control Panel'!$B$28)*'Control Panel'!$B$42*'Control Panel'!$C$42*'Control Panel'!D$59*(1+IF('Control Panel'!$D$93=1,'Control Panel'!$C$93,'Control Panel'!$B$30))^MAX(0,(2-'Control Panel'!$F$52)/2)*0.5 | F43: ='Control Panel'!$B$17*'Control Panel'!$B$7*'Control Panel'!C52*1000000*IF('Control Panel'!$B$100=1,'Control Panel'!E$99,'Control Panel'!$B$28)*'Control Panel'!$B$42*'Control Panel'!$C$42*'Control Panel'!E$59*(1+IF('Control Panel'!$D$93=1,'Control Panel'!$C$93,'Control Panel'!$B$30))^MAX(0,(3-'Control Panel'!$F$52)/2)*0.5 | G43: ='Control Panel'!$B$17*'Control Panel'!$B$7*'Control Panel'!C52*1000000*IF('Control Panel'!$B$100=1,'Control Panel'!F$99,'Control Panel'!$B$28)*'Control Panel'!$B$42*'Control Panel'!$C$42*'Control Panel'!F$59*(1+IF('Control Panel'!$D$93=1,'Control Panel'!$C$93,'Control Panel'!$B$30))^MAX(0,(4-'Control Panel'!$F$52)/2)*0.5 | H43: ='Control Panel'!$B$17*'Control Panel'!$B$7*'Control Panel'!C52*1000000*IF('Control Panel'!$B$100=1,'Control Panel'!G$99,'Control Panel'!$B$28)*'Control Panel'!$B$42*'Control Panel'!$C$42*'Control Panel'!G$59*(1+IF('Control Panel'!$D$93=1,'Control Panel'!$C$93,'Control Panel'!$B$30))^MAX(0,(5-'Control Panel'!$F$52)/2)*0.5 | I43: ='Control Panel'!$B$17*'Control Panel'!$B$7*'Control Panel'!C52*1000000*IF('Control Panel'!$B$100=1,'Control Panel'!H$99,'Control Panel'!$B$28)*'Control Panel'!$B$42*'Control Panel'!$C$42*'Control Panel'!H$59*(1+IF('Control Panel'!$D$93=1,'Control Panel'!$C$93,'Control Panel'!$B$30))^MAX(0,(6-'Control Panel'!$F$52)/2)*0.5 | J43: ='Control Panel'!$B$17*'Control Panel'!$B$7*'Control Panel'!C52*1000000*IF('Control Panel'!$B$100=1,'Control Panel'!I$99,'Control Panel'!$B$28)*'Control Panel'!$B$42*'Control Panel'!$C$42*'Control Panel'!I$59*(1+IF('Control Panel'!$D$93=1,'Control Panel'!$C$93,'Control Panel'!$B$30))^MAX(0,(7-'Control Panel'!$F$52)/2)*0.5 | K43: ='Control Panel'!$B$17*'Control Panel'!$B$7*'Control Panel'!C52*1000000*IF('Control Panel'!$B$100=1,'Control Panel'!J$99,'Control Panel'!$B$28)*'Control Panel'!$B$42*'Control Panel'!$C$42*'Control Panel'!J$59*(1+IF('Control Panel'!$D$93=1,'Control Panel'!$C$93,'Control Panel'!$B$30))^MAX(0,(8-'Control Panel'!$F$52)/2)*0.5 | L43: ='Control Panel'!$B$17*'Control Panel'!$B$7*'Control Panel'!C52*1000000*IF('Control Panel'!$B$100=1,'Control Panel'!K$99,'Control Panel'!$B$28)*'Control Panel'!$B$42*'Control Panel'!$C$42*'Control Panel'!K$59*(1+IF('Control Panel'!$D$93=1,'Control Panel'!$C$93,'Control Panel'!$B$30))^MAX(0,(9-'Control Panel'!$F$52)/2)*0.5 | M43: ='Control Panel'!$B$17*'Control Panel'!$B$7*'Control Panel'!C52*1000000*IF('Control Panel'!$B$100=1,'Control Panel'!L$99,'Control Panel'!$B$28)*'Control Panel'!$B$42*'Control Panel'!$C$42*'Control Panel'!L$59*(1+IF('Control Panel'!$D$93=1,'Control Panel'!$C$93,'Control Panel'!$B$30))^MAX(0,(10-'Control Panel'!$F$52)/2)*0.5 | N43: =SUM(C43:M43)
A44: Trading (5 bps, 100%) | B44: H1 2029 | C44: ='Control Panel'!$B$17*'Control Panel'!$B$8*'Control Panel'!C52*1000000*IF('Control Panel'!$B$100=1,'Control Panel'!B$99,'Control Panel'!$B$28)*'Control Panel'!$B$62*'Control Panel'!$B$43*'Control Panel'!$C$43*'Control Panel'!B$59*(1+IF('Control Panel'!$D$93=1,'Control Panel'!$C$93,'Control Panel'!$B$30))^MAX(0,(0-'Control Panel'!$F$52)/2)*0.5 | D44: ='Control Panel'!$B$17*'Control Panel'!$B$8*'Control Panel'!C52*1000000*IF('Control Panel'!$B$100=1,'Control Panel'!C$99,'Control Panel'!$B$28)*'Control Panel'!$B$62*'Control Panel'!$B$43*'Control Panel'!$C$43*'Control Panel'!C$59*(1+IF('Control Panel'!$D$93=1,'Control Panel'!$C$93,'Control Panel'!$B$30))^MAX(0,(1-'Control Panel'!$F$52)/2)*0.5 | E44: ='Control Panel'!$B$17*'Control Panel'!$B$8*'Control Panel'!C52*1000000*IF('Control Panel'!$B$100=1,'Control Panel'!D$99,'Control Panel'!$B$28)*'Control Panel'!$B$62*'Control Panel'!$B$43*'Control Panel'!$C$43*'Control Panel'!D$59*(1+IF('Control Panel'!$D$93=1,'Control Panel'!$C$93,'Control Panel'!$B$30))^MAX(0,(2-'Control Panel'!$F$52)/2)*0.5 | F44: ='Control Panel'!$B$17*'Control Panel'!$B$8*'Control Panel'!C52*1000000*IF('Control Panel'!$B$100=1,'Control Panel'!E$99,'Control Panel'!$B$28)*'Control Panel'!$B$62*'Control Panel'!$B$43*'Control Panel'!$C$43*'Control Panel'!E$59*(1+IF('Control Panel'!$D$93=1,'Control Panel'!$C$93,'Control Panel'!$B$30))^MAX(0,(3-'Control Panel'!$F$52)/2)*0.5 | G44: ='Control Panel'!$B$17*'Control Panel'!$B$8*'Control Panel'!C52*1000000*IF('Control Panel'!$B$100=1,'Control Panel'!F$99,'Control Panel'!$B$28)*'Control Panel'!$B$62*'Control Panel'!$B$43*'Control Panel'!$C$43*'Control Panel'!F$59*(1+IF('Control Panel'!$D$93=1,'Control Panel'!$C$93,'Control Panel'!$B$30))^MAX(0,(4-'Control Panel'!$F$52)/2)*0.5 | H44: ='Control Panel'!$B$17*'Control Panel'!$B$8*'Control Panel'!C52*1000000*IF('Control Panel'!$B$100=1,'Control Panel'!G$99,'Control Panel'!$B$28)*'Control Panel'!$B$62*'Control Panel'!$B$43*'Control Panel'!$C$43*'Control Panel'!G$59*(1+IF('Control Panel'!$D$93=1,'Control Panel'!$C$93,'Control Panel'!$B$30))^MAX(0,(5-'Control Panel'!$F$52)/2)*0.5 | I44: ='Control Panel'!$B$17*'Control Panel'!$B$8*'Control Panel'!C52*1000000*IF('Control Panel'!$B$100=1,'Control Panel'!H$99,'Control Panel'!$B$28)*'Control Panel'!$B$62*'Control Panel'!$B$43*'Control Panel'!$C$43*'Control Panel'!H$59*(1+IF('Control Panel'!$D$93=1,'Control Panel'!$C$93,'Control Panel'!$B$30))^MAX(0,(6-'Control Panel'!$F$52)/2)*0.5 | J44: ='Control Panel'!$B$17*'Control Panel'!$B$8*'Control Panel'!C52*1000000*IF('Control Panel'!$B$100=1,'Control Panel'!I$99,'Control Panel'!$B$28)*'Control Panel'!$B$62*'Control Panel'!$B$43*'Control Panel'!$C$43*'Control Panel'!I$59*(1+IF('Control Panel'!$D$93=1,'Control Panel'!$C$93,'Control Panel'!$B$30))^MAX(0,(7-'Control Panel'!$F$52)/2)*0.5 | K44: ='Control Panel'!$B$17*'Control Panel'!$B$8*'Control Panel'!C52*1000000*IF('Control Panel'!$B$100=1,'Control Panel'!J$99,'Control Panel'!$B$28)*'Control Panel'!$B$62*'Control Panel'!$B$43*'Control Panel'!$C$43*'Control Panel'!J$59*(1+IF('Control Panel'!$D$93=1,'Control Panel'!$C$93,'Control Panel'!$B$30))^MAX(0,(8-'Control Panel'!$F$52)/2)*0.5 | L44: ='Control Panel'!$B$17*'Control Panel'!$B$8*'Control Panel'!C52*1000000*IF('Control Panel'!$B$100=1,'Control Panel'!K$99,'Control Panel'!$B$28)*'Control Panel'!$B$62*'Control Panel'!$B$43*'Control Panel'!$C$43*'Control Panel'!K$59*(1+IF('Control Panel'!$D$93=1,'Control Panel'!$C$93,'Control Panel'!$B$30))^MAX(0,(9-'Control Panel'!$F$52)/2)*0.5 | M44: ='Control Panel'!$B$17*'Control Panel'!$B$8*'Control Panel'!C52*1000000*IF('Control Panel'!$B$100=1,'Control Panel'!L$99,'Control Panel'!$B$28)*'Control Panel'!$B$62*'Control Panel'!$B$43*'Control Panel'!$C$43*'Control Panel'!L$59*(1+IF('Control Panel'!$D$93=1,'Control Panel'!$C$93,'Control Panel'!$B$30))^MAX(0,(10-'Control Panel'!$F$52)/2)*0.5 | N44: =SUM(C44:M44)
A45: Custody (30 bps, 40%) | B45: H1 2029 | C45: ='Control Panel'!$B$17*'Control Panel'!$B$9*'Control Panel'!D52*1000000*IF('Control Panel'!$B$100=1,'Control Panel'!B$99,'Control Panel'!$B$28)*'Control Panel'!$B$44*'Control Panel'!$C$44*'Control Panel'!B$59*(1+IF('Control Panel'!$D$93=1,'Control Panel'!$C$93,'Control Panel'!$B$30))^MAX(0,(0-'Control Panel'!$F$52)/2)*0.5 | D45: ='Control Panel'!$B$17*'Control Panel'!$B$9*'Control Panel'!D52*1000000*IF('Control Panel'!$B$100=1,'Control Panel'!C$99,'Control Panel'!$B$28)*'Control Panel'!$B$44*'Control Panel'!$C$44*'Control Panel'!C$59*(1+IF('Control Panel'!$D$93=1,'Control Panel'!$C$93,'Control Panel'!$B$30))^MAX(0,(1-'Control Panel'!$F$52)/2)*0.5 | E45: ='Control Panel'!$B$17*'Control Panel'!$B$9*'Control Panel'!D52*1000000*IF('Control Panel'!$B$100=1,'Control Panel'!D$99,'Control Panel'!$B$28)*'Control Panel'!$B$44*'Control Panel'!$C$44*'Control Panel'!D$59*(1+IF('Control Panel'!$D$93=1,'Control Panel'!$C$93,'Control Panel'!$B$30))^MAX(0,(2-'Control Panel'!$F$52)/2)*0.5 | F45: ='Control Panel'!$B$17*'Control Panel'!$B$9*'Control Panel'!D52*1000000*IF('Control Panel'!$B$100=1,'Control Panel'!E$99,'Control Panel'!$B$28)*'Control Panel'!$B$44*'Control Panel'!$C$44*'Control Panel'!E$59*(1+IF('Control Panel'!$D$93=1,'Control Panel'!$C$93,'Control Panel'!$B$30))^MAX(0,(3-'Control Panel'!$F$52)/2)*0.5 | G45: ='Control Panel'!$B$17*'Control Panel'!$B$9*'Control Panel'!D52*1000000*IF('Control Panel'!$B$100=1,'Control Panel'!F$99,'Control Panel'!$B$28)*'Control Panel'!$B$44*'Control Panel'!$C$44*'Control Panel'!F$59*(1+IF('Control Panel'!$D$93=1,'Control Panel'!$C$93,'Control Panel'!$B$30))^MAX(0,(4-'Control Panel'!$F$52)/2)*0.5 | H45: ='Control Panel'!$B$17*'Control Panel'!$B$9*'Control Panel'!D52*1000000*IF('Control Panel'!$B$100=1,'Control Panel'!G$99,'Control Panel'!$B$28)*'Control Panel'!$B$44*'Control Panel'!$C$44*'Control Panel'!G$59*(1+IF('Control Panel'!$D$93=1,'Control Panel'!$C$93,'Control Panel'!$B$30))^MAX(0,(5-'Control Panel'!$F$52)/2)*0.5 | I45: ='Control Panel'!$B$17*'Control Panel'!$B$9*'Control Panel'!D52*1000000*IF('Control Panel'!$B$100=1,'Control Panel'!H$99,'Control Panel'!$B$28)*'Control Panel'!$B$44*'Control Panel'!$C$44*'Control Panel'!H$59*(1+IF('Control Panel'!$D$93=1,'Control Panel'!$C$93,'Control Panel'!$B$30))^MAX(0,(6-'Control Panel'!$F$52)/2)*0.5 | J45: ='Control Panel'!$B$17*'Control Panel'!$B$9*'Control Panel'!D52*1000000*IF('Control Panel'!$B$100=1,'Control Panel'!I$99,'Control Panel'!$B$28)*'Control Panel'!$B$44*'Control Panel'!$C$44*'Control Panel'!I$59*(1+IF('Control Panel'!$D$93=1,'Control Panel'!$C$93,'Control Panel'!$B$30))^MAX(0,(7-'Control Panel'!$F$52)/2)*0.5 | K45: ='Control Panel'!$B$17*'Control Panel'!$B$9*'Control Panel'!D52*1000000*IF('Control Panel'!$B$100=1,'Control Panel'!J$99,'Control Panel'!$B$28)*'Control Panel'!$B$44*'Control Panel'!$C$44*'Control Panel'!J$59*(1+IF('Control Panel'!$D$93=1,'Control Panel'!$C$93,'Control Panel'!$B$30))^MAX(0,(8-'Control Panel'!$F$52)/2)*0.5 | L45: ='Control Panel'!$B$17*'Control Panel'!$B$9*'Control Panel'!D52*1000000*IF('Control Panel'!$B$100=1,'Control Panel'!K$99,'Control Panel'!$B$28)*'Control Panel'!$B$44*'Control Panel'!$C$44*'Control Panel'!K$59*(1+IF('Control Panel'!$D$93=1,'Control Panel'!$C$93,'Control Panel'!$B$30))^MAX(0,(9-'Control Panel'!$F$52)/2)*0.5 | M45: ='Control Panel'!$B$17*'Control Panel'!$B$9*'Control Panel'!D52*1000000*IF('Control Panel'!$B$100=1,'Control Panel'!L$99,'Control Panel'!$B$28)*'Control Panel'!$B$44*'Control Panel'!$C$44*'Control Panel'!L$59*(1+IF('Control Panel'!$D$93=1,'Control Panel'!$C$93,'Control Panel'!$B$30))^MAX(0,(10-'Control Panel'!$F$52)/2)*0.5 | N45: =SUM(C45:M45)
A46: SaaS + APIs (80%) | B46: H1 2029 | C46: ='Control Panel'!$B$17*'Control Panel'!$B$10*'Control Panel'!E52*'Control Panel'!$B$45*'Control Panel'!$C$45*'Control Panel'!B$59*0.5 | D46: ='Control Panel'!$B$17*'Control Panel'!$B$10*'Control Panel'!E52*'Control Panel'!$B$45*'Control Panel'!$C$45*'Control Panel'!C$59*0.5 | E46: ='Control Panel'!$B$17*'Control Panel'!$B$10*'Control Panel'!E52*'Control Panel'!$B$45*'Control Panel'!$C$45*'Control Panel'!D$59*0.5 | F46: ='Control Panel'!$B$17*'Control Panel'!$B$10*'Control Panel'!E52*'Control Panel'!$B$45*'Control Panel'!$C$45*'Control Panel'!E$59*0.5 | G46: ='Control Panel'!$B$17*'Control Panel'!$B$10*'Control Panel'!E52*'Control Panel'!$B$45*'Control Panel'!$C$45*'Control Panel'!F$59*0.5 | H46: ='Control Panel'!$B$17*'Control Panel'!$B$10*'Control Panel'!E52*'Control Panel'!$B$45*'Control Panel'!$C$45*'Control Panel'!G$59*0.5 | I46: ='Control Panel'!$B$17*'Control Panel'!$B$10*'Control Panel'!E52*'Control Panel'!$B$45*'Control Panel'!$C$45*'Control Panel'!H$59*0.5 | J46: ='Control Panel'!$B$17*'Control Panel'!$B$10*'Control Panel'!E52*'Control Panel'!$B$45*'Control Panel'!$C$45*'Control Panel'!I$59*0.5 | K46: ='Control Panel'!$B$17*'Control Panel'!$B$10*'Control Panel'!E52*'Control Panel'!$B$45*'Control Panel'!$C$45*'Control Panel'!J$59*0.5 | L46: ='Control Panel'!$B$17*'Control Panel'!$B$10*'Control Panel'!E52*'Control Panel'!$B$45*'Control Panel'!$C$45*'Control Panel'!K$59*0.5 | M46: ='Control Panel'!$B$17*'Control Panel'!$B$10*'Control Panel'!E52*'Control Panel'!$B$45*'Control Panel'!$C$45*'Control Panel'!L$59*0.5 | N46: =SUM(C46:M46)
A47: SERVUS SUBTOTAL | B47: H1 2029 | C47: =C42+C43+C44+C45+C46 | D47: =D42+D43+D44+D45+D46 | E47: =E42+E43+E44+E45+E46 | F47: =F42+F43+F44+F45+F46 | G47: =G42+G43+G44+G45+G46 | H47: =H42+H43+H44+H45+H46 | I47: =I42+I43+I44+I45+I46 | J47: =J42+J43+J44+J45+J46 | ... M47: =M42+M43+M44+M45+M46 | N47: =SUM(C47:M47)
A48: (REMOVED - (reserved slot) out of scope)
A49: (reserved slot) | B49: 0 | C49: 0 | D49: 0 | E49: 0 | F49: 0 | G49: 0 | H49: 0 | I49: 0 | J49: 0 | K49: 0 | L49: 0 | M49: 0 | N49: 0
A50: (RESERVED - 6th revenue stream placeholder; currently OFF)
A51: (reserved - ATB Financial ) | B51: H1 2028 | C51: ='Control Panel'!$B$14*'Control Panel'!$B$138*'Control Panel'!$B$140*'Control Panel'!$B$139*'Control Panel'!B$56*(1+IF('Control Panel'!$D$90=1,'Control Panel'!$C$90,'Control Panel'!$B$30))^MAX(0,(0-1)/2)*0.5 | D51: ='Control Panel'!$B$14*'Control Panel'!$B$138*'Control Panel'!$B$140*'Control Panel'!$B$139*'Control Panel'!C$56*(1+IF('Control Panel'!$D$90=1,'Control Panel'!$C$90,'Control Panel'!$B$30))^MAX(0,(1-1)/2)*0.5 | E51: ='Control Panel'!$B$14*'Control Panel'!$B$138*'Control Panel'!$B$140*'Control Panel'!$B$139*'Control Panel'!D$56*(1+IF('Control Panel'!$D$90=1,'Control Panel'!$C$90,'Control Panel'!$B$30))^MAX(0,(2-1)/2)*0.5 | F51: ='Control Panel'!$B$14*'Control Panel'!$B$138*'Control Panel'!$B$140*'Control Panel'!$B$139*'Control Panel'!E$56*(1+IF('Control Panel'!$D$90=1,'Control Panel'!$C$90,'Control Panel'!$B$30))^MAX(0,(3-1)/2)*0.5 | G51: ='Control Panel'!$B$14*'Control Panel'!$B$138*'Control Panel'!$B$140*'Control Panel'!$B$139*'Control Panel'!F$56*(1+IF('Control Panel'!$D$90=1,'Control Panel'!$C$90,'Control Panel'!$B$30))^MAX(0,(4-1)/2)*0.5 | H51: ='Control Panel'!$B$14*'Control Panel'!$B$138*'Control Panel'!$B$140*'Control Panel'!$B$139*'Control Panel'!G$56*(1+IF('Control Panel'!$D$90=1,'Control Panel'!$C$90,'Control Panel'!$B$30))^MAX(0,(5-1)/2)*0.5 | I51: ='Control Panel'!$B$14*'Control Panel'!$B$138*'Control Panel'!$B$140*'Control Panel'!$B$139*'Control Panel'!H$56*(1+IF('Control Panel'!$D$90=1,'Control Panel'!$C$90,'Control Panel'!$B$30))^MAX(0,(6-1)/2)*0.5 | J51: ='Control Panel'!$B$14*'Control Panel'!$B$138*'Control Panel'!$B$140*'Control Panel'!$B$139*'Control Panel'!I$56*(1+IF('Control Panel'!$D$90=1,'Control Panel'!$C$90,'Control Panel'!$B$30))^MAX(0,(7-1)/2)*0.5 | K51: ='Control Panel'!$B$14*'Control Panel'!$B$138*'Control Panel'!$B$140*'Control Panel'!$B$139*'Control Panel'!J$56*(1+IF('Control Panel'!$D$90=1,'Control Panel'!$C$90,'Control Panel'!$B$30))^MAX(0,(8-1)/2)*0.5 | L51: ='Control Panel'!$B$14*'Control Panel'!$B$138*'Control Panel'!$B$140*'Control Panel'!$B$139*'Control Panel'!K$56*(1+IF('Control Panel'!$D$90=1,'Control Panel'!$C$90,'Control Panel'!$B$30))^MAX(0,(9-1)/2)*0.5 | M51: ='Control Panel'!$B$14*'Control Panel'!$B$138*'Control Panel'!$B$140*'Control Panel'!$B$139*'Control Panel'!L$56*(1+IF('Control Panel'!$D$90=1,'Control Panel'!$C$90,'Control Panel'!$B$30))^MAX(0,(10-1)/2)*0.5 | N51: =SUM(C51:M51)
A52: (reserved - Bow Valley CU ) | B52: H1 2028 | C52: ='Control Panel'!$B$15*'Control Panel'!$B$138*'Control Panel'!$B$141*'Control Panel'!$B$139*'Control Panel'!B$57*(1+IF('Control Panel'!$D$91=1,'Control Panel'!$C$91,'Control Panel'!$B$30))^MAX(0,(0-1)/2)*0.5 | D52: ='Control Panel'!$B$15*'Control Panel'!$B$138*'Control Panel'!$B$141*'Control Panel'!$B$139*'Control Panel'!C$57*(1+IF('Control Panel'!$D$91=1,'Control Panel'!$C$91,'Control Panel'!$B$30))^MAX(0,(1-1)/2)*0.5 | E52: ='Control Panel'!$B$15*'Control Panel'!$B$138*'Control Panel'!$B$141*'Control Panel'!$B$139*'Control Panel'!D$57*(1+IF('Control Panel'!$D$91=1,'Control Panel'!$C$91,'Control Panel'!$B$30))^MAX(0,(2-1)/2)*0.5 | F52: ='Control Panel'!$B$15*'Control Panel'!$B$138*'Control Panel'!$B$141*'Control Panel'!$B$139*'Control Panel'!E$57*(1+IF('Control Panel'!$D$91=1,'Control Panel'!$C$91,'Control Panel'!$B$30))^MAX(0,(3-1)/2)*0.5 | G52: ='Control Panel'!$B$15*'Control Panel'!$B$138*'Control Panel'!$B$141*'Control Panel'!$B$139*'Control Panel'!F$57*(1+IF('Control Panel'!$D$91=1,'Control Panel'!$C$91,'Control Panel'!$B$30))^MAX(0,(4-1)/2)*0.5 | H52: ='Control Panel'!$B$15*'Control Panel'!$B$138*'Control Panel'!$B$141*'Control Panel'!$B$139*'Control Panel'!G$57*(1+IF('Control Panel'!$D$91=1,'Control Panel'!$C$91,'Control Panel'!$B$30))^MAX(0,(5-1)/2)*0.5 | I52: ='Control Panel'!$B$15*'Control Panel'!$B$138*'Control Panel'!$B$141*'Control Panel'!$B$139*'Control Panel'!H$57*(1+IF('Control Panel'!$D$91=1,'Control Panel'!$C$91,'Control Panel'!$B$30))^MAX(0,(6-1)/2)*0.5 | J52: ='Control Panel'!$B$15*'Control Panel'!$B$138*'Control Panel'!$B$141*'Control Panel'!$B$139*'Control Panel'!I$57*(1+IF('Control Panel'!$D$91=1,'Control Panel'!$C$91,'Control Panel'!$B$30))^MAX(0,(7-1)/2)*0.5 | K52: ='Control Panel'!$B$15*'Control Panel'!$B$138*'Control Panel'!$B$141*'Control Panel'!$B$139*'Control Panel'!J$57*(1+IF('Control Panel'!$D$91=1,'Control Panel'!$C$91,'Control Panel'!$B$30))^MAX(0,(8-1)/2)*0.5 | L52: ='Control Panel'!$B$15*'Control Panel'!$B$138*'Control Panel'!$B$141*'Control Panel'!$B$139*'Control Panel'!K$57*(1+IF('Control Panel'!$D$91=1,'Control Panel'!$C$91,'Control Panel'!$B$30))^MAX(0,(9-1)/2)*0.5 | M52: ='Control Panel'!$B$15*'Control Panel'!$B$138*'Control Panel'!$B$141*'Control Panel'!$B$139*'Control Panel'!L$57*(1+IF('Control Panel'!$D$91=1,'Control Panel'!$C$91,'Control Panel'!$B$30))^MAX(0,(10-1)/2)*0.5 | N52: =SUM(C52:M52)
A53: (reserved - Vancity CU ) | B53: H1 2029 | C53: ='Control Panel'!$B$16*'Control Panel'!$B$138*'Control Panel'!$B$142*'Control Panel'!$B$139*'Control Panel'!B$58*(1+IF('Control Panel'!$D$92=1,'Control Panel'!$C$92,'Control Panel'!$B$30))^MAX(0,(0-3)/2)*0.5 | D53: ='Control Panel'!$B$16*'Control Panel'!$B$138*'Control Panel'!$B$142*'Control Panel'!$B$139*'Control Panel'!C$58*(1+IF('Control Panel'!$D$92=1,'Control Panel'!$C$92,'Control Panel'!$B$30))^MAX(0,(1-3)/2)*0.5 | E53: ='Control Panel'!$B$16*'Control Panel'!$B$138*'Control Panel'!$B$142*'Control Panel'!$B$139*'Control Panel'!D$58*(1+IF('Control Panel'!$D$92=1,'Control Panel'!$C$92,'Control Panel'!$B$30))^MAX(0,(2-3)/2)*0.5 | F53: ='Control Panel'!$B$16*'Control Panel'!$B$138*'Control Panel'!$B$142*'Control Panel'!$B$139*'Control Panel'!E$58*(1+IF('Control Panel'!$D$92=1,'Control Panel'!$C$92,'Control Panel'!$B$30))^MAX(0,(3-3)/2)*0.5 | G53: ='Control Panel'!$B$16*'Control Panel'!$B$138*'Control Panel'!$B$142*'Control Panel'!$B$139*'Control Panel'!F$58*(1+IF('Control Panel'!$D$92=1,'Control Panel'!$C$92,'Control Panel'!$B$30))^MAX(0,(4-3)/2)*0.5 | H53: ='Control Panel'!$B$16*'Control Panel'!$B$138*'Control Panel'!$B$142*'Control Panel'!$B$139*'Control Panel'!G$58*(1+IF('Control Panel'!$D$92=1,'Control Panel'!$C$92,'Control Panel'!$B$30))^MAX(0,(5-3)/2)*0.5 | I53: ='Control Panel'!$B$16*'Control Panel'!$B$138*'Control Panel'!$B$142*'Control Panel'!$B$139*'Control Panel'!H$58*(1+IF('Control Panel'!$D$92=1,'Control Panel'!$C$92,'Control Panel'!$B$30))^MAX(0,(6-3)/2)*0.5 | J53: ='Control Panel'!$B$16*'Control Panel'!$B$138*'Control Panel'!$B$142*'Control Panel'!$B$139*'Control Panel'!I$58*(1+IF('Control Panel'!$D$92=1,'Control Panel'!$C$92,'Control Panel'!$B$30))^MAX(0,(7-3)/2)*0.5 | K53: ='Control Panel'!$B$16*'Control Panel'!$B$138*'Control Panel'!$B$142*'Control Panel'!$B$139*'Control Panel'!J$58*(1+IF('Control Panel'!$D$92=1,'Control Panel'!$C$92,'Control Panel'!$B$30))^MAX(0,(8-3)/2)*0.5 | L53: ='Control Panel'!$B$16*'Control Panel'!$B$138*'Control Panel'!$B$142*'Control Panel'!$B$139*'Control Panel'!K$58*(1+IF('Control Panel'!$D$92=1,'Control Panel'!$C$92,'Control Panel'!$B$30))^MAX(0,(9-3)/2)*0.5 | M53: ='Control Panel'!$B$16*'Control Panel'!$B$138*'Control Panel'!$B$142*'Control Panel'!$B$139*'Control Panel'!L$58*(1+IF('Control Panel'!$D$92=1,'Control Panel'!$C$92,'Control Panel'!$B$30))^MAX(0,(10-3)/2)*0.5 | N53: =SUM(C53:M53)
A54: (reserved - Servus CU ) | B54: H1 2029 | C54: ='Control Panel'!$B$17*'Control Panel'!$B$138*'Control Panel'!$B$143*'Control Panel'!$B$139*'Control Panel'!B$59*(1+IF('Control Panel'!$D$93=1,'Control Panel'!$C$93,'Control Panel'!$B$30))^MAX(0,(0-3)/2)*0.5 | D54: ='Control Panel'!$B$17*'Control Panel'!$B$138*'Control Panel'!$B$143*'Control Panel'!$B$139*'Control Panel'!C$59*(1+IF('Control Panel'!$D$93=1,'Control Panel'!$C$93,'Control Panel'!$B$30))^MAX(0,(1-3)/2)*0.5 | E54: ='Control Panel'!$B$17*'Control Panel'!$B$138*'Control Panel'!$B$143*'Control Panel'!$B$139*'Control Panel'!D$59*(1+IF('Control Panel'!$D$93=1,'Control Panel'!$C$93,'Control Panel'!$B$30))^MAX(0,(2-3)/2)*0.5 | F54: ='Control Panel'!$B$17*'Control Panel'!$B$138*'Control Panel'!$B$143*'Control Panel'!$B$139*'Control Panel'!E$59*(1+IF('Control Panel'!$D$93=1,'Control Panel'!$C$93,'Control Panel'!$B$30))^MAX(0,(3-3)/2)*0.5 | G54: ='Control Panel'!$B$17*'Control Panel'!$B$138*'Control Panel'!$B$143*'Control Panel'!$B$139*'Control Panel'!F$59*(1+IF('Control Panel'!$D$93=1,'Control Panel'!$C$93,'Control Panel'!$B$30))^MAX(0,(4-3)/2)*0.5 | H54: ='Control Panel'!$B$17*'Control Panel'!$B$138*'Control Panel'!$B$143*'Control Panel'!$B$139*'Control Panel'!G$59*(1+IF('Control Panel'!$D$93=1,'Control Panel'!$C$93,'Control Panel'!$B$30))^MAX(0,(5-3)/2)*0.5 | I54: ='Control Panel'!$B$17*'Control Panel'!$B$138*'Control Panel'!$B$143*'Control Panel'!$B$139*'Control Panel'!H$59*(1+IF('Control Panel'!$D$93=1,'Control Panel'!$C$93,'Control Panel'!$B$30))^MAX(0,(6-3)/2)*0.5 | J54: ='Control Panel'!$B$17*'Control Panel'!$B$138*'Control Panel'!$B$143*'Control Panel'!$B$139*'Control Panel'!I$59*(1+IF('Control Panel'!$D$93=1,'Control Panel'!$C$93,'Control Panel'!$B$30))^MAX(0,(7-3)/2)*0.5 | K54: ='Control Panel'!$B$17*'Control Panel'!$B$138*'Control Panel'!$B$143*'Control Panel'!$B$139*'Control Panel'!J$59*(1+IF('Control Panel'!$D$93=1,'Control Panel'!$C$93,'Control Panel'!$B$30))^MAX(0,(8-3)/2)*0.5 | L54: ='Control Panel'!$B$17*'Control Panel'!$B$138*'Control Panel'!$B$143*'Control Panel'!$B$139*'Control Panel'!K$59*(1+IF('Control Panel'!$D$93=1,'Control Panel'!$C$93,'Control Panel'!$B$30))^MAX(0,(9-3)/2)*0.5 | M54: ='Control Panel'!$B$17*'Control Panel'!$B$138*'Control Panel'!$B$143*'Control Panel'!$B$139*'Control Panel'!L$59*(1+IF('Control Panel'!$D$93=1,'Control Panel'!$C$93,'Control Panel'!$B$30))^MAX(0,(10-3)/2)*0.5 | N54: =SUM(C54:M54)
A55: (reserved subtotal) | C55: =C51+C52+C53+C54 | D55: =D51+D52+D53+D54 | E55: =E51+E52+E53+E54 | F55: =F51+F52+F53+F54 | G55: =G51+G52+G53+G54 | H55: =H51+H52+H53+H54 | I55: =I51+I52+I53+I54 | J55: =J51+J52+J53+J54 | ... M55: =M51+M52+M53+M54 | N55: =SUM(C55:M55)
A56: (reserved for future gainshare arrangements; currently 0)
A58: TOTAL REVENUE (All FIs + (reserved)) | C58: =C26+C33+C40+C47+C49+C55 | D58: =D26+D33+D40+D47+D49+D55 | E58: =E26+E33+E40+E47+E49+E55 | F58: =F26+F33+F40+F47+F49+F55 | G58: =G26+G33+G40+G47+G49+G55 | H58: =H26+H33+H40+H47+H49+H55 | I58: =I26+I33+I40+I47+I49+I55 | J58: =J26+J33+J40+J47+J49+J55 | ... M58: =M26+M33+M40+M47+M49+M55 | N58: =SUM(C58:M58)
A60: REVENUE BREAKDOWN BY STREAM (ALL FIs)
A61: Stream | C61: H2 2026 | D61: H1 2027 | E61: H2 2027 | F61: H1 2028 | G61: H2 2028 | H61: H1 2029 | I61: H2 2029 | J61: H1 2030 | K61: H2 2030 | L61: H1 2031 | M61: H2 2031 | N61: 5-Year Total
A62: Settlement Fees (1.5 bps) | C62: =C21+C28+C35+C42 | D62: =D21+D28+D35+D42 | E62: =E21+E28+E35+E42 | F62: =F21+F28+F35+F42 | G62: =G21+G28+G35+G42 | H62: =H21+H28+H35+H42 | I62: =I21+I28+I35+I42 | J62: =J21+J28+J35+J42 | ... M62: =M21+M28+M35+M42 | N62: =SUM(C62:M62)
A63: Issuance Fees (0.5%) | C63: =C22+C29+C36+C43 | D63: =D22+D29+D36+D43 | E63: =E22+E29+E36+E43 | F63: =F22+F29+F36+F43 | G63: =G22+G29+G36+G43 | H63: =H22+H29+H36+H43 | I63: =I22+I29+I36+I43 | J63: =J22+J29+J36+J43 | ... M63: =M22+M29+M36+M43 | N63: =SUM(C63:M63)
A64: Trading Fees (5 bps) | C64: =C23+C30+C37+C44 | D64: =D23+D30+D37+D44 | E64: =E23+E30+E37+E44 | F64: =F23+F30+F37+F44 | G64: =G23+G30+G37+G44 | H64: =H23+H30+H37+H44 | I64: =I23+I30+I37+I44 | J64: =J23+J30+J37+J44 | ... M64: =M23+M30+M37+M44 | N64: =SUM(C64:M64)
A65: Custody Fees (30 bps) | C65: =C24+C31+C38+C45 | D65: =D24+D31+D38+D45 | E65: =E24+E31+E38+E45 | F65: =F24+F31+F38+F45 | G65: =G24+G31+G38+G45 | H65: =H24+H31+H38+H45 | I65: =I24+I31+I38+I45 | J65: =J24+J31+J38+J45 | ... M65: =M24+M31+M38+M45 | N65: =SUM(C65:M65)
A66: SaaS + APIs | C66: =C25+C32+C39+C46 | D66: =D25+D32+D39+D46 | E66: =E25+E32+E39+E46 | F66: =F25+F32+F39+F46 | G66: =G25+G32+G39+G46 | H66: =H25+H32+H39+H46 | I66: =I25+I32+I39+I46 | J66: =J25+J32+J39+J46 | ... M66: =M25+M32+M39+M46 | N66: =SUM(C66:M66)
A67: (reserved) | C67: 0 | D67: 0 | E67: 0 | F67: 0 | G67: 0 | H67: 0 | I67: 0 | J67: 0 | K67: 0 | L67: 0 | M67: 0 | N67: 0
A68: (reserved 6th stream) | C68: =C55 | D68: =D55 | E68: =E55 | F68: =F55 | G68: =G55 | H68: =H55 | I68: =I55 | J68: =J55 | ... M68: =M55 | N68: =SUM(C68:M68)
A69: TOTAL | C69: =C58 | D69: =D58 | E69: =E58 | F69: =F58 | G69: =G58 | H69: =H58 | I69: =I58 | J69: =J58 | ... M69: =M58 | N69: =SUM(C69:M69)

Sheet 5-Year P&L Summary
A1: 4ORM FINANCE - 5-YEAR P&L | Lean BUILD | 5 STREAMS + 4 FIs + (reserved) | SEMI-ANNUAL
A2: All revenue formulas reference Revenue Model sheet. Expenses reference DevEx and OpEx sheets. | Semi-annual periods.
A4: Line Item | B4: H2 2026 | C4: H1 2027 | D4: H2 2027 | E4: H1 2028 | F4: H2 2028 | G4: H1 2029 | H4: H2 2029 | I4: H1 2030 | J4: H2 2030 | K4: H1 2031 | L4: H2 2031 | M4: 5-Year Total | N4: Notes
A5: REVENUE
A6: Settlement Fees (1.5 bps, 4ORM 30%) | B6: ='Revenue Model'!C62 | C6: ='Revenue Model'!D62 | D6: ='Revenue Model'!E62 | E6: ='Revenue Model'!F62 | F6: ='Revenue Model'!G62 | G6: ='Revenue Model'!H62 | H6: ='Revenue Model'!I62 | I6: ='Revenue Model'!J62 | ... L6: ='Revenue Model'!M62 | M6: =SUM(B6:L6)
A7: Issuance Fees (0.5%, 4ORM 60%) | B7: ='Revenue Model'!C63 | C7: ='Revenue Model'!D63 | D7: ='Revenue Model'!E63 | E7: ='Revenue Model'!F63 | F7: ='Revenue Model'!G63 | G7: ='Revenue Model'!H63 | H7: ='Revenue Model'!I63 | I7: ='Revenue Model'!J63 | ... L7: ='Revenue Model'!M63 | M7: =SUM(B7:L7)
A8: Trading Fees (5 bps, 4ORM 100%) | B8: ='Revenue Model'!C64 | C8: ='Revenue Model'!D64 | D8: ='Revenue Model'!E64 | E8: ='Revenue Model'!F64 | F8: ='Revenue Model'!G64 | G8: ='Revenue Model'!H64 | H8: ='Revenue Model'!I64 | I8: ='Revenue Model'!J64 | ... L8: ='Revenue Model'!M64 | M8: =SUM(B8:L8)
A9: Custody Fees (30 bps, 4ORM 40%) | B9: ='Revenue Model'!C65 | C9: ='Revenue Model'!D65 | D9: ='Revenue Model'!E65 | E9: ='Revenue Model'!F65 | F9: ='Revenue Model'!G65 | G9: ='Revenue Model'!H65 | H9: ='Revenue Model'!I65 | I9: ='Revenue Model'!J65 | ... L9: ='Revenue Model'!M65 | M9: =SUM(B9:L9)
A10: SaaS + APIs ($25K/mo, 4ORM 80%) | B10: ='Revenue Model'!C66 | C10: ='Revenue Model'!D66 | D10: ='Revenue Model'!E66 | E10: ='Revenue Model'!F66 | F10: ='Revenue Model'!G66 | G10: ='Revenue Model'!H66 | H10: ='Revenue Model'!I66 | I10: ='Revenue Model'!J66 | ... L10: ='Revenue Model'!M66 | M10: =SUM(B10:L10)
A11: (reserved) | B11: ='Revenue Model'!C67 | C11: ='Revenue Model'!D67 | D11: ='Revenue Model'!E67 | E11: ='Revenue Model'!F67 | F11: ='Revenue Model'!G67 | G11: ='Revenue Model'!H67 | H11: ='Revenue Model'!I67 | I11: ='Revenue Model'!J67 | ... L11: ='Revenue Model'!M67 | M11: =SUM(B11:L11)
A12: (Reserved 6th Stream) | B12: ='Revenue Model'!C68 | C12: ='Revenue Model'!D68 | D12: ='Revenue Model'!E68 | E12: ='Revenue Model'!F68 | F12: ='Revenue Model'!G68 | G12: ='Revenue Model'!H68 | H12: ='Revenue Model'!I68 | I12: ='Revenue Model'!J68 | ... L12: ='Revenue Model'!M68 | M12: =SUM(B12:L12) | N12: New: value-based pricing on verified settlement savings
A13: TOTAL REVENUE | B13: =B6+B7+B8+B9+B10+B11+B12 | C13: =C6+C7+C8+C9+C10+C11+C12 | D13: =D6+D7+D8+D9+D10+D11+D12 | E13: =E6+E7+E8+E9+E10+E11+E12 | F13: =F6+F7+F8+F9+F10+F11+F12 | G13: =G6+G7+G8+G9+G10+G11+G12 | H13: =H6+H7+H8+H9+H10+H11+H12 | I13: =I6+I7+I8+I9+I10+I11+I12 | ... L13: =L6+L7+L8+L9+L10+L11+L12 | M13: =SUM(B13:L13)
A14: NON-DILUTIVE CAPITAL / GRANTS
A15: Total Grant Income (Toggled Programs) | B15: ='Control Panel'!C134 | C15: ='Control Panel'!D134 | D15: ='Control Panel'!E134 | E15: ='Control Panel'!F134 | F15: ='Control Panel'!G134 | G15: ='Control Panel'!H134 | H15: ='Control Panel'!I134 | I15: ='Control Panel'!J134 | ... L15: ='Control Panel'!M134 | M15: =SUM(B15:L15)
A16: TOTAL REVENUE + GRANTS | B16: =B13+B15 | C16: =C13+C15 | D16: =D13+D15 | E16: =E13+E15 | F16: =F13+F15 | G16: =G13+G15 | H16: =H13+H15 | I16: =I13+I15 | ... L16: =L13+L15 | M16: =SUM(B16:L16)
A18: DEVELOPMENT EXPENSES (DevEx)
A19: TOTAL DevEx (scenario per CP B20) | B19: =IF('Control Panel'!$B$20=1,'DevEx - Build Costs'!C35,'DevEx - Build Costs'!C36) | C19: =IF('Control Panel'!$B$20=1,'DevEx - Build Costs'!D35,'DevEx - Build Costs'!D36) | D19: =IF('Control Panel'!$B$20=1,'DevEx - Build Costs'!E35,'DevEx - Build Costs'!E36) | E19: =IF('Control Panel'!$B$20=1,'DevEx - Build Costs'!F35,'DevEx - Build Costs'!F36) | F19: =IF('Control Panel'!$B$20=1,'DevEx - Build Costs'!G35,'DevEx - Build Costs'!G36) | G19: =IF('Control Panel'!$B$20=1,'DevEx - Build Costs'!H35,'DevEx - Build Costs'!H36) | H19: =IF('Control Panel'!$B$20=1,'DevEx - Build Costs'!I35,'DevEx - Build Costs'!I36) | I19: =IF('Control Panel'!$B$20=1,'DevEx - Build Costs'!J35,'DevEx - Build Costs'!J36) | ... L19: =IF('Control Panel'!$B$20=1,'DevEx - Build Costs'!M35,'DevEx - Build Costs'!M36) | M19: =SUM(B19:L19)
A21: OPERATING EXPENSES (OpEx)
A22: TOTAL OpEx (scenario per CP B20) | B22: =IF('Control Panel'!$B$20=1,'OpEx - Ongoing'!C38,'OpEx - Ongoing'!C39) | C22: =IF('Control Panel'!$B$20=1,'OpEx - Ongoing'!D38,'OpEx - Ongoing'!D39) | D22: =IF('Control Panel'!$B$20=1,'OpEx - Ongoing'!E38,'OpEx - Ongoing'!E39) | E22: =IF('Control Panel'!$B$20=1,'OpEx - Ongoing'!F38,'OpEx - Ongoing'!F39) | F22: =IF('Control Panel'!$B$20=1,'OpEx - Ongoing'!G38,'OpEx - Ongoing'!G39) | G22: =IF('Control Panel'!$B$20=1,'OpEx - Ongoing'!H38,'OpEx - Ongoing'!H39) | H22: =IF('Control Panel'!$B$20=1,'OpEx - Ongoing'!I38,'OpEx - Ongoing'!I39) | I22: =IF('Control Panel'!$B$20=1,'OpEx - Ongoing'!J38,'OpEx - Ongoing'!J39) | ... L22: =IF('Control Panel'!$B$20=1,'OpEx - Ongoing'!M38,'OpEx - Ongoing'!M39) | M22: =SUM(B22:L22)
A24: TOTAL ALL EXPENSES | B24: =B19+B22 | C24: =C19+C22 | D24: =D19+D22 | E24: =E19+E22 | F24: =F19+F22 | G24: =G19+G22 | H24: =H19+H22 | I24: =I19+I22 | ... L24: =L19+L22 | M24: =SUM(B24:L24)
A26: NET PROFIT (LOSS) | B26: =B16-B24 | C26: =C16-C24 | D26: =D16-D24 | E26: =E16-E24 | F26: =F16-F24 | G26: =G16-G24 | H26: =H16-H24 | I26: =I16-I24 | ... L26: =L16-L24 | M26: =SUM(B26:L26)
A27: Net Margin % | B27: =IF(B16=0,0,B26/B16) | C27: =IF(C16=0,0,C26/C16) | D27: =IF(D16=0,0,D26/D16) | E27: =IF(E16=0,0,E26/E16) | F27: =IF(F16=0,0,F26/F16) | G27: =IF(G16=0,0,G26/G16) | H27: =IF(H16=0,0,H26/H16) | I27: =IF(I16=0,0,I26/I16) | ... M27: =IF(M16=0,0,M26/M16)
A28: Cumulative Net Income (Loss) | B28: =B26 | C28: =B28+C26 | D28: =C28+D26 | E28: =D28+E26 | F28: =E28+F26 | G28: =F28+G26 | H28: =G28+H26 | I28: =H28+I26 | J28: =I28+J26 | ... L28: =K28+L26 | M28: =L28

Sheet Ondo Benchmark
A1: 4ORM FINANCE - ONDO FINANCE BENCHMARK COMPARISON
A2: Ondo (~50-100 employees, $3.6B TVL) vs 4ORM at multi-FI trajectory | Sources: Tracxn, DefiLlama, PitchBook
A4: Metric | B4: Ondo Finance | C4: 4ORM Year 1 | D4: 4ORM Year 3 | E4: 4ORM Year 5 | F4: Ratio | G4: Notes
A5: Total Employees | B5: 50-100 | C5: 12 (Lean) / 18 (Trad) | D5: 22 (Lean) / 28 (Trad) | E5: 26 (Lean) / 33 (Trad) | F5: ~3x | G5: Lean build = 35% fewer eng roles
A6: Engineering Team | B6: 25-40 | C6: 5 | D6: 9 | E6: 11 | F6: ~3x | G6: 4ORM efficiency-augmented dev
A7: TVL / AUM | B7: $3.6B | C7: $433M | D7: $800M+ | E7: $1.5B+ | F7: ~2.5x | G7: 1% tokenization across 4 FIs
A8: Annual Revenue | B8: $5-10M est. | C8: ='5-Year P&L Summary'!D13+'5-Year P&L Summary'!E13 | D8: ='5-Year P&L Summary'!H13+'5-Year P&L Summary'!I13 | E8: ='5-Year P&L Summary'!L13+'5-Year P&L Summary'!M13 | F8: ~0.5-1x | G8: 4ORM: 5 streams + (reserved)
A9: Annual OpEx (Lean Build) | B9: $8-15M est. | C9: ='OpEx - Ongoing'!D38+'OpEx - Ongoing'!E38 | D9: ='OpEx - Ongoing'!H38+'OpEx - Ongoing'!I38 | E9: ='OpEx - Ongoing'!L38+'OpEx - Ongoing'!M38 | F9: ~2-3x | G9: Canadian costs lower than SF/NYC
A10: Funding Raised | B10: $24M | C10: $3M pre-seed (unit offering) | D10: $10-15M Series A | E10: $20-30M | F10: ~1x at scale
A11: Revenue Model | B11: Spread + 15-20bps | C11: 5 streams + SaaS | D11: Full stack + E-xfer | E11: Full stack + E-xfer | F11: - | G11: Diversified: 5 fee pools + SaaS
A12: Gross Margin | B12: ~60-70% | C12: 60-65% blended | D12: 65-70% | E12: 70-79% | F12: ~1x | G12: 79% gross on core platform fees
A13: Build Approach | B13: Traditional (100 ppl) | C13: SPEER + lean dev hybrid | D13: Lean + scaling | E13: Lean mature | F13: - | G13: 35% headcount savings

Sheet Sources & Validation
A1: SOURCES & VALIDATION
A3: ATB FINANCIAL FY2025 - ANNUAL REPORT SOURCES
A4: Data Point | B4: Value | C4: Source | D4: Reference | E4: Date | F4: Notes
A5: ATB Total Deposits | B5: $43,332M | C5: ATB Annual Report FY2025 | D5: p.20 Financial Position table | E5: FY2025 (March 31, 2025) | F5: Up 6.8% YoY from $40,583M
A6: ATB Net Loans | B6: $54,317M | C6: ATB Annual Report FY2025 | D6: p.20 Financial Position table | E6: FY2025 | F6: Up 6.0% YoY
A7: ATB Total Assets | B7: $64,188M | C7: ATB Annual Report FY2025 | D7: p.20 Financial Position table | E7: FY2025 | F7: Up 6.3% YoY
A8: ATB Wealth AUA | B8: $37,166M | C8: ATB Annual Report FY2025 | D8: p.20 Other information | E8: FY2025 | F8: Up 30.2% YoY (incl BCV acquisition)
A9: ATB Total Revenue | B9: $2,187M | C9: ATB Annual Report FY2025 | D9: p.19 Operating results | E9: FY2025 | F9: Record, up 8.0% ($162M increase)
A10: ATB Net Income | B10: $347.6M | C10: ATB Annual Report FY2025 | D10: p.19 Operating results | E10: FY2025 | F10: Up from $336.8M
A11: ATB Total Clients | B11: 835,261 | C11: ATB Annual Report FY2025 | D11: p.20 Other information | E11: FY2025 | F11: Up from 814,140
A12: ATB Team Members | B12: 5,251 FTE | C12: ATB Annual Report FY2025 | D12: p.20 Other information | E12: FY2025 | F12: Stable from 5,238
A13: ATB New/Renewed Lending | B13: $29.1B | C13: ATB Annual Report FY2025 | D13: p.11 Business Highlights | E13: FY2025 | F13: Invested in Alberta growth
A14: ATB Mortgage Origination | B14: $4.4B | C14: ATB Annual Report FY2025 | D14: p.8 CEO Message | E14: FY2025 | F14: Up 42.0% YoY
A15: ATB Dividends Paid | B15: $100M | C15: ATB Annual Report FY2025 | D15: p.20 Other information | E15: FY2025 | F15: First-ever dividend to Province of Alberta
A16: ATB Tier 1 Capital Ratio | B16: 12.2% | C16: ATB Annual Report FY2025 | D16: p.20 Key performance measures | E16: FY2025 | F16: Down from 13.0% (post-dividend)
A18: (RESERVED 6TH STREAM - SOURCES)
A19: Per-FI conservative savings | B19: ATB $1.03M / Servus $683K / Vancity $659K / BVCU $24K per yr | C19: 4orm Per-Institution Conservative Savings workbook | D19: 186 institutions, 7 categories | E19: June 2026 | F19: Assumptions deflated below demo v2 cost model; all parameters sourced
A20: Savings TAM | B20: $20,330,371/yr | C20: Same workbook - By Tier sheet | D20: T1 $16.1M + T2 $2.9M + T3 $1.3M | E20: June 2026 | F20: 186 Canadian banks, CUs, trusts
A21: Capture rate (25%) | B21: 20-30% typical | C21: Gainshare / value-based pricing benchmarks | D21: Editable CP B139 | E21: 2026 | F21: Conservative midpoint of verified-savings contracts
A22: Regulated settlement precedent | B22: $3T+ cumulative, $5-7B/day | C22: JPM Kinexys | D22: demo-exchange.vercel.app/how-it-works.html | E22: Mid-2026 | F22: Proves tokenized settlement rail at institutional scale
A23: BoC Project Samara | B23: C$100M tokenized bond, instant settlement | C23: Bank of Canada / EDC / RBC / TD | D23: bankofcanada.ca (Mar 2026) | E23: Mar 2026 | F23: Canadian validation of DvP on dual ledger
A24: Methodology anchors | B24: ACSS 1.2-day float; FINTRAC 1.2% alert rate; SWIFT MT103 $0.15; CDS/DTCC 2.4% fail rate | C24: Savings workbook Methodology sheet | D24: Payments Canada / FINTRAC / SWIFT / CDS | E24: June 2026 | F24: Each assumption shows conservatism vs v2 model
A26: V9 ADDITIONAL SOURCES (Phased Build)
A27: Source | B27: URL | C27: Purpose
A28: CVCA H1 2025 Reports | B28: https://intelligence.cvca.ca/reports/venture-capital/ | C28: Canadian VC benchmarks
A29: CIRO Custody Framework Feb 2026 | B29: https://www.ciro.ca/newsroom/publications/notice-ciros-digital-asset-custody-framework | C29: Regulatory framework
A30: Alberta FIA Bill 13 / Sandbox | B30: https://www.alberta.ca/financial-services-and-fintech-regulatory-sandbox.aspx | C30: Sandbox admission
A31: Cybrid Series A | B31: https://betakit.com/cybrid-closes-10-million-usd-series-a-round-to-bring-stablecoins-to-the-business-mainstream/ | C31: Comparable
A32: Tetra Trust funding | B32: https://betakit.com/tetra-trust-parent-secures-backing-from-banks-fintech-to-launch-canadian-stablecoin-and-grow-beyond-crypto-custody/ | C32: Comparable
A33: Runway benchmarks 2026 | B33: https://runway.com/blog/burn-multiple-benchmarks-for-2026-what-good-looks-like-at-seed-to-scale | C33: Benchmark
A34: YC runway advice | B34: https://www.ycombinator.com/library/3Z-advice-for-companies-with-less-than-1-year-of-runway | C34: Runway advice
A36: V10 DEVEX + OPEX LINE-ITEM SOURCE VALIDATION
A37: # | B37: Category | C37: Line Item | D37: Amount / Rate | E37: Source URL | F37: Source Description / Date Verified
A38: 1 | B38: DevEx / SPEER | C38: SPEER Statement of Work (Phase 1-3) | D38: $317,304 CAD incl 13% HST | E38: Internal SPEER SoW document | F38: SPEER Engineering SoW dated 2026; deposit Sept 1 2026 + 12 monthly $19,831.50. Verified 2026-07-03.
A39: 2 | B39: DevEx / SPEER | C39: SPEER Phase 1: Discovery & Architecture | D39: $31,200 | E39: Internal SPEER SoW | F39: 1-2 months. Verified 2026-07-03.
A40: 3 | B40: DevEx / SPEER | C40: SPEER Phase 2: MVP Design & Dev | D40: $93,600 | E40: Internal SPEER SoW | F40: 3-5 months. Verified 2026-07-03.
A41: 4 | B41: DevEx / SPEER | C41: SPEER Phase 3: Continued Dev & Integration | D41: $156,000 | E41: Internal SPEER SoW | F41: 3-6 months. Verified 2026-07-03.
A42: 5 | B42: DevEx / SPEER | C42: HST 13% on SPEER contract | D42: $36,504 | E42: https://www.canada.ca/en/revenue-agency/services/tax/businesses/topics/gst-hst-businesses/charge-collect-which-rate.html | F42: Canadian federal HST rate 13% for Ontario-based services. Verified 2026-07-03.
A43: 6 | B43: DevEx / Internal | C43: Chain abstraction layer (internal build) | D43: $40,000 | E43: https://chainstack.com/pricing/ | F43: Internal infra estimate benchmarked vs Chainstack multi-chain RPC pricing. Verified 2026-07-03.
A44: 7 | B44: DevEx / Internal | C44: Smart contract dev (patent-differentiated) | D44: $30,000 H2 2026 | E44: https://ised-isde.canada.ca/site/canadian-intellectual-property-office/en/patents/patent-fees | F44: CIPO patent fees + internal dev. Verified 2026-07-03.
A45: 8 | B45: DevEx / Internal | C45: Alberta Sandbox admission prep | D45: $30K H2 2026 + $20K H1 2027 | E45: https://www.alberta.ca/financial-services-and-fintech-regulatory-sandbox.aspx | F45: Alberta Financial Services and Fintech Regulatory Sandbox program. Verified 2026-07-03.
A46: 9 | B46: DevEx / Legal | C46: Patent provisional filings | D46: $15,000 H2 2026 | E46: https://ised-isde.canada.ca/site/canadian-intellectual-property-office/en/patents/patent-fees | F46: CIPO patent fees + Smart Biggar / Bereskin Parr counsel estimate. Verified 2026-07-03.
A47: 10 | B47: DevEx / Security | C47: Smart contract audit (initial - Trail of Bits) | D47: $80,000 | E47: https://www.trailofbits.com/services/software-assurance/blockchain/ | F47: Trail of Bits blockchain assurance rates. Verified 2026-07-03.
A48: 11 | B48: DevEx / Security | C48: Smart contract audit (annual re-audit) | D48: $25,000/half | E48: https://www.trailofbits.com/services/software-assurance/blockchain/ | F48: Ongoing quarterly/annual re-audit budget. Verified 2026-07-03.
A49: 12 | B49: DevEx / Security | C49: Penetration testing (initial) | D49: $40,000 | E49: https://bulletproofsi.com/it-security/ | F49: Bulletproof Solutions Inc. Canadian pentest rates. Verified 2026-07-03.
... A81: 44 | B81: Legal / Regulatory | C81: Stikeman Elliott regulatory practice | D81: Reference | E81: https://stikeman.com/en-ca/services/regulatory-crown-corporations | F81: Canadian regulatory practice benchmark. Verified 2026-07-03.

Sheet Formula Reference
A1: 4ORM FINANCE - FORMULA REFERENCE GUIDE
A2: Complete reference for every formula pattern used in this model | All values in CAD
A4: REVENUE FORMULAS (Revenue Model Sheet)
A5: Stream / Item | B5: Formula Pattern (English) | C5: Example Cell Reference | D5: Notes
A6: Settlement Fees | B6: FI Toggle × Stream Toggle × Deposits ($M) × 1,000,000 × Turnover (5x) × Token Rate (1%) × Fee Rate (1.5 bps) × Split (30%) × Ramp × Growth^(periods/2) × 0.5 | C6: cp!$b$14 × CP!$B$6 × CP!B49 × 1000000 × CP!$B$29 × CP!$B$27 × CP!$B$41 × CP!$C$41 × CP!B$56 × (1+CP!$B$30)^MAX(0,(p-start)/2) × 0.5 | D6: Deposit-based. 5x turnover converts deposits to settlement volume. Semi-annual (×0.5).
A7: Issuance Fees | B7: FI Toggle × Stream Toggle × Lending ($M) × 1,000,000 × Token Rate (1.5%) × Fee Rate (0.5%) × Split (60%) × Ramp × Growth^(periods/2) × 0.5 | C7: cp!$b$14 × CP!$B$7 × CP!C49 × 1000000 × CP!$B$28 × CP!$B$42 × CP!$C$42 × ramp × growth × 0.5 | D7: Lending-based. 1.5% of lending tokenized, 0.5% issuance fee.
A8: Trading Fees | B8: FI Toggle × Stream Toggle × Lending ($M) × 1,000,000 × Token Rate (1.5%) × Trading Vol % (40%) × Fee Rate (5 bps) × Split (100%) × Ramp × Growth × 0.5 | C8: cp!$b$14 × CP!$B$8 × CP!C49 × 1M × CP!$B$28 × CP!$B$62 × CP!$B$43 × CP!$C$43 × ramp × growth × 0.5 | D8: 40% of issuance volume trades on secondary market. 4ORM keeps 100%.
A9: Custody Fees | B9: FI Toggle × Stream Toggle × AUA ($M) × 1,000,000 × Token Rate (1.5%) × Fee Rate (30 bps) × Split (40%) × Ramp × Growth × 0.5 | C9: cp!$b$14 × CP!$B$9 × CP!D49 × 1M × CP!$B$28 × CP!$B$44 × CP!$C$44 × ramp × growth × 0.5 | D9: AUA-based. 1.5% of AUA tokenized, 30 bps annual custody fee.
A10: SaaS + APIs | B10: FI Toggle × Stream Toggle × Enterprise Clients × Annual SaaS Rate × Split (80%) × Ramp × 0.5 | C10: cp!$b$14 × CP!$B$10 × CP!E49 × CP!$B$45 × CP!$C$45 × ramp × 0.5 | D10: No growth factor. Flat rate per enterprise client. Annual rate halved for semi-annual.
A11: (reserved) | B11: Toggle × TAM ($B) × 1,000,000,000 × Market Share × Fee Rate (0.15%) × 0.5 | C11: cp!$b$11 × CP!B(tam_row) × 1e9 × CP!C(tam_row) × CP!$B$63 × 0.5 | D11: Market-level calculation. TAM and market share vary by period.
A12: Growth Factor | B12: (1 + Annual Growth Rate) ^ MAX(0, (period_index - start_period) / 2) | C12: (1+cp!$b$30)^MAX(0,(3-1)/2) = (1.04)^1 = 1.04 for period 3 starting period 1 | D12: Compounding is annual, applied to half-year periods. Division by 2 ensures annual rate.
A14: P&L FORMULAS (5-Year P&L Summary Sheet)
A15: Line Item | B15: Formula Pattern | C15: Reference | D15: Notes
A16: Revenue Lines | B16: Each stream pulls from Revenue Model stream breakdown section (ALL FIs summed) | C16: 'revenue model'!{col}{row} - green font = cross-sheet reference | D16: P&L col B = Revenue Model col C (offset +1 in columns)
A17: Total Revenue | B17: Sum of all 6 revenue stream rows | C17: B6+B7+B8+B9+B10+B11 | D17: Settlement + Issuance + Trading + Custody + SaaS + (reserved)
A18: Total DevEx | B18: References DevEx sheet total row directly | C18: 'devex - build costs'!{col}{row} | D18: P&L col B → DevEx col C (offset +1). Green font.
A19: Total OpEx | B19: References OpEx sheet total row directly | C19: 'opex - ongoing'!{col}{row} | D19: P&L col B → OpEx col C (offset +1). Green font.
A20: Total All Expenses | B20: Total DevEx + Total OpEx | C20: B(devex_row)+B(opex_row) | D20: Red font indicates expense total.
A21: Net Profit (Loss) | B21: Total Revenue - Total All Expenses | C21: B(rev_row)-B(exp_row) | D21: Double border. Bold 11pt.
A22: Net Margin % | B22: IF(Revenue=0, 0, Net Profit / Revenue) | C22: IF(B12=0,0,B22/B12) | D22: Shows profitability per period.
A23: Cumulative Net Income | B23: Running total: first period = Net Profit, subsequent = previous cumulative + current Net Profit | C23: B(prev_row)+c(net_row) | D23: Shows when the business reaches breakeven.
A25: KEY CONTROL PANEL REFERENCES
A26: Parameter | B26: Cell Reference | C26: Default Value | D26: Description
A27: Stream Toggles | B27: B6:B11 | C27: 1 (all ON) | D27: Enable/disable individual revenue streams
A28: FI Toggles | B28: B14:B17 | C28: 1 (all ON) | D28: Enable/disable individual financial institutions
A29: Deposit Tokenization | B29: B27 | C29: 1.0% | D29: Percentage of FI deposits tokenized
A30: Issuance/Custody Token | B30: B28 | C30: 1.5% | D30: Percentage of lending/AUA tokenized
A31: Turnover Multiplier | B31: B29 | C31: 5x | D31: Annual deposit turnover for settlement volume
A32: Annual Growth | B32: B30 | C32: 4.0% | D32: Conservative YoY growth rate
A33: Fee Rates | B33: B41:B45 | C33: Varies | D33: Fee rate per stream
A34: Fee Splits | B34: C41:C45 | C34: 30-100% | D34: 4ORM revenue share per stream
A35: FI Data | B35: B49:F52 | C35: Varies | D35: Deposits, lending, AUA, clients, start period
A36: Ramp Schedule | B36: B56:L59 | C36: 0-1.0 | D36: 11-period onboarding ramp (0=off, 0.5=ramp, 1=full)
A38: SEMI-ANNUAL CONVERSION NOTES
A40: All annual volumes are divided by 2 (×0.5) for each semi-annual period.
A41: Growth is applied per year elapsed: (1+g)^(periods_elapsed/2). Period 0 = H2 2026, Period 1 = H1 2027, etc.
A42: FI Start Period: ATB=1 (H1 2027), BVCU=1 (H1 2027), Servus=3 (H1 2028), Vancity=3 (H1 2028). Ramp at 50% first half, 100% thereafter.
A43: SaaS revenue has NO growth factor - it's a flat rate per enterprise client, scaled by ramp only.
A44: (reserved) uses market-level TAM × market share × fee, NOT per-FI. TAM and share are set per period on Control Panel.
A46: M2-ADJUSTED GROWTH RATES
A47: Parameter | B47: Formula Pattern | C47: Example | D47: Notes
A48: Per-FI Growth Rate | B48: IF(Use_Custom=1, Custom_Rate, Global_Rate) | C48: IF(CP!$D$90=1, CP!$C$90, CP!$B$30) | D48: Each FI can override the global 4% growth with its own M2-correlated rate
A49: Effective M2 Rate | B49: M2 Growth Rate × FI Correlation Factor | C49: 5.7% × 0.75 = 4.275% (ATB Base Case) | D49: M2 scenarios: Bear 2%, Base 5.7%, Bull 9.85%. ATB corr ~0.75
A50: Growth in Revenue | B50: Revenue formula growth factor becomes: (1 + per_FI_growth)^(periods/2) | C50: If ATB custom=6.8%: (1.068)^1 = 1.068 vs default (1.04)^1 = 1.04 | D50: ~70% more growth with M2-adjusted rate. Toggle "Use Custom" to switch.
A52: TOKENIZATION PENETRATION RAMP
A53: Parameter | B53: Formula Pattern | C53: Example | D53: Notes
A54: Deposit Token Rate | B54: IF(Use_Ramp=1, per_period_deposit_%, flat_1%) | C54: IF(CP!$B$100=1, CP!B$98, CP!$B$27) | D54: Default ramp: 1% (2027) → 2% (2028) → 3% (2029) → 4% (2030) → 5% (2031). Set toggle=0 for flat 1%.
A55: Issuance/Custody Token Rate | B55: IF(Use_Ramp=1, per_period_issuance_%, flat_1.5%) | C55: IF(CP!$B$100=1, CP!B$99, CP!$B$28) | D55: Default ramp: 1.5% (2027) → 3% (2028) → 4.5% (2029) → 6% (2030) → 7.5% (2031). Tracks 1.5x deposit rate.
A56: Settlement Formula (Updated) | B56: FI_Toggle × Stream_Toggle × Deposits$M × 1M × Turnover × IF(Ramp, period_dep_%, flat_1%) × Fee × Split × Ramp × Growth × 0.5 | C56: Deposit token rate now scales per period instead of fixed 1% | D56: With ramp ON: 5% tokenization in 2031 = 5x the Year 1 volume on same deposit base
A57: Impact on Revenue | B57: Ramp ON dramatically increases Year 3-5 revenue as tokenization penetration scales from 1% to 5% | C57: Year 5 at 5% deposit token = 5x settlement volume vs flat 1%. Issuance/custody at 7.5% = 5x custody/issuance. | D57: Consistent with McKinsey 75% CAGR forecast and JPM Kinexys 10x YoY growth trajectory.
A59: NON-DILUTIVE CAPITAL / GRANTS FORMULAS
A60: Item | B60: Formula Pattern | C60: Cell Reference | D60: Description
A61: Grant Toggle | B61: IF(B{toggle_row}=1,"ON","OFF") | C61: Control Panel C114+ | D61: Each grant has ON/OFF toggle (1/0) in column B
A62: Grant Period Amount | B62: Editable input (yellow) | C62: Control Panel C-M rows 126-133 | D62: User-editable funding amount per semi-annual period
A63: Grant Total (per period) | B63: SUM of (amount × toggle) for all grants | C63: Control Panel C-M row 134 | D63: Sums only toggled-ON grant amounts for each period
A64: P&L Grant Income | B64: 'Control Panel'!{col}134 | C64: P&L row 14 | D64: Pulls total toggled grant income from Control Panel
A65: P&L Total Rev + Grants | B65: Revenue + Grant Income | C65: P&L row 15 | D65: Total Revenue (row 12) + Grant Income (row 14)
A66: P&L Net Profit | B66: (Revenue + Grants) - Expenses | C66: P&L row 25 | D66: Now includes non-dilutive capital in net calculation
A67: Summary Grant Rows | B67: Toggle × Period Amount (per grant) | C67: Summary rows 67-74 | D67: Each grant shown separately with toggle-aware formula
A68: Key Metrics update | B68: Net Income now includes grants | C68: Summary B6, B7, B8, B10 | D68: 5-Year figures now reflect grant income in totals
A70: V8 - SAVINGS SHARE STREAM & TOGGLE WIRING
A71: Savings Share revenue | B71: FI Toggle x Stream Toggle (CP B138) x Annual Savings (CP B140-143) x Capture % (CP B139) x Ramp x Growth x 0.5 | C71: Revenue Model rows 51-54 | D71: Same ramp/growth pattern as other streams; semi-annual x0.5
A72: Savings subtotal | B72: Sum of 4 FI savings-share rows | C72: Revenue Model row 55 | D72: Flows into TOTAL REVENUE row 58 and breakdown row 68
A73: P&L stream line | B73: Pulls Revenue Model row 68 | C73: P&L row 12 | D73: TOTAL REVENUE (row 13) includes it
A74: Scenario switch (P&L) | B74: IF(CP B20=1, the platform Build total, Traditional total) | C74: P&L rows 19 & 22 | D74: Master the platform Build/Traditional toggle drives the P&L
A75: SPEER gating | B75: Constant x CP toggle (B22 / B23) | C75: DevEx rows 6-10 | D75: HST = 13% of toggled phases
A76: SR&ED gating | B76: Credit x CP B24 | C76: OpEx row 37 | D76: Negative expense only when ON
A77: Team comp link | B77: Links to Team Roadmap row 38 x (1+CP B36)^years | C77: OpEx row 6 / Roadmap row 38 | D77: Escalation now applied; stale hardcodes removed

Sheet Pre-Seed Deployment
A1: 4ORM FINANCE - PRE-SEED DEPLOYMENT PLAN
A2: ="$" & TEXT('Control Panel'!B147,"#,##0") & " CAD | 15-Month Runway | " & TEXT('Control Panel'!B150,"0%") & " Reserve ($" & TEXT('Control Panel'!B147*'Control Panel'!B150,"#,##0") & ")"
A4: USE OF PROCEEDS
A5: Category | B5: Amount CAD | C5: % of $3.5M | D5: Notes
A6: Team (comp + 18% benefits) | B6: =D28 | C6: =B6/'Control Panel'!$B$147 | D6: 7 employees + 3 advisor retainers + fractional CFO. 15 months post-close.
A7: Legal | B7: 200000 | C7: =B7/'Control Panel'!$B$147 | D7: Securities counsel, unit offering, IP, MOUs (tightened from prior estimate)
A8: Compliance advisory | B8: 150000 | C8: =B8/'Control Panel'!$B$147 | D8: Alberta Sandbox prep, CIRO framework advisory
A9: Product / DevEx | B9: 492000 | C9: =B9/'Control Panel'!$B$147 | D9: SPEER $317K + Chain abstraction $40K + Patent SC $30K + Sandbox prep $50K + Token opinion $30K + Provincial reg $10K + Patent filings $15K
A10: BD + travel | B10: 140000 | C10: =B10/'Control Panel'!$B$147 | D10: Bank counterparty motion, MOUs, conferences (tightened)
A11: G&A | B11: 124000 | C11: =B11/'Control Panel'!$B$147 | D11: Office, D&O insurance, accounting, tools (tightened)
A12: Reserve / contingency | B12: ='Control Panel'!B147*'Control Panel'!B150 | C12: =B12/'Control Panel'!$B$147 | D12: 25% reserve per policy - 4-5 months buffer
A13: TOTAL | B13: =SUM(B6:B12) | C13: =SUM(C6:C12)
A15: TEAM CASH COMP DETAIL (15 MONTHS POST-CLOSE)
A16: Role | B16: Cash Comp | C16: Benefits (18%) | D16: Total
A17: Chad (CEO) @ $8K/mo | B17: 120000 | C17: 21600 | D17: 141600
A18: CTO (Phase 1 hire) @ $15K/mo | B18: 225000 | C18: 40500 | D18: 265500
A19: Zed (Head Architect) | B19: 212500 | C19: 38250 | D19: 250750
A20: Smart Contract Dev | B20: 181250 | C20: 32625 | D20: 213875
A21: Backend Dev | B21: 181250 | C21: 32625 | D21: 213875
A22: DevOps 0.5 FTE | B22: 70000 | C22: 12600 | D22: 82600
A23: Exec Asst / Ops 0.5 FTE | B23: 30000 | C23: 5400 | D23: 35400
A24: Kevin (CMO PT) @ $4K/mo | B24: 60000 | C24: 0 | D24: 60000
A25: Bruce (Advisor via Mench) @ $6K/mo | B25: 90000 | C25: 0 | D25: 90000
A26: Dean (Advisor) @ $5K/mo | B26: 75000 | C26: 0 | D26: 75000
A27: Fractional CFO @ $6K/mo | B27: 90000 | C27: 0 | D27: 90000
A28: SUBTOTAL | B28: =SUM(B17:B27) | C28: =SUM(C17:C27) | D28: =SUM(D17:D27)
A29: MATH CHECK: Team $1,519K + DevEx $492K + Legal $200K + Compliance $150K + BD $140K + G&A $124K = $2,625K operating
A30: Operating $2,625K + Reserve $875K = $3,500K total pre-seed | B30: $125,000 / mo
A31: With reserve drawn | B31: $167,000 / mo
A32: MONTHLY BURN | B32: 18 months
A33: Operating burn (excl. reserve) | B33: $175,000 / mo
A34: With reserve drawn | B34: $233,000 / mo
A35: Runway (op-ex only) | B35: 15 months
A36: Runway (drawing reserve) | B36: 20 months
A37: [ ] ATB testnet integration live
A38: SIGNAL FOR SEED UNLOCK - CHECKLIST
A39: [ ] Alberta Sandbox admission
A40: [ ] ATB testnet integration live
A41: [ ] 2 additional bank MOUs signed
A42: [ ] SPEER Phase 1+2 production-ready
A43: [ ] CIRO framework compliance verified
A44: [ ] $500K-$1M ARR pipeline documented

Sheet Seed Round Sizing
A1: 4ORM FINANCE - SEED ROUND SIZING
A2: Scenario planning for Seed round (H1 2028 target close, 15 months post-Seed to product-in-market)
A4: SCENARIO COMPARISON
A5: Scenario | B5: Raise | C5: Pre-Money | D5: Post-Money | E5: Dilution | F5: Runway (mo)
A6: Conservative | B6: 10000000 | C6: 22000000 | D6: 32000000 | E6: 0.313 | F6: 20
A7: Base | B7: 15000000 | C7: 30000000 | D7: 45000000 | E7: 0.333 | F7: 24
A8: Aggressive | B8: 20000000 | C8: 40000000 | D8: 60000000 | E8: 0.333 | F8: 24
A9: Stretch | B9: 25000000 | C9: 50000000 | D9: 75000000 | E9: 0.333 | F9: 30
A10: Series-A profile | B10: 30000000 | C10: 70000000 | D10: 100000000 | E10: 0.3 | F10: 36
A13: BASE CASE ($15M) DEPLOYMENT
A14: Category | B14: Amount | C14: % of $15M
A15: Product / Engineering | B15: 5250000 | C15: 0.35
A16: Regulatory / Compliance | B16: 2250000 | C16: 0.15
A17: GTM / BD | B17: 2250000 | C17: 0.15
A18: Team scale (Phase 2) | B18: 3000000 | C18: 0.2
A19: Reserve | B19: 2250000 | C19: 0.15
A20: TOTAL | B20: =SUM(B15:B19) | C20: =SUM(C15:C19)
A22: COMPARABLES ANCHORING
A23: Company | B23: Round | C23: Details | D23: Notes
A24: Cybrid (Toronto, stablecoin infra) | B24: Seed to Series A | C24: $3.8M CAD seed (Apr 2022, Golden lead) to $10M USD Series A (2025, BDC Capital Growth Venture Fund lead) | D24: Closest direct Canadian precedent for a regulated fintech infrastructure seed-to-A trajectory
A25: Tetra Trust (Calgary, digital custodian) | B25: Multi-round | C25: ~$15M CAD total equity across rounds + $10M CAD parent stablecoin round (2025) | D25: Anchor backers: ATB Financial, National Bank of Canada, Wealthsimple, Coinbase Ventures. Canada's first qualified digital asset custodian.
A26: Balance Trust (Toronto, digital custodian) | B26: Regulatory launch | C26: $10M CAD parent committed regulatory capital (Oct 2024) | D26: Canada's second qualified digital asset custodian. No external round for trust launch.
A27: Ondo Finance (US, RWA tokenization) | B27: Seed | C27: $4M USD (Aug 2021) at ~$130M USD post-money. Pantera + DCG lead | D27: 2021 US environment; discount ~65-75% for Canadian 2026
A28: Fnality (UK, wholesale settlement) | B28: Series B / C | C28: $95M USD Series B (Nov 2023, Goldman + BNP lead) + $133M USD Series C (Sept 2025) | D28: Global bank-institutional analog to 4orm. Later-stage benchmark.
A29: BondbloX (Singapore, bond tokenization) | B29: Series A / B | C29: ~$12M USD total across A ($6M Jun 2021) and B ($6M Nov 2023) | D29: Uses Hyperledger Sawtooth.
A30: Sources: BetaKit, Crunchbase, Fintech Futures, PitchBook, Tracxn.
A32: VALUATION STEP-UP
A33: Pre-Seed pre-money: $10M CAD
A34: Seed pre-money (Base case): $30M CAD
A35: Step-up multiple: 3.0x
A36: Note: Cybrid trajectory suggests ~2.5-3x is achievable for validated Canadian regulated fintech; Tetra Trust and Balance Trust show that bank co-invest is available if the signal is strong.
A37: SEED UNLOCK SIGNAL - CHECKLIST
A38: [ ] Alberta Sandbox admission
A39: [ ] ATB testnet integration live
A40: [ ] 2 additional bank MOUs signed
A41: [ ] SPEER Phase 1+2 production-ready
A42: [ ] CIRO framework compliance verified
A43: [ ] $500K-$1M ARR pipeline documented

Sheet Non-Dilutive Capital
A1: 4ORM FINANCE - NON-DILUTIVE CAPITAL STACK
A2: Grants, tax credits, and advance-financing programs supporting the 4orm build
A4: ACCESSIBLE NOW
A5: SR&ED (Federal) | B5: $150K-$300K / yr | C5: 35% refundable on qualifying R&D, up to $3M CCPC ceiling
A6: Alberta Innovation Employment Grant | B6: $50K-$100K / yr | C6: 8% base + 12% incremental; stacks with SR&ED
A7: NRC IRAP contribution funding | B7: $100K-$500K project | C7: Up to 80% of eligible labour; project-based
A8: CDAP Boost Your Business Technology Grant | B8: $15,000 CAD | C8: Federal Canada Digital Adoption Program. Grant for digital adoption plan. Low application effort (~40 hours). No R&D matching required. Trivial for scale but real cash. Timing: 30-60 days from application.
A9: BC Small Business Venture Capital Tax Credit (SBVCTC) | B9: Investor-side benefit | C9: 30% tax credit for BC-resident investors up to $200K per investor per year on eligible BC small business investments. Makes 4orm unit offering ~30% more attractive to BC angels. Verify eligibility for Bruce Fair (BC), Kevin Wong (verify province), Don Hickling (verify province). Real capital-raising lever. Timing: Immediate (at time of investment).
A10: PrairiesCan (RIE / BSP) | B10: $250,000 to $1,000,000 CAD | C10: PrairiesCan (Prairies Economic Development Canada) non-repayable contributions for innovation and commercialization. Two programs relevant to 4orm: (1) Regional Innovation Ecosystems (RIE) up to $500K for tech scale-up; (2) Business Scale-Up and Productivity (BSP) up to $10M repayable but with soft terms for high-growth tech. Not tied to R&D dollar match. Alberta-based Calgary HQ is eligible. Application effort ~$20K prep + 4-6 month cycle. Timing: 6-12 months from application.
A12: REQUIRES R&D FIRST
A13: SR&ED filings need eligible technical activity in the tax year
A14: IEG stacks with SR&ED - both require documented eligible R&D labour
A16: ADVANCE FINANCING (SR&ED-backed)
A17: Providers: Boast, Easly, Venbridge
A18: Terms: 60-75% advance on projected SR&ED; monthly draws; ~1.5-2.5% monthly financing cost
A20: NOT AVAILABLE
A21: AITC (Alberta Investor Tax Credit) - program ended 2019
A22: Federal Angel ITC - not enacted
A24: PROJECTED 5-YEAR NON-DILUTIVE STACK
A25: Year | B25: Amount | C25: Notes
A26: Yr1 (2026-27) | B26: 50000 | C26: IRAP + Mitacs during pre-seed
A27: Yr2 (2027-28) | B27: 200000 | C27: First SR&ED claim + IRAP scale
A28: Yr3 (2028-29) | B28: 400000 | C28: SR&ED + IEG + IRAP full-stack
A29: Yr4 (2029-30) | B29: 500000 | C29: Mature R&D pipeline
A30: Yr5 (2030-31) | B30: 600000 | C30: Continued SR&ED + IEG scale
A31: 5-YR TOTAL | B31: =SUM(B26:B30)
A33: KEY MESSAGE
A34: The non-dilutive stack materially extends seed runway and reduces future dilution.
A35: It is NOT counted in the $3M pre-seed use of proceeds - treat as upside to base plan.
